Workbook
Name IQ_CH: 110000
Name IQ_CQ: 5000
Name IQ_CY: 10000
Name IQ_DAILY: 500000
Name IQ_FH: 100000
Name IQ_FQ: 500
Name IQ_FY: 1000
Name IQ_LTM: 2000
Name IQ_MONTH: 15000
Name IQ_NTM: 6000
Name IQ_WEEK: 50000
Name IQ_YTD: 3000

Sheet SystemsList
B1: *Click on system name to go to the sheet
A2: No. of fields | B2: *Systems List | C2: Hosted in RAKBANK? Can Data be fetched through Databricks or Can be exposed via API? | D2: Appln type | E2: Vendor | F2: Vendor Spoc | G2: Vendor contact | H2: Phone | I2: Technology Owner | J2: Engineering SME | K2: PM | L2: BA | M2: Architect | N2: Technology owner lead | O2: Application link | P2: Remarks
A3: 1184 | B3: Finacle | C3: In Data Platform Scope | D3: ThirdParty | E3: Infosys | F3: Amruta Anil Wadke | G3: Amruta.Wadke@rakbank.ae | I3: Mani John | J3: Sathiyan Venkatesh | N3: Sumat Kumar
A4: 335 | B4: Prime | C4: In Data Platform Scope | D4: ThirdParty | E4: TSYS | F4: Mohamed Sukkari Muhammed Ajmal | G4: mohamedsukkari@tsys.com majmal@tsys.com | H4: (050) 2100680 | I4: Sree Rasmi Shaik Hussain Shariff | J4: Shaik Hussain Shariff | L4: Kanhai Kumar Jha | M4: Ravish Kumar | N4: Gavin Stead
A5: 197 | B5: WMS | C5: In Data Platform Scope | D5: ThirdParty | E5: Infosys | F5: Aditya Kulkarni | G5: Aditya.Kulkarni@rakbank.ae | I5: Mani John | J5: Sathiyan Venkatesh | N5: Sumat Kumar
A6: 190 | B6: RLS | C6: In Data Platform Scope | D6: ThirdParty | E6: Nucleus Software | F6: Kaushal.misra@nucleussoftware.com | G6: Kaushal.misra@nucleussoftware.com | H6: 0091 9810617822 | I6: Mani John | J6: Sathiyan Venkatesh | N6: Sumat Kumar
A7: 74 | B7: CASMEX | C7: In Data Platform Scope | D7: ThirdParty | E7: Distinct Infotech | F7: rajeshkumar.rn@distinctinfotech.com chacko@distinctinfotech.com | G7: rajeshkumar.rn@distinctinfotech.com chacko@distinctinfotech.com | I7: Guruprasad Narayan Shetty | J7: Sathiyan Venkatesh | N7: Sumat Kumar
A8: 73 | B8: IDD | D8: Internal | E8: NA | F8: NA | G8: NA | I8: Gaurav Kumar | J8: Sathiyan Venkatesh | N8: Sumat Kumar
A9: 64 | B9: ICCS - Cheque Flow System | C9: In Data Platform Scope | D9: ThirdParty | E9: NewGen technologies | F9: Anshu Raj | G9: anshu.raj@newgensoft.com | H9: 0091 9971211909 | I9: Guruprasad Narayan Shetty | J9: Sathiyan Venkatesh | N9: Sumat Kumar
A10: 48 | B10: Previous RAKNet Version (Personal Banking) | D10: Internal | E10: NA | F10: NA | G10: NA | I10: Gaurav Kumar | J10: Sathiyan Venkatesh | N10: Sumat Kumar
A11: 48 | B11: Digital Banking Admin | C11: In Data Platform Scope | D11: ThirdParty | E11: Infosys | F11: Saranya | G11: @Saranya Devi Sankarappan (Ext) | I11: Milind Harichandra Gowari | J11: Sathiyan Venkatesh | N11: Lalit Lekhwani
A12: 41 | B12: Pay Hub Plus (NPSS Unity) | D12: ThirdParty | E12: Unity | F12: Veena Vijayan | G12: Veena.Kochattil@rakbank.ae | I12: Guruprasad Narayan Shetty | J12: Sathiyan Venkatesh | N12: Sumat Kumar
A13: 33 | B13: CCM | D13: ThirdParty | E13: Dtech | F13: Muhammed Anees | G13: Muhammed.anees@dtechsoft.com | H13: (054) 4922546 | I13: Mani John | J13: Sathiyan Venkatesh | N13: Sumat Kumar
A14: 32 | B14: CPF | C14: In Data Platform Scope | D14: Internal | E14: NA | F14: NA | G14: NA | I14: Mani John | J14: Sathiyan Venkatesh | N14: Sumat Kumar
A15: 31 | B15: RAKRewards Admin | D15: ThirdParty | E15: ICC | F15: ayush@iccfze.com abhilasha@iccfze.com | G15: ayush@iccfze.com abhilasha@iccfze.com | H15: +971-52-8059072 | I15: Gaurav Kumar | J15: Sathiyan Venkatesh | L15: Kanhai Kumar Jha | M15: Ravish Kumar | N15: Sumat Kumar
A16: 29 | B16: Bank Auth Representative E-Register(auth rep) | D16: Internal | E16: NA | F16: NA | G16: NA | I16: Gaurav Kumar | J16: Sathiyan Venkatesh | N16: Sumat Kumar | O16: Need to check application name
A17: 27 | B17: MDES (PRIME) | D17: ThirdParty | E17: Not Identified
A18: 25 | B18: Cheque Book System | D18: Internal | E18: NA | F18: NA | G18: NA | I18: Gaurav Kumar | J18: Sathiyan Venkatesh | N18: Sumat Kumar
A19: 25 | B19: Cross Sell | D19: ThirdParty | E19: pennanttech | F19: prasad.s@pennanttech.com venkatesh.ch@pennanttech.com | G19: prasad.s@pennanttech.com venkatesh.ch@pennanttech.com | H19: Prasad -917893940697 Venkatesh - 916305949549 | I19: Balaji Natarajan | J19: ? | N19: Sumat Kumar
A20: 24 | B20: Intellect Collection | C20: In Data Platform Scope | D20: ThirdParty | E20: Intellect Design | F20: mallikarjuna.chevvu@intellectdesign.com chelliah.p@intellectdesign.com | G20: mallikarjuna.chevvu@intellectdesign.com chelliah.p@intellectdesign.com | H20: =91-8939838656 -> -8939838565 | I20: Mani John | J20: Sathiyan Venkatesh | N20: Sumat Kumar
A21: 22 | B21: Digital ON-Boarding Tracking (DEH) | C21: In Data Platform Scope | D21: ThirdParty | E21: Infosys | F21: Ayesha Siddikha | G21: @Ayesha Siddikha Mohamed Iqbal (Ext) | I21: Milind Harichandra Gowari | J21: Sathiyan Venkatesh | N21: Lalit Lekhwani
A22: 20 | B22: CPPS | C22: In Data Platform Scope | D22: Internal | E22: NA | F22: NA | G22: NA | I22: Sree Rasmi Shaik Hussain Shariff | J22: Shaik Hussain Shariff | L22: Kanhai Kumar Jha | M22: Ravish Kumar | N22: Gavin Stead
A23: 16 | B23: VISA Online | D23: ThirdParty | E23: Not Identified
A24: 16 | B24: RAKTRACK | D24: ThirdParty | E24: Game Change | F24: Shailesh Tiwari | G24: shailesh.tiwari@gamechangesns.com | H24: (050) 4595618 | I24: Mani John | J24: Sathiyan Venkatesh | N24: Sumat Kumar
A25: 14 | B25: 3D Secure | D25: ThirdParty/Internal | E25: Broadcom | F25: Konrad Karczmarczyk | G25: konrad.karczmarczyk@broadcom.com | I25: Guruprasad Narayan Shetty | J25: Sathiyan Venkatesh | N25: Sumat Kumar
A26: 13 | B26: Team Express Portal | C26: External systems. Data cannot be ingested and can be fetched through API | D26: ThirdParty | E26: Team Express | I26: Mahesh Kannan | J26: Mahesh Kannan | N26: Mahes Kannan
A27: 11 | B27: Infobip | C27: External systems. Data cannot be ingested and can be fetched through API | D27: ThirdParty | E27: Infobip | F27: Edita Rokša Durić <edita.roksaduric@infobip.com>; Neira Kratovac Akriche <neira.kratovacakriche@infobip.com>; Nedžad Grizović <nedzad.grizovic@infobip.com> | G27: Edita Rokša Durić <edita.roksaduric@infobip.com>; Neira Kratovac Akriche <neira.kratovacakriche@infobip.com>; Nedžad Grizović <nedzad.grizovic@infobip.com> | I27: Mani John | J27: Sathiyan Venkatesh | N27: Sumat Kumar
A28: 10 | B28: IBPS | C28: In Data Platform Scope | D28: ThirdParty | E28: NewGen technologies | F28: Anshu Raj | G28: anshu.raj@newgensoft.com | H28: 0091 9971211909 | I28: Gaurav Kumar | J28: Sathiyan Venkatesh | N28: Sumat Kumar
A29: 10 | B29: Prospect | D29: Internal | E29: NA | F29: NA | G29: NA | I29: Gaurav Kumar | J29: Sathiyan Venkatesh | N29: Sumat Kumar
A30: 9 | B30: CardNet | D30: Internal | E30: NA | F30: NA | G30: NA | I30: Sree Rasmi Shaik Hussain Shariff | J30: Shaik Hussain Shariff | N30: Sumat Kumar
A31: 8 | B31: VAT | D31: Internal | E31: NA | F31: NA | G31: NA | I31: Gaurav Kumar | J31: Sathiyan Venkatesh | N31: Sumat Kumar
A32: 7 | B32: CAPS | C32: In Data Platform Scope | D32: Internal | E32: NA | F32: NA | G32: NA | I32: Sree Rasmi Shaik Hussain Shariff | J32: Sathiyan Venkatesh | L32: Kanhai Kumar Jha | M32: Ravish Kumar | N32: Gavin Stead
A33: 5 | B33: RAKFLUX | D33: Internal | E33: NA | F33: NA | G33: NA | I33: Balaji Natarajan | J33: Sathiyan Venkatesh
A34: 5 | B34: Salary Application | C34: In Data Platform Scope | D34: Internal | E34: NA | F34: NA | G34: NA | I34: Gaurav Kumar | J34: Sathiyan Venkatesh | N34: Sumat Kumar
A35: 2 | B35: FX Rate Calculator | D35: Internal | I35: Mohammed Shoaib | J35: ?
A36: 3 | B36: DCR | D36: Internal | E36: NA | F36: NA | G36: NA | I36: Sree Rasmi Shaik Hussain Shariff | J36: Sathiyan Venkatesh | L36: Kanhai Kumar Jha | M36: Ravish Kumar | N36: Gavin Stead
A37: 2 | B37: Genesys/ EID/ UAEPASS | C37: External systems. Data can be fetched through API | D37: ThirdParty | E37: Al Futtaim | F37: Ghous Sayyed-External | G37: ghous.sayyed-external@alfuttaim.com | I37: Gaurav Kumar Mani John | J37: Sathiyan Venkatesh | N37: Sumat Kumar

Sheet Sheet2
E5: No. of fields | F5: CRM Source Systems List | G5: Vendor
E6: 1184 | F6: Finacle | G6: Infosys
E7: 335 | F7: Prime | G7: TSYS
E8: 197 | F8: WMS | G8: Infosys
E9: 190 | F9: RLS | G9: Nucleus Software
E10: 74 | F10: CASMEX | G10: Distinct Infotech
E11: 64 | F11: ICCS - Cheque Flow System | G11: NewGen technologies
E12: 48 | F12: Digital Banking Admin | G12: Infosys
E13: 41 | F13: Pay Hub Plus (NPSS Unity) | G13: Unity
E14: 33 | F14: CCM | G14: Dtech
E15: 27 | F15: MDES | G15: Master Card
E16: 24 | F16: RLS Collection | G16: Nucleus Software
E17: 22 | F17: Digital ON-Boarding Tracking (DEH) | G17: Infosys
... E23: 10 | F23: IBPS | G23: NewGen technologies

Sheet Remarks
A4: Application Type | B4: Remarks | C4: No. of fields | D4: *Systems List | E4: Approach | F4: Appln type | G4: Vendor | H4: Vendor Spoc | I4: Tech owner
A5: Third Party | B5: Procurement reached out | C5: 1184 | D5: Finacle | E5: In Data Platform Scope | F5: ThirdParty | G5: Infosys | H5: Amruta Anil Wadke | I5: Mani John
B6: Emailed on July 23rd | C6: 335 | D6: Prime | E6: In Data Platform Scope | F6: ThirdParty | G6: TSYS | H6: Mohamed Sukkari Muhammed Ajmal | I6: Sree Rasmi Shaik Hussain Shariff
B7: Procurement reached out | C7: 197 | D7: WMS | E7: In Data Platform Scope | F7: ThirdParty | G7: Infosys | H7: Aditya Kulkarni | I7: Mani John
B8: Emailed on July 25th | C8: 190 | D8: RLS | E8: In Data Platform Scope | F8: ThirdParty | G8: Nucleus Software | H8: Kaushal.misra@nucleussoftware.com | I8: Mani John
B9: Emailed on Jul 28th | C9: 74 | D9: CASMEX | E9: In Data Platform Scope | F9: ThirdParty | G9: Distinct Infotech | H9: rajeshkumar.rn@distinctinfotech.com chacko@distinctinfotech.com | I9: Guruprasad Narayan Shetty
B10: Emailed on Jul 28th | C10: 64 | D10: ICCS - Cheque Flow System | E10: In Data Platform Scope | F10: ThirdParty | G10: NewGen technologies | H10: Anshu Raj | I10: Guruprasad Narayan Shetty
B11: Procurement reached out | C11: 48 | D11: Digital Banking Admin | E11: In Data Platform Scope | F11: ThirdParty | G11: Infosys | H11: Amruta Anil Wadke | I11: Milind Harichandra Gowari
B12: Get confirmation from business | C12: 41 | D12: Pay Hub Plus (NPSS Unity) | F12: ThirdParty | G12: Unity | H12: Veena Vijayan | I12: Guruprasad Narayan Shetty
B13: Emailed on Jul 28th | C13: 33 | D13: CCM | F13: ThirdParty | G13: Dtech | H13: Muhammed Anees | I13: Mani John
B14: Contact to be provided by Procurement | C14: 27 | D14: MDES | F14: ThirdParty | G14: Not Identified
B15: Getting decommissioned. Need to refer intellect collection | C15: 24 | D15: RLS Collection | E15: In Data Platform Scope | F15: ThirdParty | G15: Nucleus Software | H15: Kaushal.misra@nucleussoftware.com | I15: Mani John
B16: Procurement reached out | C16: 22 | D16: Digital ON-Boarding Tracking (DEH) | E16: In Data Platform Scope | F16: ThirdParty | G16: Infosys | H16: Amruta Anil Wadke | I16: Milind Harichandra Gowari
B17: Contact to be provided by Procurement | C17: 16 | D17: VISA Online | F17: ThirdParty | G17: Not Identified
B18: Emailed on Jul 28th | C18: 16 | D18: RAKTRACK | F18: ThirdParty | G18: Game Change | H18: Shailesh Tiwari | I18: Mani John
B19: Get confirmation from business | C19: 14 | D19: 3D Secure | F19: ThirdParty/Internal | G19: Broadcom | H19: Konrad Karczmarczyk | I19: Guruprasad Narayan Shetty
B20: Contact to be provided by Procurement | C20: 13 | D20: Team Express Portal | F20: ThirdParty | G20: Not Identified
B21: Emailed on Jul 28th | C21: 11 | D21: Infobip | F21: ThirdParty | G21: Infobip | H21: Edita Rokša Durić <edita.roksaduric@infobip.com>; Neira Kratovac Akriche <neira.kratovacakriche@infobip.com>; Nedžad Grizović <nedzad.grizovic@infobip.com> | I21: Mani John
B22: Emailed on Jul 28th | C22: 10 | D22: IBPS | E22: In Data Platform Scope | F22: ThirdParty | G22: NewGen technologies | H22: Anshu Raj | I22: Gaurav Kumar
A23: Internal - CARDS platform | B23: ADO ticket created with CARDS platform - 400859 | C23: 20 | D23: CPPS | E23: In Data Platform Scope | F23: Internal | G23: CARDS Platform | H23: Sree Rasmi Shaik Hussai Sharif | I23: Gavin Stead
C24: 9 | D24: CardNet | F24: Internal
C25: 7 | D25: CAPS | E25: In Data Platform Scope | F25: Internal
C26: 3 | D26: DCR | F26: Internal
A27: Internal - Non cards applications | B27: Aligned Nilkanth and Sathiyan on Friday | C27: 73 | D27: IDD | F27: Internal | G27: Internal Applications | H27: Sathiyan Venkatesh | I27: Gaurav Kumar
C28: 48 | D28: Previous RAKNet Version (Personal Banking) | F28: Internal | I28: Gaurav Kumar
C29: 32 | D29: CPF | E29: In Data Platform Scope | F29: Internal | I29: Mani John
C30: 31 | D30: RAKRewards Admin | F30: Internal | I30: Gaurav Kumar
C31: 29 | D31: Bank Auth Representative E-Register(auth rep) | F31: Internal | I31: Gaurav Kumar
C32: 25 | D32: Cheque Book System | F32: Internal | I32: Gaurav Kumar
C33: 25 | D33: Cross Sell | F33: Internal | I33: Gaurav Kumar
C34: 10 | D34: Prospect | F34: Internal | I34: Gaurav Kumar
C35: 8 | D35: VAT | F35: Internal | I35: Gaurav Kumar
C36: 5 | D36: RAKFLUX | F36: Internal | I36: Balaji Natarajan
C37: 5 | D37: Salary Application | E37: In Data Platform Scope | F37: Internal | I37: Gaurav Kumar
C38: 14 | D38: 3D Secure | F38: Internal | I38: Guruprasad Narayan Shetty
C39: 2 | D39: FX Rate Calculator | F39: Internal | I39: Sunit Shetty

Sheet Status
N2: Isolated environment | O2: https://adb-4467010307787545.5.azuredatabricks.net/?o=4467010307787545
K3: source Type
A4: Tamanna comments | B4: Vendor | C4: *Systems List | D4: Milestone | E4: No. of fields | F4: No.of fields received | G4: Status | H4: Status as on Oct 20th | I4: Pending with | J4: RAG | K4: Integration Mechanism | L4: System Pipeline available | N4: IP UAT/Endpoint (Existing) | O4: UAT env (testing team) | P4: Business Owner | Q4: Technology Owner | R4: IP PROD | S4: IP DR | T4: DB Prod/Endpoint | U4: Peak CPU Utilization in Production Current | V4: Peak Memory Utilization | W4: DB name
A5: Have asked Mani | B5: Infosys | C5: Finacle | D5: M2,M3,M5,M7 | E5: 1184 | F5: 1069 | G5: In Progress | H5: Sep 19 - Received 834 fields as on 19/9. 341 to be shared. Alok reviewing the data. Oct 7 - 1069 data received - all 1to1 data fields | I5: Surabhi Alok Vendor | J5: Green | K5: Data Platform | L5: Yes | M5: ok | N5: 10.15.12.60, 5300 | O5: UAT2 | P5: Juzer Netterwala | Q5: Mani John | R5: 10.17.19.85/86:5300 | S5: 10.16.19.85/86:5300 | U5: 0.95 | V5: 0.6 | W5: Provided by source system team at field level
A6: Have asked Mani | B6: Infosys | C6: WMS | D6: M2, M6 | E6: 197 | F6: 118 | G6: In Progress | H6: Solution to be discussed for fields that has run time logical values Aditya - to clarify on fields marked as "Not applicable. Module is not licensed." Sep 26 - Surabhi scheduled meeting Oct 7 - BA followed up. NA items to be provided by vendor Discussion required on API development | I6: Dragos Vendor Alok, Surabhi | J6: Amber | K6: Data Platform + API? | L6: Yes | N6: 10.15.13.200,5301 | O6: UAT2 | P6: Rahul Gian Chandnani | Q6: Mani John | R6: 10.17.29.120/121:5310 | S6: 10.16.29.120:5310 | U6: 1 | V6: 0.65 | W6: Provided by source system team at field level
A7: Asked Milind | B7: Infosys | C7: Digital Banking Admin | D7: M2,M5,M7 | E7: 48 | F7: 46 | G7: In Progress | H7: 44 - database 2 fields - need API 2 fields - require BA inputs | I7: Surabhi Gopi Alok | J7: Green | K7: Data Platform + API? | L7: No | N7: CORP5 MCF Database IP: 10.15.25.6 Port: 5300 | O7: UAT2 | P7: Thomas Baxendale -Corporate Rahul Singh - Retail | Q7: Milind Harichandra Gowari | W7: Provided by source system team at field level
A8: Asked Milind | B8: Infosys | C8: Digital ON-Boarding Tracking (DEH) | D8: M5,M2 | E8: 22 | F8: 7 | G8: In Progress | H8: Front end code base is with Arjun's team Surabhi to clarify on fields requested from IBPS Surabhi scheduled meeting with vendor on Sep 26 Oct 13 - Business shared query. Alok to check on DEH tables Oct 13 - IBPS related fields to be provided by Business | I8: Alok Business | J8: Green | K8: Data Platform | L8: Yes | N8: server deh-db-dev-01.chgggpswwiss.me-central-1.rds.amazonaws.com:5500; 10.15.12.12:530 | P8: Sumat Kumar | Q8: Milind Harichandra Gowari Mani John | R8: 10.17.4.186/187:5300 | S8: 10.16.5.186/187:5300 | T8: deh-db-production-01.c9ma088winqb.me-central-1.rds.amazonaws.com : 5500 | U8: 0.7 | V8: 0.7 | W8: Provided by source system team at field level
A9: Have asked Sree | B9: TSYS | C9: Prime | D9: M2,M3, M5 | E9: 335 | F9: 0 | G9: Yet to Start | H9: Resourcing estimates shared by TSYS on Sep 25th. Sep 25 - PM emailed to Alfie to place WO and also included MDES in the scope to vendor Oct 13 - Awaiting VO/SoW from vendor | I9: Vendor | J9: Amber | K9: Data Platform? | L9: Yes | M9: ok | N9: 10.15.12.122, 5300 | O9: UAT2 | P9: Rehan Riaz Ahmad | Q9: Shaik Hussain Shariff | R9: 10.17.21.53/55:5300 | S9: 10.16.21.53/55:5300 | U9: NA | V9: NA | W9: Provided by source system team at field level
A10: Have asked Mani | B10: Nucleus | C10: RLS | D10: M2,M3,M5 | E10: 190 | F10: 149 | G10: In Progress | H10: Aug 12th - RLS is on-prem but DB access cannot be provided. Aug 13th - Discusses with RLS. Vendor agreed to provide DB details and come up with solution for other specs. Sent reminders on Sep 16, 25 Sep 26 - vendor confirmed the specs will be shared on or before Oct 7th - 149 fields provided only DB details. FE details not provided for any of 190 fields. Meeting scheduled on Oct 14th Oct 14 - Dragos to confirm on the calculated fields solution. Emailed | I10: Dragos Alok | J10: Amber | K10: Data Platform | L10: Yes | M10: ok | N10: 10.15.11.165:5300 | O10: UAT2 | P10: Shibani Mehra | Q10: Mani John | R10: 10.17.4.229:5300 | S10: 10.16.5.145:5300 | U10: 0.99 | V10: 0.99 | W10: Provided by source system team at field level
A11: Have asked Mani | B11: Intellect Design Arena | C11: Intellect Collection | D11: M2,M3,M5 | E11: 24 | F11: 0 | G11: Yet to start | H11: Sep 25 - Business Shared requirements from Intellect Surabhi reviewing pending 2 fields | I11: Business Surabhi | J11: Red | K11: Data Platform | L11: Yes | N11: Same DB as of RLS, app IP is different | O11: UAT2 | P11: Khadija Sultan Alhammadi | Q11: Mani John | W11: Provided by source system team at field level
A12: Have asked Devi | B12: Distinct Infotech | C12: CASMEX | D12: M2,M3 | E12: 74 | F12: 0 | G12: In Progress | H12: Had discussion with Vendor on Sep 1st. Vendor will share the detailes by EOD this month. Reminder sent on Sep 16 and 25 Sep 26 - vendor assured to provide specs asap. Oct 13 - PM sent followup | I12: Vendor | J12: Amber | K12: Data Platform | L12: Yes | N12: 10.15.13.97 & 5300 | O12: UAT2 | P12: Elcin Yanik | Q12: Guruprasad Narayan Shetty | R12: 10.17.4.147:5300 | S12: 10.16.4.90:5300 | U12: 0.65 | V12: 0.65 | W12: Provided by source system team at field level
A13: Have asked Guru | B13: NewGen | C13: ICCS - Cheque Flow System | D13: M2,M3 | E13: 64 | F13: 64 | G13: Completed | H13: Received on Aug 5th. | I13: Alok | J13: Completed | K13: Data Platform | L13: Yes | N13: 10.15.25.230; 5301 | O13: UAT2 | P13: Juzer Netterwala | Q13: Guruprasad Narayan Shetty | R13: 10.17.4.121:5301 | S13: 10.16.4.24:5301 | U13: NA | V13: NA | W13: Provided by source system team at field level
A14: Have asked Gaurav | B14: NewGen | C14: IBPS | D14: M5,M2 | E14: 10 | F14: 6 | G14: In Progress | H14: Received partially from Nikhil. Nikhil requested clarifications which Surabhi is addressing | I14: Surabhi | J14: Green | K14: Data Platform | L14: Yes | N14: 10.15.14.83:5301 | O14: UAT2 | P14: Juzer Netterwala | Q14: Gaurav Kumar | R14: 10.17.4.50:5301 | S14: 10.16.4.50:5301 | U14: NA | V14: NA | W14: Provided by source system team at field level
A15: Have asked Guru | B15: Unity | C15: Pay Hub Plus (NPSS Unity) | D15: M2,M3 | E15: 41 | F15: 0 | G15: Yet to Start | H15: To align with Payments team PM - Khutubuddin.Mohamed@rakbank.ae | I15: Surabhi | J15: Amber | K15: API | L15: No | P15: Elcin Yanik | Q15: Guruprasad Narayan Shetty | W15: Provided by source system team at field level
A16: Have asked Mani | B16: Dtech | C16: CCM | D16: M2,M5,M7 | E16: 33 | F16: 0 | G16: In Progress | H16: Had call with vendor on Jul 29th. Data ingestion possible. Anees suggesting to have DB view and proposing a solution that requires development effort. Call on Sep 23rd - Vendor team to come back with efforts. Some fields may not have one-to-one mapping DB type - Microsoft Sep 25 - Vendor confirmed to provide data by Oct 1st. SOW will be shared Oct 13 - PM requested for SoW and specs asap Oct 14 - SoW received. | I16: Vendor | J16: Green | K16: Data Platform | L16: No | N16: 10.15.13.125 | O16: Common env | P16: Sumat Kumar | Q16: Mani John | W16: Provided by source system team at field level
A17: Have asked Mani | B17: Game Change | C17: RAKTRACK | D17: M2,M5 | E17: 16 | F17: 14 | G17: In Progress | H17: Shailesh and Dragos discussed on 3 options. Shailesh team to assess these options and come with efforts and cost. RAKTRACK is on Mongo DB (non RDBMS), hence direct data ingestion will be a challenge though the app is onprem. 18.08 - Received front end specs for all 16 fields 18.09 - Confluent topic or API is proposed by vendor. Solution to be finalised by architects on 3 options Oct 6 - Solution finalised to go with Option 3 - API dev Oct 13 - PM emailed vendor for SoW and looped procurement | I17: Gopi/Dragos/Affan | J17: Red | K17: API | L17: No | N17: 10.15.13.246:5401 (DBA and Linux team unable to find this IP please confirm where is it hosted??) | O17: UAT2 | P17: Thomas Baxendale | Q17: Mani John | W17: Provided by source system team at field level
A18: Have asked Mani | B18: Infobip | C18: Infobip | D18: M2,M5 | E18: 11 | F18: 0 | G18: In Progress | H18: Solution discussion in progress with Infobip. Narek and Gopi discussing. We will be consuming details through API exposed to RAKBANK common platform. Frontend fields can be fetched from API details as well. Development of API - will be done by CRM. Ownership will be with Infobip support team - Mani John. Narek mentioned that Infobip will share their APIs for our dev to start | J18: Green | K18: API | L18: No | P18: Naya Kiochou | Q18: Mani John | W18: Provided by source system team at field level
A19: Have asked Sree | B19: MasterCard | C19: MDES (PRIME) | D19: M2,M3 | E19: 27 | F19: 0 | G19: Yet to Start | H19: Details can be taken from Cards systems per Ravish/Gopi. BA had call with CCO for business justification. BA to provide justification to Ravish . Sep 25 - PM included MDES in TSYS scope as Velan confirmed these details are from PRIME. Procurement to issue WO Sep 26 - PM emailed procurement team on establishing project with vendor | I19: Procurement | J19: Red | K19: API | L19: No | N19: Checked with Cards platform, this is not a system & it is only a token data stored in PRIME table. | O19: UAT2 | P19: Rehan Riaz Ahmad | Q19: Shaik Hussain Shariff | W19: Provided by source system team at field level
A20: Have asked Sree | B20: VISA | C20: VISA Online | D20: M2,M3 | E20: 16 | F20: 0 | G20: Yet to Start | H20: Sep 25 - Velan confirmed Visa tokenization is not working in production due to outdated interface flow. Surabhi to check with business on further steps Sep 26 - PM emailed procurement team on establishing project with vendor | I20: Procurement | J20: Red | K20: API | L20: No | N20: Checked with Cards platform, this is not a system & it is only a token data stored in PRIME table. | O20: UAT2 | P20: Rehan Riaz Ahmad | Q20: Shaik Hussain Shariff | W20: Provided by source system team at field level
A21: Have asked Sree | B21: Team Express | C21: Team Express Portal | D21: M5 | E21: 13 | F21: 13 | G21: Completed | H21: Scheduled meeting with Stalin. Team Express Portal can expose new API with required details. Data ingestion not possible. Budgeted development effort from the vendor. Front-end details to be provided by the vendor Front-End specs received Surabhi to confirm on milestone dates. Solution to be designed, Vendor to be aligned for dev efforts Not managed by IT Procurement. Mahesh to be contacted | I21: Surabhi Gopi | J21: Completed | K21: API | L21: No | P21: Shibani Mehra | Q21: Mahesh Kannan Kalarickel Gopalakrishnan ? | W21: Provided by source system team at field level
B22: ICC | C22: RAKRewards Admin | D22: M2,M3 | E22: 31 | F22: 0 | G22: Yet to Start | H22: Discussed with Badusha and Amit. This is new requirement for ICC and existing Digital banking APIs cannot be reused. Data cannot be ingested. 20.08 - Discussed with vendor - Detailed BRD on fields , API requested by vendor Surabhi to provide BRD | I22: Surabhi | J22: Green | K22: API | L22: No | P22: Rehan Riaz Ahmad | Q22: Mamta Peswani? | W22: Provided by source system team at field level
A23: Have asked Gaurav | B23: Pennanttech | C23: Cross Sell | D23: M2,M5 | E23: 25 | F23: 25 | G23: Completed | H23: All details received. In Data Platform scope. DB2 can provide only batch. Alternation solution to be provided by architect. Oct 9 - Solution confirmed by Gopi to go with API. Oct 13 - PM emailed vendor requesting API development efforts and looped procurement | I23: Vendor Procurement | J23: Amber | K23: API | L23: No | N23: 10.15.24.158 - 5302 (DB2 batch only possible) | O23: common env | P23: Himanshu Tyagi | Q23: Gaurav Kumar | W23: Provided by source system team at field level
A24: Have asked Sree | B24: Internal - CARDS | C24: CPPS | D24: M2,M3 | E24: 20 | F24: 20 | G24: Completed | H24: ADO ticket created with CARDS platform - 400859 Solution to be provided | I24: Gopi | J24: Completed | K24: API | L24: Yes | N24: 10.15.11.79:5322 (DB2 batch only possible) | O24: UAT1 | P24: Rehan Riaz Ahmad | Q24: Shaik Hussain Shariff | W24: Provided by source system team at field level
A25: Have asked Sree | B25: Internal - CARDS | C25: CAPS | D25: M2,M3 | E25: 7 | F25: 7 | G25: Completed | H25: ADO ticket created with CARDS platform - 400859. Gap analysis WIP | I25: Alok | J25: Completed | K25: Data Platform | L25: Yes | N25: 10.15.12.26:5310 | O25: UAT2 | P25: Rehan Riaz Ahmad | Q25: Shaik Hussain Shariff | R25: 10.17.4.97:5300 | S25: 10.16.5.154:5300 | U25: 0.98 | V25: 0.88 | W25: Provided by source system team at field level
A26: Have asked Sree | B26: Internal - CARDS | C26: DCR | D26: M2,M3,M5 | E26: 3 | F26: 3 | G26: Completed | H26: ADO ticket created with CARDS platform - 400859. Gap analysis WIP | I26: Alok | J26: Completed | K26: Data Platform | L26: No | N26: 10.15.12.26:5310 (DB IP is same, schema is different) | O26: UAT2 | P26: Elcin Yanik | Q26: Shaik Hussain Shariff | W26: Provided by source system team at field level
A27: Have asked Guru | B27: Internal | C27: CardNet | D27: M5 | E27: 9 | F27: 9 | G27: Completed | H27: Received from Sathiyan on Sep 12th. Solution to be provided | I27: Gopi | J27: Completed | K27: API | L27: No | P27: Rehan Riaz Ahmad | Q27: Guruprasad Narayan Shetty | W27: Provided by source system team at field level
A28: Have asked Gaurav | B28: Internal | C28: IDD | D28: M2,M6 | E28: 73 | F28: 73 | G28: Yet to Start | H28: Oct 6 - Received specs | I28: Sathiyan | J28: Completed | K28: API | L28: No | P28: Mohammed Ahmed Siddiqui | Q28: Gaurav Kumar | W28: Provided by source system team at field level
B29: Internal | C29: Previous RAKNet Version (Personal Banking) | D29: M2,M3,M5 | E29: 48 | F29: 0 | G29: Yet to Start | H29: Sathiyan searching for code base - legacy application | I29: Sathiyan | J29: Amber | K29: API? | L29: No | P29: ? | Q29: Gaurav Kumar | W29: Provided by source system team at field level
A30: Have asked Mani | B30: Internal | C30: CPF | D30: M2,M3,M7 | E30: 32 | F30: 32 | G30: Completed | H30: Oct 6 - Received specs | I30: Sathiyan | J30: Completed | K30: Data Platform | L30: Yes | N30: 10.15.12.194:5301 | O30: Common env | P30: Naya Kiochou | Q30: Mani John | W30: Provided by source system team at field level
A31: Have asked Gaurav | B31: Internal | C31: Bank Auth Representative E-Register(auth rep) | D31: M2,M3 | E31: 29 | F31: 0 | G31: Yet to Start | H31: Sathiyan searching for code base - legacy application | I31: Sathiyan | J31: Amber | K31: API? | L31: No | P31: Juzer Netterwala | Q31: Gaurav Kumar | W31: Provided by source system team at field level
A32: Have asked Gaurav | B32: Internal | C32: Cheque Book System | D32: M2,M3 | E32: 25 | F32: 25 | G32: Completed | H32: Received from Sathiyan on Sep 12th. Solution to be provided | I32: Gopi | J32: Completed | K32: API | L32: No | P32: Juzer Netterwala | Q32: Gaurav Kumar | W32: Provided by source system team at field level
A33: Have asked Guru | B33: Internal | C33: 3D Secure | D33: M2,M3, M5 | E33: 14 | F33: 14 | G33: Completed | H33: Received from Sathiyan on Sep 12th. Solution to be provided | I33: Gopi | J33: Completed | K33: API | L33: No | P33: Rehan Riaz Ahmad | Q33: Guruprasad Narayan Shetty | W33: Provided by source system team at field level
A34: Have asked Gaurav | B34: Internal | C34: Prospect | D34: M2,M5 | E34: 10 | F34: 10 | G34: Completed | H34: Received from Sathiyan on Aug 7th. Solution to be provided | I34: Gopi | J34: Completed | K34: API | L34: No | P34: Mona Ibrahim Al Shamsi | Q34: Gaurav Kumar | W34: Provided by source system team at field level
A35: Have asked Gaurav | B35: Internal | C35: VAT | D35: M5,M2 | E35: 8 | F35: 8 | G35: Completed | H35: Received from Sathiyan on Aug 7th. Solution to be provided | I35: Gopi | J35: Completed | K35: API | L35: No | P35: Manohar Bhoir | Q35: Gaurav Kumar | W35: Provided by source system team at field level
B36: Internal | C36: RAKFLUX | D36: M5 | E36: 5 | F36: 0 | G36: Yet to Start | H36: Sathiyan to prioritize the task. | I36: Sathiyan | J36: Green | K36: API | L36: No | W36: Provided by source system team at field level
A37: Have asked Gaurav | B37: Internal | C37: Salary Application | D37: M2,M3 | E37: 5 | F37: 5 | G37: Completed | H37: Received from Sathiyan on Sep 12th. Solution to be provided | I37: Gopi | J37: Completed | K37: API | L37: No | P37: Juzer Netterwala | Q37: Gaurav Kumar | W37: Provided by source system team at field level
A38: Have asked Mani | B38: Internal | C38: FX Rate Calculator | D38: M5,M2 | E38: 2 | F38: 2 | G38: Completed | H38: https://www.rakbank.ae/en/everyday-banking/send-pay/foreign-exchange-rates Data is required from this link. Its internal. Business -> Trade & Forex -> Forex Exchange rates will be fetched via API. Solution to be provided. Gopi to align with Manoj | I38: Gopi | J38: Completed | K38: API | L38: No | P38: Mohammad Ahteshamoddin | Q38: Mani John | W38: Provided by source system team at field level
B39: External | C39: Genesys | D39: M2, M7 | E39: 2 | F39: 2 | G39: Completed | H39: Authentication flag. To receive from API Solution signed-off by EDA. BRD to be issued to Genesys for SOW | I39: Surabhi | J39: Completed | K39: API | L39: No | P39: Mona Ibrahim Al Shamsi | Q39: Mani John | W39: Provided by source system team at field level
B40: External | C40: EID | E40: 2 | F40: 2 | G40: Completed | H40: Authentication flag. To receive from API Solution to be provided | I40: Gopi | J40: Completed | K40: API | L40: No | P40: Sumat Kumar | Q40: Gaurav
B41: External | C41: UAEPASS | E41: 2 | F41: 2 | G41: Completed | H41: Authentication flag. To receive from API Solution to be provided | I41: Gopi | J41: Completed | K41: API | L41: No | P41: -
E42: =SUM(E5:E41) -> 2657 | F42: =SUM(F5:F41) -> 1725
E45: =F42/E42 -> 0.64922845
C47: Internal Systems requiring API dev | D47: 12 | E47: no procurement
C48: External Systems requiring API Dev | D48: 13 | E48: Procurement
C49: Internal Systems through Databricks | D49: 3 | E49: no procurement
C50: External Systems through Databricks | D50: 11
C51: Systems that require both Databricks & API | D51: 2 | E51: for now

Sheet Sheet3
B3: *Systems List | C3: Vendor | D3: Vendor Spoc | E3: Vendor contact | F3: Contact Phone
B4: Prime | C4: TSYS | D4: Mohamed Sukkari Muhammed Ajmal | E4: mohamedsukkari@tsys.com majmal@tsys.com
B5: RLS | C5: Nucleus Software | D5: Kaushal.misra@nucleussoftware.com | E5: Kaushal.misra@nucleussoftware.com
B6: CASMEX | C6: Distinct Infotech | D6: rajeshkumar.rn@distinctinfotech.com chacko@distinctinfotech.com | E6: rajeshkumar.rn@distinctinfotech.com chacko@distinctinfotech.com
B7: ICCS - Cheque Flow System | C7: NewGen technologies | D7: Anshu Raj | E7: anshu.raj@newgensoft.com
B8: CCM | C8: Dtech | D8: Muhammed Anees | E8: Muhammed.anees@dtechsoft.com
B9: MDES | C9: MASTERCARD
B10: RLS Collection | C10: Nucleus Software | D10: Kaushal.misra@nucleussoftware.com | E10: Kaushal.misra@nucleussoftware.com
B11: VISA Online | C11: VISA
B12: RAKTRACK | C12: Game Change | D12: Shailesh Tiwari | E12: shailesh.tiwari@gamechangesns.com
B13: 3D Secure | C13: Broadcom | D13: Konrad Karczmarczyk | E13: konrad.karczmarczyk@broadcom.com
B14: Team Express Portal | C14: Not Identified
B15: Infobip | C15: Infobip | D15: Edita Rokša Durić <edita.roksaduric@infobip.com>; Neira Kratovac Akriche <neira.kratovacakriche@infobip.com>; Nedžad Grizović <nedzad.grizovic@infobip.com> | E15: Edita Rokša Durić <edita.roksaduric@infobip.com>; Neira Kratovac Akriche <neira.kratovacakriche@infobip.com>; Nedžad Grizović <nedzad.grizovic@infobip.com>
B16: IBPS | C16: NewGen technologies | D16: Anshu Raj | E16: anshu.raj@newgensoft.com

Sheet M2
A1: Field Name | B1: CRM Section | C1: Core System | D1: Mapping
A2: Policy Number | B2: Basic Details | C2: IDD | D2: IDD -> Enquiry -> Policy Search -> Policy/ Proposal No.
A3: Product Name | B3: Basic Details | C3: IDD | D3: IDD -> Enquiry -> Policy Search -> Product Name
A4: Plan Name | B4: Basic Details | C4: IDD | D4: IDD -> Enquiry -> Policy Search -> Plan Name
A5: Policy Status | B5: Basic Details | C5: IDD | D5: IDD -> Enquiry -> Policy Search -> Policy Status
A6: Payment Frequency | B6: Policy Details | C6: IDD | D6: IDD -> Enquiry -> Policy Search -> Policy Details -> Policy Details -> Payment Frequency
A7: Policy Currency | B7: Basic Details | C7: IDD | D7: IDD -> Enquiry -> Policy Search -> Policy Details -> Policy Details -> Policy Currency
A8: Monthly Premium | B8: Policy Details | C8: IDD | D8: IDD -> Enquiry -> Policy Search -> Policy Details -> Policy Details -> M Premium
A9: Type | B9: Policy Details | C9: IDD | D9: IDD -> Enquiry -> Policy Search -> Policy Details -> Policy Details -> Type
A10: Plan Term (Years) | B10: Policy Details | C10: IDD | D10: IDD -> Enquiry -> Policy Search -> Policy Details -> Policy Details -> Plan Terms (Years)
A11: Total Premium
A12: Effective Policy Date | B12: Policy Details | C12: IDD | D12: IDD -> Enquiry -> Policy Search -> Policy Details -> Effective Policy Date

Sheet Approach
E2: Fileds/Logic received | G2: Fields yet to receive
B3: Vendor | C3: System | D3: No. of fields requested | E3: No. of static fields | F3: No. of runtime fields | G3: No. of static fields | H3: No. of runtime fields | I3: Is source DB internal to RAKBANK network ? | J3: Is System Pipeline available? | K3: Integration mechansim suggested by Architects | L3: Is API or IL development required from vendor/source team? | M3: Action with | N3: Action | O3: Remarks
A4: Oxygen, OF | B4: Infosys | C4: Finacle | D4: 1184 | E4: 1066 | F4: 0 | G4: 99 | H4: 19 | I4: Yes | J4: Yes | K4: Data Platform + API? | L4: Yes | M4: Alok | N4: Checking with vendor for logic | O4: Checking with vendor for logic
A5: Oxygen | B5: Infosys | C5: WMS | D5: 197 | E5: 117 | F5: 0 | G5: 47 | H5: 28 | I5: Yes | J5: Yes | K5: Data Platform + API? | L5: Yes | M5: Alok | N5: Checking with vendor for logic | O5: Checking with vendor for logic
B6: Infosys | C6: Digital Banking Admin | D6: 48 | E6: 44 | G6: 2 | H6: 2 | I6: Yes | J6: No | K6: Data Platform + API? | L6: Yes | M6: Alok | N6: Checking with vendor for logic | O6: Checking with vendor for logic
B7: Infosys | C7: Digital ON-Boarding Tracking (DEH) | D7: 8 | E7: 7 | F7: 0 | G7: 1 | H7: 0 | I7: Yes | J7: Yes | K7: Data Platform | L7: No | M7: Alok | N7: Alok to check with vendor for 1 field | O7: Alok to check with vendor for 1 field
A8: Oxygen, OF | B8: TSYS | C8: Prime | D8: 335 | E8: 0 | F8: 0 | G8: 0 | H8: 0 | I8: Yes | J8: Yes | K8: To be decided | L8: Maybe | M8: Keerthana | N8: PO in approval | O8: PO in approval
A9: Oxygen, OF | B9: Nucleus | C9: RLS | D9: 190 | E9: 149 | F9: 0 | G9: 0 | H9: 41 | I9: Yes | J9: Yes | K9: Data Platform | L9: Yes | M9: Dragos | N9: Dragos to confirm back to vendor on solution | O9: IL table dev required from vendor.
B10: Intellect Design Arena | C10: Intellect Collection | D10: 24 | E10: 0 | F10: 0 | G10: 0 | H10: 0 | I10: Yes | J10: Yes | K10: To be decided | L10: Maybe | M10: Surabhi | N10: Business to provide req | O10: Business to provide req
B11: Distinct Infotech | C11: CASMEX | D11: 74 | E11: 70 | F11: 0 | G11: 4 | H11: 0 | I11: Yes | J11: Yes | K11: Data Platform | L11: Maybe | M11: Alok | N11: Alok to check with vendor for 4 fields | O11: Alok to check with vendor for 4 fields
B12: NewGen | C12: ICCS - Cheque Flow System | D12: 64 | E12: 64 | F12: 0 | G12: 0 | H12: 0 | I12: Yes | J12: Yes | K12: Data Platform | L12: No | M12: DB team | N12: Data build to start | O12: No action
B13: NewGen | C13: IBPS | D13: 24 | E13: 6 | F13: 0 | G13: 18 | H13: 0 | I13: Yes | J13: Yes | K13: Data Platform | L13: No | M13: Surabhi | N13: Surabhi to check 18 fields with Nikhil | O13: Surabhi to check 18 fields with Nikhil
B14: Unity | C14: Pay Hub Plus (NPSS Unity) | D14: 41 | E14: 0 | F14: 0 | G14: 0 | H14: 0 | I14: Yes | J14: No | K14: Data Platform | L14: No | M14: Keerthana | N14: Keerthana to align with Unity PM | O14: Keerthana to align with Unity PM
B15: Dtech | C15: CCM | D15: 33 | E15: 0 | F15: 0 | G15: 0 | H15: 0 | I15: Yes | J15: No | K15: To be decided | L15: Maybe | M15: Keerthana | N15: PO in approval | O15: PO in approval
B16: Game Change | C16: RAKTRACK | D16: 16 | E16: NA | F16: NA | G16: NA | H16: NA | I16: Yes | J16: No | K16: API | L16: Yes | M16: Gopi | N16: Architect to provide tech requirement doc | O16: Mongo DB (Requires review). DB cannot connect
B17: Infobip | C17: Infobip | D17: 11 | E17: NA | F17: NA | G17: NA | H17: NA | I17: No | J17: No | K17: API | L17: Yes | M17: Narek | N17: Narek/Nedzad to develop API from vendor | O17: Infobip integration. External system
B18: MasterCard | C18: MDES | D18: 27 | E18: NA | F18: NA | G18: NA | H18: NA | I18: No | J18: No | K18: API | L18: Yes | M18: Gopi | N18: Architect to provide tech requirement doc | O18: External
B19: VISA | C19: VISA Online | D19: 16 | E19: NA | F19: NA | G19: NA | H19: NA | I19: No | J19: No | K19: API | L19: Yes | M19: Gopi | N19: Architect to provide tech requirement doc | O19: External
B20: Team Express | C20: Team Express Portal | D20: 13 | E20: NA | F20: NA | G20: NA | H20: NA | I20: No | J20: No | K20: API | L20: Yes | M20: Gopi | N20: Architect to provide tech requirement doc | O20: External
B21: ICC | C21: RAKRewards Admin | D21: 31 | E21: NA | F21: NA | G21: NA | H21: NA | I21: No | J21: No | K21: API | L21: Yes | M21: Surabhi/Gopi | N21: Surabhi to provide BRD. | O21: External
B22: Pennanttech | C22: Cross Sell | D22: 25 | E22: 25 | F22: 0 | G22: 0 | H22: 0 | I22: Yes | J22: No | K22: API | L22: Yes | M22: Gopi | N22: Architect to provide tech requirement doc | O22: DB2 (batch only possible)
B23: Internal - CARDS | C23: CPPS | D23: 20 | E23: 20 | F23: 0 | G23: 0 | H23: 0 | I23: Yes | J23: Yes | K23: API | L23: Yes | M23: Keerthana | N23: To align CARDS team for development | O23: DB2 (batch only possible)
B24: Internal - CARDS | C24: CAPS | D24: 7 | E24: 6 | F24: 1 | G24: 0 | H24: 0 | I24: Yes | J24: Yes | K24: Data Platform | L24: No | M24: Data team | N24: Data build to start | O24: 1 field logic to be redone
B25: Internal - CARDS | C25: DCR | D25: 3 | E25: NA | F25: NA | G25: NA | H25: NA | I25: Yes | J25: No | K25: API | L25: No | M25: Int. team | N25: Existing API to be used | O25: Existing API given by team
B26: Internal | C26: CardNet | D26: 9 | E26: 9 | F26: 0 | G26: 0 | H26: 0 | I26: Yes | J26: No | K26: API | L26: Yes | N26: To confirm the integration approach | O26: Legacy system
B27: Internal | C27: IDD | D27: 73 | E27: 73 | F27: 0 | G27: 0 | H27: 0 | I27: Yes | J27: No | K27: API | L27: Yes | N27: To confirm the integration approach | O27: Legacy system
B28: Internal | C28: Previous RAKNet Version (Personal Banking) | D28: 48 | E28: NA | F28: NA | G28: NA | H28: NA | I28: Yes | J28: No | K28: API | L28: Yes | N28: To confirm the integration approach | O28: Legacy system
B29: Internal | C29: CPF | D29: 32 | E29: 32 | F29: 0 | G29: 0 | H29: 0 | I29: Yes | J29: Yes | K29: Data Platform | L29: No | M29: Data team | N29: Data build to start
B30: Internal | C30: Bank Auth Representative E-Register(auth rep) | D30: 29 | E30: NA | F30: NA | G30: NA | H30: NA | I30: Yes | J30: No | K30: API | L30: Yes | N30: To confirm the integration approach | O30: Legacy system
B31: Internal | C31: Cheque Book System | D31: 25 | E31: 22 | F31: 0 | G31: 3 | H31: 0 | I31: Yes | J31: No | K31: API | L31: Yes | N31: To confirm the integration approach | O31: Legacy system
B32: Internal | C32: 3D Secure | D32: 14 | E32: 14 | F32: 0 | G32: 0 | H32: 0 | I32: Yes | J32: No | K32: API | L32: Yes | N32: To confirm the integration approach | O32: Legacy system
B33: Internal | C33: Prospect | D33: 10 | E33: 10 | F33: 0 | G33: 0 | H33: 0 | I33: Yes | J33: No | K33: API | L33: Yes | N33: To confirm the integration approach | O33: Legacy system
B34: Internal | C34: VAT | D34: 8 | E34: 4 | F34: 2 | G34: 2 | H34: 0 | I34: Yes | J34: No | K34: API | L34: Yes | N34: To confirm the integration approach | O34: Legacy system
B35: Internal | C35: RAKFLUX | D35: 5 | I35: Yes | J35: No | K35: API | L35: Yes | N35: To confirm the integration approach | O35: Legacy system
B36: Internal | C36: Salary Application | D36: 5 | E36: 5 | F36: 0 | G36: 0 | I36: Yes | J36: No | K36: API | L36: Yes | N36: To confirm the integration approach | O36: Legacy system
B37: Internal | C37: FX Rate Calculator | D37: 2 | E37: 0 | F37: 2 | I37: Yes | J37: No | K37: API | L37: Yes | N37: To confirm the integration approach | O37: Legacy system
B38: External | C38: Genesys | D38: 2 | E38: 0 | F38: 2 | I38: Yes | J38: No | K38: API | L38: Yes | N38: To confirm the integration approach | O38: Genesys integration
B39: External | C39: EID | D39: 2 | E39: 0 | F39: 2 | I39: Yes | J39: No | K39: API | L39: Yes | N39: To confirm the integration approach | O39: EIDA integration
B40: External | C40: UAEPASS | D40: 2 | E40: 0 | F40: 2 | I40: Yes | J40: No | K40: API | L40: Yes | N40: To confirm the integration approach | O40: UAEPASS integration
D41: =SUM(D4:D40) -> 2657 | E41: =SUM(E4:E40) -> 1743 | F41: =SUM(F4:F40) -> 11 | G41: =SUM(G4:G40) -> 176 | H41: =SUM(H4:H40) -> 90
D43: =E41/D41 -> 0.65600301

Sheet SampleData
B3: Sample Required information –
B4: Type of Field (Frontend) | C4: Type of Field (Backend) | D4: Length (Frontend) | E4: Length (Backend) | F4: Format (Frontend) | G4: Format (Backend) | H4: List of Values (Frontend) | I4: List of Values (Backend) | J4: Can this data be fetched from DB or can be exposed via API? | K4: Database Name | L4: Table Name | M4: Database Field Name | N4: Any custom logic to populate this field
B5: dropdown | C5: dropdown | D5: 10 | E5: NVARCHAR(10 CHAR) | F5: String | G5: NVARCHAR2(10 CHAR) | H5: -FEMALE -MALE -NOT AVAILABLE | I5: -F -M -O
B6: Text | C6: Text | D6: 10 | E6: NVARCHAR(75) | F6: String | G6: NVARCHAR2(80 CHAR) | H6: NA | I6: NA

Sheet Sheet1
C3: Priority | D3: Application systems | E3: Description | F3: Technology Owner | G3: Technology Owner Manager | H3: Business Owner | I3: Business Owner Manager | J3: Vendor Spoc | K3: Vendor Contact
C4: 1 | D4: Finacle (Core Banking) | E4: Core Banking System | F4: Joy Sunil/ Mani John | G4: Sumat Kumar | H4: Chelliah Kumar | I4: Juzer Netterwala | J4: Yashpaul Jindal, Yashpaul.Jindal@infosys.com | K4: +971 565064530
J5: Vikram_Ansal@infosys.com
C6: 2 | D6: Islamic Banking(Flexcube) | E6: Islamic Banking System | F6: Manjit Kaur | G6: Sumat Kumar | H6: Shakeeb Inayatullah Isane/ Mani John | I6: Abdul Karim Juma | J6: Varghese Mathew , varghese.x.mathew@oracle.com | K6: +91 9986874212
J7: bikram.nanada@oracle.com
C8: 2 | D8: Front Arena (FIS) - Treasury | E8: Treasury Application | F8: Ruan Chapman | G8: Sumat Kumar | H8: Khushbu | I8: Vikas Suri | J8: Philip E, philip.hill@fisglobal.com | K8: Internal
C9: 3 | D9: FinOne- RLS | E9: Conventional Loan Management System | F9: Semeer Cherangathody | G9: Sumat Kumar | H9: Shibani , Divya, Archana , Abdullah Farooq | I9: Shibani Mehra | J9: Kaushal.misra@nucleussoftware.com | K9: +91 9810617822
E10: Loan originating System | G10: Sumat Kumar | H10: Abdullah Farooq / Roshan/ Archana | I10: Khadija Sultan Alhammadi
E11: Collection System is used for tracking bank collections and used by collection agents. | F11: Manjit Kaur | G11: Sumat Kumar | H11: Chelliah Kumar/ | I11: Shibani Mehra
C12: 4 | D12: PRIME4 | E12: Card Management system | F12: Shaik Hussain Shariff | G12: Sumat Kumar | I12: Rehan Riaz Ahmad | J12: majmal@tsys.com | K12: +971 50 2100680
J13: mohamedsukkari@tsys.com
C14: 4 | D14: CAPS | E14: (Provision of Loan System) | F14: Sijina, Vijayalakshmi (Viji), Anuj Agarwal | G14: Sumat Kumar | H14: Saurabh Kumar Sharma | I14: Sumeet Vijay Jain | J14: Sree Rasmi Sasikumaran <Sree.Sasikumaran@rakbank.ae> | K14: Internal
H15: Farzan Dalal
C16: 5 | D16: EximBills | E16: Trade Finance Application | F16: Deshika Mani | G16: Sumat Kumar | H16: Chelliah Kumar/Balaji Viswalingam / Hemalika | I16: Vikas Suri | J16: Thushara@chinasystems-me.com
J17: Antony-antony@chinasystems-me.com
C18: 6 | D18: MAPS | E18: Retail Banking | F18: Hadrain Fernando | G18: Sumat Kumar | H18: Shaik Hussain Shariff | I18: Rajesh Sharma/Sonia Gregory/ | J18: Rahul Mehta - rahul.mehta@isgdigitalfirst.com
J19: Praveen Balusu - praveenb@insolutionsglobal.com
C20: 7 | D20: ALM (Fund Transfer Pricing-Asset Management Liability) | E20: Fund transfer pricing Asset Liabilities Mgmt | F20: Charu Saumya/ KRM Support | G20: Sumat Kumar | I20: Mridul Ashok Baberwal | J20: KamakuraAspacTeam@sas.com | K20: +886 919361377
J21: WeiBo.Kao@sas.com
C22: 8 | D22: CASMEX | E22: Remittance Processing System | F22: Guruprasad Narayan Shetty/ Jonathan/Hadrian Fernando | G22: Sumat Kumar | H22: Ashutosh/Rahul/Manoj | J22: rajeshkumar.rn@distinctinfotech.com, chacko@distinctinfotech.com
C23: 9 | D23: Kiplot -Project Portfolio System | E23: Project Portfolio System | F23: Steeve | G23: Samil Salim | H23: Steeve | I23: Samil Salim | J23: Balpreet Rihal - balpreet.rihal@kiplot.com

Sheet Summary
A2: Vendor | B2: System | C2: Milestone | D2: No. of fields requested | E2: Integration mechansim suggested by Architects | F2: Milestone 1 tables | G2: Milestone 2 tables | H2: Milestone 3 tables | I2: Milestone 4 tables | J2: Milestone 5 tables | K2: Milestone 6 tables | L2: Milestone 7 tables | M2: Milestone 8 tables
A3: Infosys | B3: Finacle | C3: M1, M2, M3, M4, M5, M6, M7, M8 | D3: 1202 | E3: Data Platform + API | F3: accounts, corporate, ENTITYDOCUMENT, Person, PhoneEmail, categories, category_lang Incidents | G3: Accounts, agent_entity_details, bizcenter, Corporate, DEMOGRAPHIC, ENTITY_INTEREST_TABLE, ENTITYDOCUMENT, EXTN_BODATA , GENERAL_ACCT_MAST_TABLE, MiscellaneousInfo, Person, PhoneEmail, SBCA_MAST_TABLE, TD_ACCT_MASTER_TABLE, | H3: ACCT_AUTH_SIGN_TABLE, Accounts, Address, agent_entity_details, ACH_PAYSYS_REASON_TABLE, ACCT_STATEMENT_TABLE, bizcenter, CUST_LDFEE, CUST_PAYGEN_ORD_TABLE, C_PORD_REMIT_INR, C_PORDM_DELETE, C_REJECT CMB_CSIS_GEN_ACCT_TABLE, CNMA, Corporate, CUST_CALBK, DEMOGRAPHIC, DAILY_TRAN_DETAIL_TABLE, ENTITY_INTEREST_TABLE, ENTITYDOCUMENT, entityrelationship, GEN_ACCT_MAST_MOD_TABLE, GEN_ACCT_CLASS_TABLE, GENERAL_ACCT_MAST_TABLE, SOL_GROUP_CONTROL_TABLE, GEN_SCHM_PARM_TABLE, LOGIN_TABLE, memberships, MiscellaneousInfo, ML_MMSG_TBL, MEMO_PAD_TABLE, OPERATIONSREASONCODES, Person, PhoneEmail, PAYMENT_ORDER_DETAIL_TABLE, PAYMENT_ORDER_HEADER_TABLE, preferences, psychographic, SWIFT_MSG_HISTORY_TABLE, SBCA_MAST_TABLE, SERVICE_OUTLET_TABLE, users, | I3: accounts, ACCT_AUTH_SIGN_TABLE, ADM, ALH, ALT, AST, C_CPVALUE, C_CRDT, CBT, CNC, corporate, DTD, EIT, entityrelationship, EXTN_BODATA , FinancialDetails, GAC, GAM, GSP, Incidents, ITC, PFT, Request, RSTD, SIH, TAM, TBA_RENEWAL_OPTION_TBL, TBA_TD_ACCT_MASTER_TBL, TDT, TSD
A4: Infosys | B4: WMS | C4: M2, M3, M7 | D4: 159 | E4: Data Platform + API | F4: WIGDT | G4: WIGDT | H4: WIGDT
A5: Infosys | B5: Digital Banking Admin | C5: M1, M2, M3, M4 | D5: 48 | E5: Data Platform + API | F5: CORPORATE_USER, MULTI_LEVEL_WORKFLOW_TABLE | G5: CORPORATE_USER
A6: Infosys | B6: Digital ON-Boarding Tracking (DEH) | C6: M1, M3, M5, M7, M8 | D6: 8 | E6: Data Platform
A7: TSYS | B7: Prime | C7: M1, M2, M3, M4 | D7: 305 | E7: Data Platform + API | F7: ILCARDX, People | G7: ILCARDEMBOSSING, ILCARDX, ILCACCOUNTS, lILCURRENCIES, ILPRODUCTS, ILCARDSTATUS, ILCSTATEMENTS PEOPLE ILISSUER_AUTHORIZATIONS iltbalances | H7: ILCINSTALMENTS Cinstalmentamortization ILACPLINKS ILACPROFILES ILAPPLOG ILBATCHES lILCURRENCIES ilcaccounts ILCACCOUNTSTMT ILCADDRESSES ILCARDEMBOSSING ILCARDS ILCARDSTATUS ILCARDX ILCCUSTOMERS ILCEXTENSION ILCSTATEMENTS ILCISOTRXNS ILCTRANSACTIONS ILCURRENCIES ILTRXNSTATUS ILGLOBALPARAMETERVALUES ILGLOBALPARAMETERS ILGROUPS ILINSTALMENTPLANS ILISSUER_AUTHORIZATIONS ILMEMOS ILMEMOTYPES ILPRODUCTS ILPROFILES ilTrxntypes iltBalances ilarchtBalances
A8: Nucleus | B8: RLS | C8: M1, M2, M3, M4, M5, M6 | D8: 190 | E8: Data Platform (batch) | F8: lea_agreement_dtl NBFC_CUSTOMER_M LEA_APPL_DTL | G8: LEA_AGREEMENT_DTL LEA_APPL_DTL LEA_REPAYSCH_DTL NBFC_CUSTOMER_M | H8: lea_agreement_dtl NBFC_CUSTOMER_M LEA_APPL_DTL
A9: Nucleus | B9: RLS collection | C9: M2, M4, M5 | D9: 24 | E9: Data Platform
A10: Distinct Infotech | B10: CASMEX | C10: M3, M5 | D10: 74 | E10: Data Platform | H10: DX_TRNS_REMITTANCE DX_REF_ACTIVITY_LOG | I10: DX_TRNS_REMITTANCE DX_REF_ACTIVITY_LOG
A11: NewGen | B11: ICCS - Cheque Flow System | C11: M3 | D11: 64 | E11: Data Platform | H11: Outward_ICCS ICCS_TAB_RoutingNumbers Inward_Ext_Tab
A12: NewGen | B12: IBPS | C12: M1, M2, M3, M4 | D12: 24 | E12: Data Platform | F12: wfinstrumenttable RB_PC_EXTTABLE RB_CMS_EXTTABLE RB_ML_EXTTABLE RB_DAC_EXTTABLE RB_BSR_EXTTABLE RB_iRBL_EXTTABLE RB_CSR_BT_EXTTABLE RB_CSR_CCB_EXTTABLE RB_CSR_CCC_EXTTABLE RB_CSR_MISC_EXTTABLE RB_CSR_OCC_EXTTABLE RB_CSR_RR_EXTTABLE RB_DSR_DCB_EXTTABLE RB_DSR_MISC_EXTTABLE RB_DSR_ODC_EXTTABLE RB_GSR_LCOL_EXTTABLE RB_ODDD_EXTTABLE RB_DA_Exttable RB_TF_EXTTABLE RB_SRB_EXTTABLE RB_AO_EXTTABLE RB_SRM_EXTTABLE RB_EPP_EXTTABLE RB_SAR_EXTTABLE RB_BAIS_EXTTABLE NG_DCC_EXTTABLE NG_DAO_EXTTABLE NG_TT_EXT_TABLE RB_TL_EXTTABLE RB_SRO_EXTTABLE RB_OECD_EXTTABLE RB_TWC_EXTTABLE RB_CU_EXTTABLE NG_DPL_EXTTABLE RB_DBO_EXTTABLE RB_CMS_EXTTABLE NG_TS_EXTTABLE RB_NBTL_EXTTABLE NG_EIBOR_EXTTABLE ng_CourtOrder_exttable RB_KYC_REM_EXTTABLE RB_DBS_EXTTABLE RB_PL_EXTTABLE | H12: wfinstrumenttable
A13: Unity | B13: Pay Hub Plus (NPSS Unity) | C13: M3, M4 | D13: 41 | E13: Data Platform | H13: NPSS_PaymentsStatusConfig NPSS_PmtStatus_ReqHdr NPSS_RTPaymentsDtl_Inw NPSS_RTPaymentsDtl_InwExn NPSS_RTPaymentsDtl_Out NPSS_RTPaymentsDtl_OutExn NPSS_RTPaymentsHdr_Inw NPSS_RTPaymentsHdr_Out NPSS_RTS_PmtStatusDtl_Dbtr
A14: Dtech | B14: CCM | C14: M2, M4, M5 | D14: 33 | E14: Data Platform | G14: DeliveryRegistration
A15: Infobip | B15: Infobip | C15: M3, M4 | D15: 11 | E15: Data Platform
A16: Internal - CARDS | B16: CPPS | C16: M4 | D16: 20 | E16: Data Platform (batch)
A17: Internal - CARDS | B17: CAPS | C17: M3, M6 | D17: 7 | E17: Data Platform (batch) | H17: CARD_GENERAL CARDS
A18: Internal - CARDS | B18: DCR (take from PRIME) | C18: - | D18: 3 | E18: Data Platform
A19: Internal | B19: CPF | C19: M1, M2, M3, M7 | D19: 32 | E19: Data Platform | G19: customer_consent customer_info consent_configs | H19: customer_consent customer_info consent_configs customer_consent_audit
A20: Internal | B20: 3D Secure (take from Infobip) | C20: M4 | D20: 14 | E20: Data Platform

Sheet DataIngestion-SQL
A1: Finacle | H1: Prime | O1: WMS | V1: Digital Banking Admin | AC1: Digital ON-Boarding Tracking (DEH) | AJ1: RLS | AQ1: RLS collection (RLS) | AX1: CASMEX | BE1: ICCS - Cheque Flow System | BL1: IBPS | BS1: Pay Hub Plus (NPSS Unity) | BZ1: CCM | CG1: Infobip | CN1: CPPS | CU1: CAPS | DB1: DCR (from PRIME) | DI1: CPF | DP1: 3D secure (from Infobip)
A2: Milestone | B2: Source table name | C2: CRM ODS table name | D2: Transactional table? If Y, one yr historical datato be loaded (rolling time) Purging to be implemented | E2: Data ingestion CRM_DEV from UAT2 | F2: Data ingestion CRM_SIT from UAT2 | G2: Data ingestion CRM_UAT from UAT2 | H2: Milestone | I2: Source table name | J2: CRM ODS table name | K2: Transactional table? If Y, one yr historical datato be loaded (rolling time) Purging to be implemented | L2: Data ingestion CRM_DEV | M2: Data ingestion CRM_SIT | N2: Data ingestion CRM_UAT | O2: Milestone | P2: Source table name | Q2: CRM ODS table name | R2: Transactional table? If Y, one yr historical datato be loaded (rolling time) Purging to be implemented | S2: Data ingestion CRM_DEV | T2: Data ingestion CRM_SIT | U2: Data ingestion CRM_UAT | V2: Milestone | W2: Source table name | X2: CRM ODS table name | Y2: Transactional table? If Y, one yr historical datato be loaded (rolling time) Purging to be implemented | Z2: Data ingestion CRM_DEV | AA2: Data ingestion CRM_SIT | AB2: Data ingestion CRM_UAT | AC2: Milestone | AD2: Source table name | AE2: CRM ODS table name | AF2: Transactional table? If Y, one yr historical datato be loaded (rolling time) Purging to be implemented | AG2: Data ingestion CRM_DEV | AH2: Data ingestion CRM_SIT | AI2: Data ingestion CRM_UAT | AJ2: Milestone | AK2: Source table name | AL2: CRM ODS table name | AM2: Transactional table? If Y, one yr historical datato be loaded (rolling time) Purging to be implemented | AN2: Data ingestion CRM_DEV | AO2: Data ingestion CRM_SIT | AP2: Data ingestion CRM_UAT | AQ2: Milestone | AR2: Source table name | AS2: CRM ODS table name | AT2: Transactional table? If Y, one yr historical datato be loaded (rolling time) Purging to be implemented | AU2: Data ingestion CRM_DEV | AV2: Data ingestion CRM_SIT | AW2: Data ingestion CRM_UAT | AX2: Milestone | AY2: Source table name | AZ2: CRM ODS table name | BA2: Transactional table? If Y, one yr historical datato be loaded (rolling time) Purging to be implemented | BB2: Data ingestion CRM_DEV | BC2: Data ingestion CRM_SIT | BD2: Data ingestion CRM_UAT | BE2: Milestone | BF2: Source table name | BG2: CRM ODS table name | BH2: Transactional table? If Y, one yr historical datato be loaded (rolling time) Purging to be implemented | BI2: Data ingestion CRM_DEV | BJ2: Data ingestion CRM_SIT | BK2: Data ingestion CRM_UAT | BL2: Milestone | BM2: Source table name | BN2: CRM ODS table name | BO2: Transactional table? If Y, one yr historical datato be loaded (rolling time) Purging to be implemented | BP2: Data ingestion CRM_DEV | BQ2: Data ingestion CRM_SIT | BR2: Data ingestion CRM_UAT | BS2: Milestone | BT2: Source table name | BU2: CRM ODS table name | BV2: Transactional table? If Y, one yr historical datato be loaded (rolling time) Purging to be implemented | BW2: Data ingestion CRM_DEV | BX2: Data ingestion CRM_SIT | BY2: Data ingestion CRM_UAT | BZ2: Milestone | CA2: Source table name | CB2: CRM ODS table name | CC2: Transactional table? If Y, one yr historical datato be loaded (rolling time) Purging to be implemented | CD2: Data ingestion CRM_DEV | CE2: Data ingestion CRM_SIT | CF2: Data ingestion CRM_UAT | CG2: Milestone | CH2: Source table name | CI2: CRM ODS table name | CJ2: Transactional table? If Y, one yr historical datato be loaded (rolling time) Purging to be implemented | CK2: Data ingestion CRM_DEV | CL2: Data ingestion CRM_SIT | CM2: Data ingestion CRM_UAT | CN2: Milestone | CO2: Source table name | CP2: CRM ODS table name | CQ2: Transactional table? If Y, one yr historical datato be loaded (rolling time) Purging to be implemented | CR2: Data ingestion CRM_DEV | CS2: Data ingestion CRM_SIT | CT2: Data ingestion CRM_UAT | CU2: Milestone | CV2: Source table name | CW2: CRM ODS table name | CX2: Transactional table? If Y, one yr historical datato be loaded (rolling time) Purging to be implemented | CY2: Data ingestion CRM_DEV | CZ2: Data ingestion CRM_SIT | DA2: Data ingestion CRM_UAT | DB2: Milestone | DC2: Source table name | DD2: CRM ODS table name | DE2: Transactional table? If Y, one yr historical datato be loaded (rolling time) Purging to be implemented | DF2: Data ingestion CRM_DEV | DG2: Data ingestion CRM_SIT | DH2: Data ingestion CRM_UAT | DI2: Milestone | DJ2: Source table name | DK2: CRM ODS table name | DL2: Transactional table? If Y, one yr historical datato be loaded (rolling time) Purging to be implemented | DM2: Data ingestion CRM_DEV | DN2: Data ingestion CRM_SIT | DO2: Data ingestion CRM_UAT | DP2: Milestone | DQ2: Source table name | DR2: CRM ODS table name | DS2: Transactional table? If Y, one yr historical datato be loaded (rolling time) Purging to be implemented | DT2: Data ingestion CRM_DEV | DU2: Data ingestion CRM_SIT | DV2: Data ingestion CRM_UAT
A3: Milestone 1 | B3: accounts | C3: CRM_DEV.finacle.CRMUSER_ACCOUNTS | E3: 46387 | H3: Milestone 1 | I3: ILCARDX | J3: CRM_DEV.prime4.TCTDBS_CARDX | O3: Milestone 1 | P3: WMS_INV_GEN_DTLS_TBL | Q3: 46035 | S3: 46035 | T3: 46035 | V3: Milestone1 | W3: CORPORATE_USER | Z3: 46038 | AJ3: Milestone1 | AK3: LEA_AGREEMENT_DTL | AL3: CRM_DEV.rls.FIN_LEAM_LEA_AGREEMENT_DTL | AX3: Milestone 3 | AY3: DX_TRNS_REMITTANCE | BE3: Milestone3 | BF3: Outward_ICCS | BL3: Milestone1 | BM3: wfinstrumenttable | BS3: Milestone3 | BT3: NPSS_PaymentsStatusConfig | BZ3: Milestone 2 | CA3: DeliveryRegistration | CU3: Milestone3 | CV3: CARD_GENERAL | CW3: CRM_DEV.caps.CAPSADMIN_CARD_GENERAL | DI3: Milestone2 | DJ3: customer_consent
A4: Milestone 1 | B4: corporate | C4: CRM_DEV.finacle.CRMUSER_CORPORATE | E4: 46387 | H4: Milestone 1 | I4: PEOPLE | J4: CRM_DEV.prime4.TCTDBS_PEOPLE | L4: 46030 | O4: Milestone 2 | P4: WMS_INV_GEN_DTLS_TBL | V4: Milestone1 | W4: MULTI_LEVEL_WORKFLOW_TABLE | AJ4: Milestone1 | AK4: NBFC_CUSTOMER_M | AX4: Milestone 3 | AY4: DX_REF_ACTIVITY_LOG | BE4: Milestone3 | BF4: ICCS_TAB_RoutingNumbers | BL4: Milestone1 | BM4: RB_PC_EXTTABLE | BS4: Milestone3 | BT4: NPSS_PmtStatus_ReqHdr | CU4: Milestone3 | CV4: CARDS | CW4: CRM_DEV.caps.CAPSADMIN_CARDS | DI4: Milestone2 | DJ4: customer_info
A5: Milestone 1 | B5: ENTITYDOCUMENT | C5: CRM_DEV.finacle.CRMUSER_ENTITYDOCUMENT | H5: Milestone 2 | I5: ILCARDEMBOSSING | J5: TCTDBS_CARDEMBOSSING | O5: Milestone 3 | P5: WMS_INV_GEN_DTLS_TBL | V5: Milestone2 | W5: CORPORATE_USER | AJ5: Milestone1 | AK5: LEA_APPL_DTL | AL5: CRM_DEV.rls.FIN_LEAM_LEA_APPL_DTL | AX5: Milestone 4 | AY5: DX_TRNS_REMITTANCE | BE5: Milestone3 | BF5: Inward_Ext_Tab | BL5: Milestone1 | BM5: RB_CMS_EXTTABLE | BS5: Milestone3 | BT5: NPSS_RTPaymentsDtl_Inw | DI5: Milestone2 | DJ5: consent_configs
A6: Milestone 1 | B6: Person | C6: CRM_DEV.finacle.CRMUSER_PERSON | E6: 46387 | H6: Milestone 2 | I6: ILCARDX | J6: CRM_DEV.prime4.TCTDBS_CARDX | AJ6: Milestone2 | AK6: LEA_AGREEMENT_DTL | AL6: CRM_DEV.rls.FIN_LEAM_LEA_AGREEMENT_DTL | AX6: Milestone 4 | AY6: DX_REF_ACTIVITY_LOG | BL6: Milestone1 | BM6: RB_ML_EXTTABLE | BS6: Milestone3 | BT6: NPSS_RTPaymentsDtl_InwExn | DI6: Milestone3 | DJ6: customer_consent
A7: Milestone 1 | B7: PhoneEmail | C7: CRM_DEV.finacle.CRMUSER_PHONEEMAIL | H7: Milestone 2 | I7: ILCACCOUNTS | J7: CRM_DEV.prime4.TCTDBS_CACCOUNTS | L7: 46030 | AJ7: Milestone2 | AK7: LEA_APPL_DTL | AL7: CRM_DEV.rls.FIN_LEAM_LEA_APPL_DTL | BL7: Milestone1 | BM7: RB_DAC_EXTTABLE | BS7: Milestone3 | BT7: NPSS_RTPaymentsDtl_Out | DI7: Milestone3 | DJ7: customer_info
A8: Milestone 1 | B8: categories | C8: CRM_DEV.finacle.CRMUSER_CATEGORIES | E8: 46024 | H8: Milestone 2 | I8: ILCURRENCIES | J8: CRM_DEV.prime4.TCTDBS_CURRENCIES | AJ8: Milestone2 | AK8: LEA_REPAYSCH_DTL | AL8: CRM_DEV.rls.FIN_LEAM_LEA_REPAYSCH_DTL | BL8: Milestone1 | BM8: RB_BSR_EXTTABLE | BS8: Milestone3 | BT8: NPSS_RTPaymentsDtl_OutExn | DI8: Milestone3 | DJ8: consent_configs
A9: Milestone 1 | B9: category_lang | C9: CRM_DEV.finacle.CRMUSER_CATEGORY_LANG | E9: 46024 | H9: Milestone 2 | I9: ILPRODUCTS | AJ9: Milestone2 | AK9: NBFC_CUSTOMER_M | BL9: Milestone1 | BM9: RB_iRBL_EXTTABLE | BS9: Milestone3 | BT9: NPSS_RTPaymentsHdr_Inw | DI9: Milestone3 | DJ9: customer_consent_audit
A10: Milestone 1 | B10: Incidents | H10: Milestone 2 | I10: ILCARDSTATUS | AJ10: Milestone3 | AK10: LEA_AGREEMENT_DTL | AL10: CRM_DEV.rls.FIN_LEAM_LEA_AGREEMENT_DTL | BL10: Milestone1 | BM10: RB_CSR_BT_EXTTABLE | BS10: Milestone3 | BT10: NPSS_RTPaymentsHdr_Out
A11: Milestone 2 | B11: Accounts | C11: CRM_DEV.finacle.CRMUSER_ACCOUNTS | E11: 46387 | H11: Milestone 2 | I11: ILCSTATEMENTS | J11: CRM_DEV.prime4.TCTDBS_CSTATEMENTS | L11: 46030 | AJ11: Milestone3 | AK11: NBFC_CUSTOMER_M | AL11: CRM_DEV.rls.FIN_LEAM_NBFC_CUSTOMER_M | BL11: Milestone1 | BM11: RB_CSR_CCB_EXTTABLE | BS11: Milestone3 | BT11: NPSS_RTS_PmtStatusDtl_Dbtr
A12: Milestone 2 | B12: agent_entity_details | C12: CRM_DEV.finacle.CRMUSER_AGENT_ENTITY_DETAILS | E12: 46387 | H12: Milestone 2 | I12: PEOPLE | J12: CRM_DEV.prime4.TCTDBS_PEOPLE | L12: 46030 | AJ12: Milestone3 | AK12: LEA_APPL_DTL | AL12: CRM_DEV.rls.FIN_LEAM_LEA_APPL_DTL | BL12: Milestone1 | BM12: RB_CSR_CCC_EXTTABLE
A13: Milestone 2 | B13: bizcenter | C13: CRM_DEV.finacle.CRMUSER_BIZCENTER | E13: 46025 | H13: Milestone 2 | I13: ILISSUER_AUTHORIZATIONS | BL13: Milestone1 | BM13: RB_CSR_MISC_EXTTABLE
A14: Milestone 2 | B14: Corporate | C14: CRM_DEV.finacle.CRMUSER_CORPORATE | E14: 46387 | H14: Milestone 2 | I14: iltbalances | J14: CRM_DEV.prime4.TCTDBS_TBALANCES | L14: 46030 | BL14: Milestone1 | BM14: RB_CSR_OCC_EXTTABLE
A15: Milestone 2 | B15: DEMOGRAPHIC | C15: CRM_DEV.finacle.CRMUSER_DEMOGRAPHIC | E15: 46387 | H15: Milestone3 | I15: CINSTALMENTS | BL15: Milestone1 | BM15: RB_CSR_RR_EXTTABLE
A16: Milestone 2 | B16: ENTITY_INTEREST_TABLE | C16: CRM_DEV.finacle.TBAADM_ENTITY_INTEREST_TABLE | H16: Milestone3 | I16: Cinstalmentamortization | J16: CRM_DEV.prime4.TCTDBS_CINSTALMENTAMORTIZATION | BL16: Milestone1 | BM16: RB_DSR_DCB_EXTTABLE
A17: Milestone 2 | B17: ENTITYDOCUMENT | C17: CRM_DEV.finacle.CRMUSER_ENTITYDOCUMENT | H17: Milestone3 | I17: ACPLINKS | BL17: Milestone1 | BM17: RB_DSR_MISC_EXTTABLE
A18: Milestone 2 | B18: EXTN_BODATA | H18: Milestone3 | I18: ACPROFILES | BL18: Milestone1 | BM18: RB_DSR_ODC_EXTTABLE
A19: Milestone 2 | B19: GENERAL_ACCT_MAST_TABLE | C19: CRM_DEV.finacle.TBAADM_GENERAL_ACCT_MAST_TABLE | E19: 46027 | H19: Milestone3 | I19: APPLOG | BL19: Milestone1 | BM19: RB_GSR_LCOL_EXTTABLE
A20: Milestone 2 | B20: MiscellaneousInfo | C20: CRM_DEV.finacle.CRMUSER_MISCELLANEOUSINFO | E20: 46028 | H20: Milestone3 | I20: BATCHES | J20: CRM_DEV.prime4.TCTDBS_BATCHES | BL20: Milestone1 | BM20: RB_ODDD_EXTTABLE
A21: Milestone 2 | B21: Person | C21: CRM_DEV.finacle.CRMUSER_PERSON | E21: 46387 | H21: Milestone3 | I21: CURRENCIES | J21: CRM_DEV.prime4.TCTDBS_CURRENCIES | BL21: Milestone1 | BM21: RB_DA_Exttable
A22: Milestone 2 | B22: PhoneEmail | C22: CRM_DEV.finacle.CRMUSER_PHONEEMAIL | H22: Milestone3 | I22: caccounts | J22: CRM_DEV.prime4.TCTDBS_CACCOUNTS | BL22: Milestone1 | BM22: RB_TF_EXTTABLE
A23: Milestone 2 | B23: SBCA_MAST_TABLE | C23: CRM_DEV.finacle.TBAADM_SBCA_MAST_TABLE | H23: Milestone3 | I23: CACCOUNTSTMT | J23: CRM_DEV.prime4.TCTDBS_CACCOUNTSTMT | BL23: Milestone1 | BM23: RB_SRB_EXTTABLE
A24: Milestone 2 | B24: TD_ACCT_MASTER_TABLE | C24: CRM_DEV.finacle.TBAADM_TD_ACCT_MASTER_TABLE | E24: 46027 | H24: Milestone3 | I24: CADDRESSES | J24: CRM_DEV.prime4.TCTDBS_CADDRESSES | BL24: Milestone1 | BM24: RB_AO_EXTTABLE
A25: Milestone 3 | B25: ACCT_AUTH_SIGN_TABLE | C25: CRM_DEV.finacle.TBAADM_ACCT_AUTH_SIGN_TABLE | E25: 46027 | H25: Milestone3 | I25: CARDEMBOSSING | J25: CRM_DEV.prime4.TCTDBS_CARDEMBOSSING | BL25: Milestone1 | BM25: RB_SRM_EXTTABLE
A26: Milestone 3 | B26: Accounts | C26: CRM_DEV.finacle.CRMUSER_ACCOUNTS | E26: 46387 | H26: Milestone3 | I26: CARDS | BL26: Milestone1 | BM26: RB_EPP_EXTTABLE
A27: Milestone 3 | B27: Address | C27: CRM_DEV.finacle.CRMUSER_ADDRESS | E27: 46028 | H27: Milestone3 | I27: CARDSTATUS | BL27: Milestone1 | BM27: RB_SAR_EXTTABLE
A28: Milestone 3 | B28: agent_entity_details | C28: CRM_DEV.finacle.CRMUSER_AGENT_ENTITY_DETAILS | E28: 46387 | H28: Milestone3 | I28: CARDX | J28: CRM_DEV.prime4.TCTDBS_CARDX | BL28: Milestone1 | BM28: RB_BAIS_EXTTABLE
A29: Milestone 3 | B29: ACH_PAYSYS_REASON_TABLE | H29: Milestone3 | I29: CCUSTOMERS | J29: CRM_DEV.prime4.TCTDBS_CCUSTOMERS | BL29: Milestone1 | BM29: NG_DCC_EXTTABLE
A30: Milestone 3 | B30: ACCT_STATEMENT_TABLE | C30: CRM_DEV.finacle.TBAADM_ACCT_STATEMENT_TABLE | E30: 46029 | H30: Milestone3 | I30: CEXTENSION | BL30: Milestone1 | BM30: NG_DAO_EXTTABLE
A31: Milestone 3 | B31: bizcenter | C31: CRM_DEV.finacle.CRMUSER_BIZCENTER | E31: 46387 | H31: Milestone3 | I31: CSTATEMENTS | J31: CRM_DEV.prime4.TCTDBS_CSTATEMENTS | BL31: Milestone1 | BM31: NG_TT_EXT_TABLE
A32: Milestone 3 | B32: CUST_LDFEE | H32: Milestone3 | I32: CISOTRXNS | BL32: Milestone1 | BM32: RB_TL_EXTTABLE
A33: Milestone 3 | B33: CUST_PAYGEN_ORD_TABLE | H33: Milestone3 | I33: CTRANSACTIONS | J33: CRM_DEV.prime4.TCTDBS_CTRANSACTIONS | BL33: Milestone1 | BM33: RB_SRO_EXTTABLE
A34: Milestone 3 | B34: C_PORD_REMIT_INR | H34: Milestone3 | I34: TRXNSTATUS | J34: CRM_DEV.prime4.TCTDBS_TRXNSTATUS | BL34: Milestone1 | BM34: RB_OECD_EXTTABLE
A35: Milestone 3 | B35: CUST_REJECT | H35: Milestone3 | I35: GLOBALPARAMETERVALUES | J35: CRM_DEV.prime4.TCTDBS_GLOBALPARAMETERVALUES | BL35: Milestone1 | BM35: RB_TWC_EXTTABLE
A36: Milestone 3 | B36: CMB_CSIS_GEN_ACCT_TABLE | H36: Milestone3 | I36: GLOBALPARAMETERS | J36: CRM_DEV.prime4.TCTDBS_GLOBALPARAMETERS | BL36: Milestone1 | BM36: RB_CU_EXTTABLE
A37: Milestone 3 | B37: CNMA | H37: Milestone3 | I37: GROUPS | BL37: Milestone1 | BM37: NG_DPL_EXTTABLE
A38: Milestone 3 | B38: Corporate | C38: CRM_DEV.finacle.CRMUSER_CORPORATE | E38: 46387 | H38: Milestone3 | I38: INSTALMENTPLANS | J38: CRM_DEV.prime4.TCTDBS_INSTALMENTPLANS | BL38: Milestone1 | BM38: RB_DBO_EXTTABLE
A39: Milestone 3 | B39: CUST_CALBK | H39: Milestone3 | I39: AUTHORIZATIONS | BL39: Milestone1 | BM39: RB_CMS_EXTTABLE
A40: Milestone 3 | B40: DEMOGRAPHIC | C40: CRM_DEV.finacle.CRMUSER_DEMOGRAPHIC | E40: 46024 | H40: Milestone3 | I40: MEMOS | BL40: Milestone1 | BM40: NG_TS_EXTTABLE
A41: Milestone 3 | B41: DAILY_TRAN_DETAIL_TABLE | C41: CRM_DEV.finacle.TBAADM_DAILY_TRAN_DETAIL_TABLE | E41: 46029 | H41: Milestone3 | I41: MEMOTYPES | J41: CRM_DEV.prime4.TCTDBS_MEMOTYPES | BL41: Milestone1 | BM41: RB_NBTL_EXTTABLE
A42: Milestone 3 | B42: ENTITY_INTEREST_TABLE | C42: CRM_DEV.finacle.TBAADM_ENTITY_INTEREST_TABLE | E42: 46029 | H42: Milestone3 | I42: PRODUCTS | BL42: Milestone1 | BM42: NG_EIBOR_EXTTABLE
A43: Milestone 3 | B43: ENTITYDOCUMENT | C43: CRM_DEV.finacle.CRMUSER_ENTITYDOCUMENT | H43: Milestone3 | I43: PROFILES | J43: CRM_DEV.prime4.TCTDBS_PROFILES | BL43: Milestone1 | BM43: ng_CourtOrder_exttable
A44: Milestone 3 | B44: entityrelationship | C44: CRM_DEV.finacle.CRMUSER_ENTITYRELATIONSHIP | E44: 46024 | H44: Milestone3 | I44: Trxntypes | BL44: Milestone1 | BM44: RB_KYC_REM_EXTTABLE
A45: Milestone 3 | B45: GEN_ACCT_MAST_MOD_TABLE | H45: Milestone3 | I45: tBalances | J45: CRM_DEV.prime4.TCTDBS_TBALANCES | BL45: Milestone1 | BM45: RB_DBS_EXTTABLE
A46: Milestone 3 | B46: GEN_ACCT_CLASS_TABLE | C46: CRM_DEV.finacle.TBAADM_GEN_ACCT_CLASS_TABLE | E46: 46029 | H46: Milestone3 | I46: archtBalances | J46: CRM_DEV.prime4.TCTDBS_ARCHTBALANCES | BL46: Milestone1 | BM46: RB_PL_EXTTABLE
A47: Milestone 3 | B47: GENERAL_ACCT_MAST_TABLE | C47: CRM_DEV.finacle.TBAADM_GENERAL_ACCT_MAST_TABLE | E47: 46030 | BL47: Milestone3 | BM47: wfinstrumenttable
A48: Milestone 3 | B48: SOL_GROUP_CONTROL_TABLE | C48: CRM_DEV.finacle.TBAADM_SOL_GROUP_CONTROL_TABLE | E48: 46030 | BL48: Milestone3 | BM48: RB_PC_EXTTABLE
A49: Milestone 3 | B49: GEN_SCHM_PARM_TABLE | C49: CRM_DEV.finacle.TBAADM_GEN_SCHM_PARM_TABLE | E49: 46030 | BL49: Milestone3 | BM49: RB_CMS_EXTTABLE
A50: Milestone 3 | B50: LOGIN_TABLE | C50: CRM_DEV.finacle.TBAADM_LOGIN_TABLE | E50: 46024 | BL50: Milestone3 | BM50: RB_ML_EXTTABLE
A51: Milestone 3 | B51: memberships | C51: CRM_DEV.finacle.CRMUSER_MEMBERSHIPS | E51: 46024 | BL51: Milestone3 | BM51: RB_DAC_EXTTABLE
A52: Milestone 3 | B52: MiscellaneousInfo | C52: CRM_DEV.finacle.CRMUSER_MISCELLANEOUSINFO | E52: 46030 | BL52: Milestone3 | BM52: RB_BSR_EXTTABLE
A53: Milestone 3 | B53: ML_MMSG_TBL | C53: CRM_DEV.finacle.TBAADM_ML_MMSG_TBL | E53: 46024 | BL53: Milestone3 | BM53: RB_iRBL_EXTTABLE
A54: Milestone 3 | B54: MEMO_PAD_TABLE | C54: CRM_DEV.finacle.TBAADM_MEMO_PAD_TABLE | E54: 46030 | BL54: Milestone3 | BM54: RB_CSR_BT_EXTTABLE
A55: Milestone 3 | B55: OPERATIONSREASONCODES_DEDUP | BL55: Milestone3 | BM55: RB_CSR_CCB_EXTTABLE
A56: Milestone 3 | B56: Person | C56: CRM_DEV.finacle.CRMUSER_PERSON | E56: 46387 | BL56: Milestone3 | BM56: RB_CSR_CCC_EXTTABLE
A57: Milestone 3 | B57: PhoneEmail | C57: CRM_DEV.finacle.CRMUSER_PHONEEMAIL | BL57: Milestone3 | BM57: RB_CSR_MISC_EXTTABLE
A58: Milestone 3 | B58: PAYMENT_ORDER_DETAIL_TABLE | BL58: Milestone3 | BM58: RB_CSR_OCC_EXTTABLE
A59: Milestone 3 | B59: PAYMENT_ORDER_HEADER_TABLE | BL59: Milestone3 | BM59: RB_CSR_RR_EXTTABLE
A60: Milestone 3 | B60: preferences | C60: CRM_DEV.finacle.CRMUSER_PREFERENCES | E60: 46025 | BL60: Milestone3 | BM60: RB_DSR_DCB_EXTTABLE
A61: Milestone 3 | B61: psychographic | C61: CRM_DEV.finacle.CRMUSER_PSYCHOGRAPHIC | E61: 46025 | BL61: Milestone3 | BM61: RB_DSR_MISC_EXTTABLE
A62: Milestone 3 | B62: SWIFT_MSG_HISTORY_TABLE | BL62: Milestone3 | BM62: RB_DSR_ODC_EXTTABLE
A63: Milestone 3 | B63: C_PORDM_DELETE | BL63: Milestone3 | BM63: RB_GSR_LCOL_EXTTABLE
A64: Milestone 3 | B64: SBCA_MAST_TABLE | C64: CRM_DEV.finacle.TBAADM_SBCA_MAST_TABLE | BL64: Milestone3 | BM64: RB_ODDD_EXTTABLE
A65: Milestone 3 | B65: SERVICE_OUTLET_TABLE | C65: CRM_DEV.finacle.TBAADM_SERVICE_OUTLET_TABLE | E65: 46030 | BL65: Milestone3 | BM65: RB_DA_Exttable
A66: Milestone 3 | B66: users | C66: CRM_DEV.finacle.CRMUSER_USERS | E66: 46025 | BL66: Milestone3 | BM66: RB_TF_EXTTABLE
A67: Milestone 4 | B67: accounts | C67: CRM_DEV.finacle.CRMUSER_ACCOUNTS | BL67: Milestone3 | BM67: RB_SRB_EXTTABLE
A68: Milestone 4 | B68: ACCT_AUTH_SIGN_TABLE | C68: CRM_DEV.finacle.TBAADM_ACCT_AUTH_SIGN_TABLE | E68: 46030 | BL68: Milestone3 | BM68: RB_AO_EXTTABLE
A69: Milestone 4 | B69: ADM | BL69: Milestone3 | BM69: RB_SRM_EXTTABLE
A70: Milestone 4 | B70: ALH | BL70: Milestone3 | BM70: RB_EPP_EXTTABLE
A71: Milestone 4 | B71: ALT | BL71: Milestone3 | BM71: RB_SAR_EXTTABLE
A72: Milestone 4 | B72: AST | BL72: Milestone3 | BM72: RB_BAIS_EXTTABLE
A73: Milestone 4 | B73: C_CPVALUE | BL73: Milestone3 | BM73: NG_DCC_EXTTABLE
A74: Milestone 4 | B74: C_CRDT | BL74: Milestone3 | BM74: NG_DAO_EXTTABLE
A75: Milestone 4 | B75: CBT | BL75: Milestone3 | BM75: NG_TT_EXT_TABLE
A76: Milestone 4 | B76: CNC | BL76: Milestone3 | BM76: RB_TL_EXTTABLE
A77: Milestone 4 | B77: corporate | C77: CRM_DEV.finacle.CRMUSER_CORPORATE | E77: 46025 | BL77: Milestone3 | BM77: RB_SRO_EXTTABLE
A78: Milestone 4 | B78: DTD | BL78: Milestone3 | BM78: RB_OECD_EXTTABLE
A79: Milestone 4 | B79: EIT | BL79: Milestone3 | BM79: RB_TWC_EXTTABLE
A80: Milestone 4 | B80: entityrelationship | C80: CRM_DEV.finacle.CRMUSER_ENTITYRELATIONSHIP | BL80: Milestone3 | BM80: RB_CU_EXTTABLE
A81: Milestone 4 | B81: EXTN_BODATA | BL81: Milestone3 | BM81: NG_DPL_EXTTABLE
A82: Milestone 4 | B82: FinancialDetails | BL82: Milestone3 | BM82: RB_DBO_EXTTABLE
A83: Milestone 4 | B83: GAC | BL83: Milestone3 | BM83: RB_CMS_EXTTABLE
A84: Milestone 4 | B84: GAM | BL84: Milestone3 | BM84: NG_TS_EXTTABLE
A85: Milestone 4 | B85: GSP | BL85: Milestone3 | BM85: RB_NBTL_EXTTABLE
A86: Milestone 4 | B86: Incidents | C86: CRM_DEV.finacle.CRMUSER_INCIDENTS | E86: 46030 | BL86: Milestone3 | BM86: NG_EIBOR_EXTTABLE
A87: Milestone 4 | B87: ITC | BL87: Milestone3 | BM87: ng_CourtOrder_exttable
A88: Milestone 4 | B88: PFT | BL88: Milestone3 | BM88: RB_KYC_REM_EXTTABLE
A89: Milestone 4 | B89: Request | BL89: Milestone3 | BM89: RB_DBS_EXTTABLE
A90: Milestone 4 | B90: RSTD | BL90: Milestone3 | BM90: RB_PL_EXTTABLE
A91: Milestone 4 | B91: SIH
A92: Milestone 4 | B92: TAM
A93: Milestone 4 | B93: TBA_RENEWAL_OPTION_TBL
A94: Milestone 4 | B94: TBA_TD_ACCT_MASTER_TBL
A95: Milestone 4 | B95: TDT
A96: Milestone 4 | B96: TSD

Sheet Environment
B3: Scope of testing | C3: PowerApps Front End | D3: Dataverse | E3: SQL DB | F3: Source Systems Data + Microservices | G3: Remarks | H3: Requirement SQL load
B4: Unit | C4: https://crm-dev.crm15.dynamics.com/ | D4: CRM-Dev | E4: CRM_DEV | F4: UAT2 (Databricks DEV) | G4: CRM-Dev Dataverse will continue to have limited test data | H4: All tables full load except transactional tables . TXN tables should be loaded with 1 yr data only
B5: QA (interim) | C5: https://crm-sit.crm15.dynamics.com | D5: CRM-SIT | G5: 1. QA is in progress in CRM-SIT FE. Will be eventually moved to CRM-UAT FE once data ingestion is complete. No impact as the Front-end is same and underlying DB is same 2. CRM_DEV SQL has data directly from source thru confluent
B6: QA, UAT, RA, VA | C6: https://crm-uat.crm15.dynamics.com/ | D6: CRM-UAT | G6: 1. Data ingestion to Dataverse UAT (Day0 and CDC) to be started based on new approach once CRM_PT SQL ingestion is complete
B7: PT, Data movement testing | C7: https://crm-pt.crm15.dynamics.com/ | D7: CRM-PT | E7: CRM_PT | G7: 1. Dedicated and temp environment for PT 2. Data movement testing can be performed only on the DB where new approach is implemented
B8: OAT /Replica | C8: https://crm-preprod.crm15.dynamics.com/ | D8: CRM-Preprod | E8: CRM_PREPROD | F8: UAT1 (Databricks Test) | H8: All tables full load except transactional tables . TXN tables should be loaded with 1 yr data only
B9: Pilot | C9: https://crm.crm15.dynamics.com | D9: CRM-Prod | E9: CRM_PROD | F9: PROD (Databricks PROD) | H9: All tables full load except transactional tables . TXN tables should be loaded with 1 yr data only

Sheet DataActions
A1: DB | B1: Environment | C1: Load type | D1: Source | E1: Task | F1: Priority | G1: Owner | H1: ETA | I1: Remarks
A2: - | B2: - | C2: - | D2: - | E2: Data Analysis and modeling remaining stories completion for M2, M3, M4 | F2: 1 | G2: Alok Pradhan
A3: - | B3: - | C3: - | D3: - | E3: Develop the ADF pipelines that will move the data for the Initial load (Data Engineering) from ADLS to ODS (CRM DB) | F3: 1 | G3: Batch :Sunil , Affan ,Karna & Sai Real time : Sunil | H3: Batch Systems :19-Mar Realtime systems : 27-Feb | I3: Batch is 4step process hence needs time till 19-March 1. Sunil to ingest data in ADLS using Confluent 2. Affan from ADLS to Databricks 3. Karna will help with design and Sai to devlopment of Databricks to CRMDB Pipeline 4. Sai to run the pipelines along with DBA
A4: - | B4: - | C4: - | D4: - | E4: Develop Confluent pipelines to Dataverse | F4: 1 | G4: Sunil | H4: POC Failed - NO APPROACH NO ETA | I4: Requires attention and support from Confluent
A5: - | B5: - | C5: - | D5: - | E5: SETUP CRM_PT, CRM_PREPROD DB instances. Create the DBs, Schemas, Partition logic, Partitions, Tables, Stored procedures, scheduled DB jobs. | F5: 1 | G5: DBA | I5: • export the DDLs for all CRM tables from Dev and apply those in PT • create and associate partitions for the transaction tables • Create the stored procedures for automatically provision the partitions and schedule the jobs for the same • create the stored procedures for keeping only the 12months rolling period data by purging the old partitions and schedule the associated jobs
A6: SQL | B6: DEV | C6: Day 0 | D6: Databricks Bronze Dev (UAT2) | E6: Data ingestion of remaining tables enabling M1, M2, M3, M4 defects and stories closure | F6: 1 | G6: Batch :Sunil , Affan ,Karna & Sai Real time : Sunil | H6: Batch Systems :19-Mar Realtime systems : 27-Feb | I6: Batch is 4step process hence needs time 1. Sunil to ingest data in ADLS using Confluent 2. Affan from ADLS to Databricks 3. Karna will help with design and Sai to devlopment of Databricks to CRMDB Pipeline 4. Sai to run the pipelines along with DBA
A7: SQL | B7: DEV | C7: CDC | D7: Source systems UAT2 | E7: CDC enablement of all tables enabling M1, M2, M3, M4 defects and stories closure | F7: 1 | G7: Sunil | H7: Real time Systems : 6-Mar
A8: Dataverse | B8: CRM-UAT | C8: Day 0 | D8: CRM_DEV SQL DB | E8: Cleaner Data ingestion of all tables enabling M1, M2, M3, M4 defects and stories closure | F8: 1 | G8: Karna | H8: All systems : 6-Mar | I8: Ingestion throufh ADF using Joins
A9: Dataverse | B9: CRM-UAT | C9: CDC | D9: Source systems UAT2 | E9: Cleaner Data ingestion of all tables enabling M1, M2, M3, M4 defects and stories closure | F9: 1 | G9: DE | I9: ASK IS NOT CLEAR
A10: SQL | B10: PT | C10: Day 0 | D10: Databricks Bronze Dev (UAT2) | E10: Execute loading | F10: 2 | G10: DE | H10: 46131 | I10: This will be stared after Dev & UAT are completed - Appoach change on 23-Jan initially SQL Sink connector was devloped to cater this requirement
A11: Approach | B11: PT | C11: CDC | D11: Source systems UAT2 | E11: Execute loading | F11: 2 | G11: DE | H11: 46131 | I11: This will be stared after Dev & UAT are completed
A12: Dataverse | B12: PT | C12: Day 0 | D12: CRM_PT SQL DB | E12: Execute loading | F12: 2 | G12: DE | H12: 46131 | I12: This will be stared after Dev & UAT are completed
A13: Dataverse | B13: PT | C13: CDC | D13: Source systems UAT2 | E13: Execute loading | F13: 2 | G13: DE | H13: 46131 | I13: This will be stared after Dev & UAT are completed
A14: SQL | B14: Preprod | C14: Day 0 | D14: Databricks Bronze Test (UAT1) | E14: Execute loading | F14: 3 | G14: DE | H14: 46131 | I14: PT & Prepod wil be done in parallel
A15: SQL | B15: Preprod | C15: CDC | D15: Source systems UAT1 | E15: Execute loading | F15: 3 | G15: DE | H15: 46131 | I15: PT & Prepod wil be done in parallel
A16: Dataverse | B16: Preprod | C16: Day 0 | D16: CRM_PREPROD SQL DB | E16: Execute loading | F16: 3 | G16: DE | H16: 46131 | I16: PT & Prepod wil be done in parallel
A17: Dataverse | B17: Preprod | C17: CDC | D17: Source systems UAT1 | E17: Execute loading | F17: 3 | G17: DE | H17: 46131 | I17: PT & Prepod wil be done in parallel

Sheet Data_EDC_old
D4: Development completion | I4: Data Ingestion Completion
B5: Type | C5: Flow | D5: ADLS Sink | E5: DLT Job | F5: ADF pipeline | G5: SQL Sink | H5: ADF Microbatches | I5: CRM_DEV Source - UAT 2 | J5: CRM_UAT Source - UAT 2 | K5: CRM_PT Source - UAT 2 | L5: CRM_PREPROD Source - UAT 1 | M5: Remarks
B6: SQL Day 0 | C6: Source -->( ADLS Sink ) --> ADLS --> (DLT jobs) --> Databricks Bronze --> (ADF pipeline) --> MS SQL | D6: 27-Feb Sunil | E6: 02-Mar Sai/Affan | F6: 02-Mar Sai | G6: NA | H6: NA | I6: 03Mar to 04Mar Sai | J6: NA | K6: 03Mar to 04Mar Sai | M6: 5 systems are still remaining to start from source to Confluent, 8 systems are still remaining to start from confluent to ADLS. we are also working User story and Bug s, (Sai's comment)-- For development I have enforced primary key is the blocker and and availablity of the tables in ADLS is the blocker
B7: SQL Batch systems | C7: Source -->( ADF ) --> Databricks Bronze --> (ADF pipeline) --> MS SQL | D7: NA | E7: NA | F7: 4-Mar Syeda & Sunil | G7: NA | H7: NA | I7: 05-Mar Sai | J7: NA | K7: 05-Mar Sai | M7: Syeda just got access
B8: SQL Continuous streaming | C8: Source --> (Confluent Kafka SQL SINK) --> MS SQL | D8: NA | E8: NA | F8: NA | G8: 05-Mar Sunil | H8: NA | I8: 05-Mar Sunil | J8: NA | K8: 06-Mar Sunil | M8: Need to work on CDC bugs to fix issue which are related to SQL Sink
B9: Dataverse Day 0 | C9: Source -->( ADLS Sink ) --> ADLS --> (DLT jobs) --> Databricks Bronze --> (ADF pipeline) --> Dataverse | D9: 27-Feb Sunil | E9: 02-Mar Sai | F9: 02-Mar Sai Microsoft review required before starting ingestion | G9: NA | H9: NA | I9: 03-Mar Sai | J9: 04-Mar Sai | K9: 04-Mar Sai | M9: for Contacts entity -- I have asked Alok and powerapps team for duplicated records issue and for Accounts entity I already ingested to DEV env and now working on rest of the three entites code development
B10: Dataverse Continuous streaming | C10: Source -->( ADLS Sink ) --> ADLS --> (DLT jobs) --> Databricks Bronze --> (ADF microbatch pipeline) --> Dataverse ADF microbatch should pick only delta of only 60+ fields and run every 1 min | D10: 27-Feb Sunil | E10: 03Mar to 04Mar Sai | F10: NA | G10: NA | H10: 06-Mar Sai Microsoft review required before starting ingestion | I10: 07-Mar Sai | J10: 08-Mar Sai | K10: 08-Mar Sai | M10: Microsoft review required before starting ingestion

Sheet pivot1
N1: Table already available Databricks Bronze DEV/TEST ? | P1: Table already available Databricks Bronze PROD ?
A3: Count of table available in Databricks Bronze DEV/TEST instances | B3: Column Labels | F3: Count of table Available in Databricks Bronze PROD instances | G3: Column Labels
A4: Row Labels | B4: No | C4: Yes | D4: Grand Total | F4: Row Labels | G4: No | H4: yes | I4: Grand Total | L4: Row Labels | M4: Grand Total | N4: No | O4: Yes | P4: No | Q4: Yes
A5: CAPS | B5: 5 | D5: 5 | F5: CAPS | G5: 5 | I5: 5 | L5: CAPS | M5: 5 | N5: 5 | P5: 5
A6: CASMEX | B6: 8 | D6: 8 | F6: CASMEX | G6: 6 | H6: 2 | I6: 8 | L6: CASMEX | M6: 8 | N6: 8 | P6: 6 | Q6: 2
A7: CCM | B7: 5 | C7: 1 | D7: 6 | F7: CCM | G7: 5 | H7: 1 | I7: 6 | L7: CCM | M7: 6 | N7: 5 | O7: 1 | P7: 5 | Q7: 1
A8: CPF | B8: 4 | D8: 4 | F8: CPF | H8: 4 | I8: 4 | L8: CPF | M8: 4 | N8: 4 | Q8: 4
A9: CPPS | B9: 3 | D9: 3 | F9: CPPS | G9: 3 | I9: 3 | L9: CPPS | M9: 3 | N9: 3 | P9: 3
A10: Digital Banking Admin | B10: 7 | D10: 7 | F10: Digital Banking Admin | G10: 7 | I10: 7 | L10: Digital Banking Admin | M10: 7 | N10: 7 | P10: 7
A11: Digital Onboarding Tracking | B11: 8 | D11: 8 | F11: Digital Onboarding Tracking | G11: 8 | I11: 8 | L11: Digital Onboarding Tracking | M11: 8 | N11: 8 | P11: 8
A12: Finacle | B12: 105 | C12: 2 | D12: 107 | F12: Finacle | G12: 63 | H12: 44 | I12: 107 | L12: Finacle | M12: 107 | N12: 105 | O12: 2 | P12: 63 | Q12: 44
A13: IBPS | B13: 44 | D13: 44 | F13: IBPS | G13: 31 | H13: 13 | I13: 44 | L13: IBPS | M13: 44 | N13: 44 | P13: 31 | Q13: 13
A14: ICCS | B14: 4 | D14: 4 | F14: ICCS | G14: 4 | I14: 4 | L14: ICCS | M14: 4 | N14: 4 | P14: 4
A15: IDD | B15: 1 | D15: 1 | F15: IDD | G15: 1 | I15: 1 | L15: IDD | M15: 1 | N15: 1 | P15: 1
A16: Infobip | B16: 1 | D16: 1 | F16: Infobip | G16: 1 | I16: 1 | L16: Infobip | M16: 1 | N16: 1 | P16: 1
A17: ONLINE | B17: 6 | D17: 6 | F17: ONLINE | G17: 6 | I17: 6 | L17: ONLINE | M17: 6 | N17: 6 | P17: 6
A18: Pay Hub Plus (NPSS Unity) | B18: 10 | D18: 10 | F18: Pay Hub Plus (NPSS Unity) | G18: 7 | H18: 3 | I18: 10 | L18: Pay Hub Plus (NPSS Unity) | M18: 10 | N18: 10 | P18: 7 | Q18: 3
A19: PRIME | B19: 38 | C19: 2 | D19: 40 | F19: PRIME | G19: 40 | I19: 40 | L19: PRIME | M19: 40 | N19: 38 | O19: 2 | P19: 40
A20: Prospect | B20: 1 | D20: 1 | F20: Prospect | G20: 1 | I20: 1 | L20: Prospect | M20: 1 | N20: 1 | P20: 1
A21: RLS | B21: 23 | D21: 23 | F21: RLS | G21: 20 | H21: 3 | I21: 23 | L21: RLS | M21: 23 | N21: 23 | P21: 20 | Q21: 3
A22: WMS | B22: 23 | D22: 23 | F22: WMS | G22: 20 | H22: 3 | I22: 23 | L22: WMS | M22: 23 | N22: 23 | P22: 20 | Q22: 3
A23: Grand Total | B23: 296 | C23: 5 | D23: 301 | F23: Grand Total | G23: 228 | H23: 73 | I23: 301 | L23: Grand Total | M23: 301 | N23: 296 | O23: 5 | P23: 228 | Q23: 73

Sheet Data_EDC
B3: Task Name | C3: Owner | D3: Milestone 1 | E3: Milestone 2 | F3: Milestone 3 | G3: Milestone 4 | H3: Remarks | K3: Task Name | L3: Duration | M3: Start | N3: Finish | O3: Risk/Dependency
B4: ADLS Sink (Source to ADLS) - Data pipeline dev | C4: Sunil K | D4: 46093 | E4: 46093 | F4: 46105 | G4: 46105 | H4: IBPS pending - M1 IDD, PROSPECT - WIP - M1 | K4: ADLS Sink (Source to ADLS) - Data pipeline dev | L4: 31 days | M4: Tue 2/10/26 | N4: Tue 3/24/26
B5: DLT jobs (ADLS to Databricks bronze) | C5: Sunil K | D5: 46093 | E5: 46093 | F5: 46108 | G5: 46107 | K5: Milestone 1 - Foundational Capabilities | L5: 23 days | M5: Tue 2/10/26 | N5: Thu 3/12/26
B6: ADF pipeline (Databricks bronze to SQL) | C6: SaiPrasad | D6: 46093 | E6: 46093 | F6: 46108 | G6: 46108 | K6: Milestone 2 - Customer-360 Individual | L6: 23 days | M6: Tue 2/10/26 | N6: Thu 3/12/26
B7: ADF batch pipeline (Databricks bronze to SQL) | C7: SaiPrasad | D7: 46093 | E7: 46093 | F7: 46112 | G7: 46114 | K7: Milestone 3 - Portfolio Drilldown | L7: 8 days | M7: Fri 3/13/26 | N7: Tue 3/24/26
B8: SQL Sink (Source to SQL) | C8: Sunil K | D8: 46093 | E8: 46093 | F8: 46105 | G8: 46104 | K8: Milestone 4 - Enquiries and Interactions | L8: 8 days | M8: Fri 3/13/26 | N8: Tue 3/24/26
B9: ADF pipeline (Databricks bronze to Dataverse) | C9: Syeda S | D9: 46098 | E9: 46098 | F9: - | G9: - | H9: Discussion with MS WIP. Country column cannot be populated. MS recommendations to be adhered to - Multiple users | K9: DLT jobs (ADLS to Databricks bronze) | L9: 15 days | M9: Mon 3/9/26 | N9: Fri 3/27/26
B10: ADF microbatch pipeline (Databricks bronze to Dataverse) | C10: Syeda S | D10: 46099 | E10: 46099 | F10: - | G10: - | H10: Discussion with MS WIP. Country column cannot be populated | K10: Milestone 1 - Foundational Capabilities | L10: 4 days | M10: Mon 3/9/26 | N10: Thu 3/12/26
B11: CRM_DEV SQL Day 0 load ingestion - strategic approach | C11: SaiPrasad | D11: 46099 | E11: 46101 | F11: 46121 | G11: 46121 | K11: Milestone 2 - Customer-360 Individual | L11: 3 days | M11: Tue 3/10/26 | N11: Thu 3/12/26
B12: CRM_DEV SQL Continuous streaming - strategic approach | C12: Sunil K | D12: 46107 | E12: 46111 | F12: 46129 | G12: 46129 | K12: Milestone 3 - Portfolio Drilldown | L12: 3 days | M12: Wed 3/25/26 | N12: Fri 3/27/26
B13: CRM_DEV SQL Batch system ingestion - strategic approach | C13: SaiPrasad | D13: 46098 | E13: 46098 | F13: 46118 | G13: 46120 | K13: Milestone 4 - Enquiries and Interactions | L13: 2 days | M13: Wed 3/25/26 | N13: Thu 3/26/26
B14: CRM_UAT Dataverse Day 0 load ingestion - strategic approach | C14: Syeda S | D14: 46106 | E14: 46106 | F14: - | G14: - | H14: Reported issue is not resolved yet . we will work as per Soheb suggestion | K14: ADF pipeline (Databricks bronze to SQL) | L14: 15 days | M14: Mon 3/9/26 | N14: Fri 3/27/26
B15: CRM-UAT Dataverse Continuous streaming (Micro batches) | C15: Syeda S | D15: 46107 | E15: 46107 | F15: - | G15: - | K15: Milestone 1 - Foundational Capabilities | L15: 4 days | M15: Mon 3/9/26 | N15: Thu 3/12/26
B16: Data movement testing - DEV env - Bronze, SQL (incl. CDC) | C16: Amit P | D16: 46108 | E16: 46113 | F16: 46139 | G16: 46139 | H16: Testing cannot complete as per these dates, because 1. Databricks Bronze location was confirmed and reshared on 24th March 2. Delivery package is delayed as per proposed plan on line 11 | K16: Milestone 2 - Customer-360 Individual | L16: 3 days | M16: Tue 3/10/26 | N16: Thu 3/12/26
B17: Data movement testing - UAT environment - Dataverse (incl CDC) | C17: Rana F | D17: 46111 | E17: 46111 | F17: - | G17: - | K17: Milestone 3 - Portfolio Drilldown | L17: 3 days | M17: Wed 3/25/26 | N17: Fri 3/27/26
B18: CRM_PT SQL Day 0 load ingestion - strategic approach | C18: SaiPrasad | D18: 46115 | E18: 46120 | F18: 46149 | G18: 46148 | K18: Milestone 4 - Enquiries and Interactions | L18: 3 days | M18: Wed 3/25/26 | N18: Fri 3/27/26
B19: CRM_PT SQL Continuous streaming - strategic approach | C19: Sunil K | D19: 46122 | E19: 46127 | F19: 46156 | G19: 46155 | K19: ADF batch pipeline (Databricks bronze to SQL) | L19: 18 days | M19: Tue 3/10/26 | N19: Thu 4/2/26
B20: CRM_PT SQL Batch system ingestion - strategic approach | C20: SaiPrasad | D20: 46113 | E20: 46118 | F20: 46143 | G20: 46143 | K20: Milestone 1 - Foundational Capabilities | L20: 3 days | M20: Tue 3/10/26 | N20: Thu 3/12/26
B21: CRM_PT Dataverse Day 0 load ingestion - strategic approach | C21: Syeda S | D21: 46119 | E21: 46119 | F21: - | G21: - | K21: Milestone 2 - Customer-360 Individual | L21: 2 days | M21: Wed 3/11/26 | N21: Thu 3/12/26
B22: CRM-PT Dataverse Continuous streaming (Micro batches) | C22: Syeda S | D22: 46121 | E22: 46121 | F22: - | G22: - | K22: Milestone 3 - Portfolio Drilldown | L22: 5 days | M22: Wed 3/25/26 | N22: Tue 3/31/26
B23: CRM_PREPROD SQL Day 0 load ingestion - strategic approach | C23: SaiPrasad | D23: 46120 | E23: 46122 | F23: 46151 | G23: 46150 | K23: Milestone 4 - Enquiries and Interactions | L23: 7 days | M23: Wed 3/25/26 | N23: Thu 4/2/26
B24: CRM_PREPROD SQL Continuous streaming - strategic approach | C24: Sunil K | D24: 46128 | E24: 46132 | F24: 46160 | G24: 46157 | K24: SQL Sink (Source to SQL) | L24: 17 days | M24: Mon 3/2/26 | N24: Tue 3/24/26
B25: CRM_PREPROD SQL Batch system ingestion - strategic approach | C25: SaiPrasad | D25: 46118 | E25: 46120 | F25: 46147 | G25: 46146 | K25: Milestone 1 - Foundational Capabilities | L25: 9 days | M25: Mon 3/2/26 | N25: Thu 3/12/26
B26: CRM_PREPROD Dataverse Day 0 load ingestion - strategic approach | C26: Syeda S | D26: 46121 | E26: 46121 | F26: - | G26: - | K26: Milestone 2 - Customer-360 Individual | L26: 8 days | M26: Tue 3/3/26 | N26: Thu 3/12/26
B27: CRM_PREPROD Dataverse Continuous streaming (Micro batches) | C27: Syeda S | D27: 46132 | E27: 46132 | F27: - | G27: - | K27: Milestone 3 - Portfolio Drilldown | L27: 8 days | M27: Fri 3/13/26 | N27: Tue 3/24/26
B28: CRM_PROD SQL Day 0 load ingestion - strategic approach | C28: SaiPrasad | D28: 46122 | E28: 46125 | F28: 46149 | G28: 46147 | K28: Milestone 4 - Enquiries and Interactions | L28: 7 days | M28: Fri 3/13/26 | N28: Mon 3/23/26
B29: CRM_PROD SQL Continuous streaming - strategic approach | C29: Sunil K | D29: 46129 | E29: 46132 | F29: 46155 | G29: 46155 | K29: ADF pipeline (Databricks bronze to Dataverse) | L29: 10 days | M29: Wed 3/4/26 | N29: Tue 3/17/26
B30: CRM_PROD SQL Batch system ingestion - strategic approach | C30: SaiPrasad | D30: 46119 | E30: 46120 | F30: 46146 | G30: 46146 | K30: Milestone 1 - Foundational Capabilities | L30: 10 days | M30: Wed 3/4/26 | N30: Tue 3/17/26
B31: CRM_PROD Dataverse Day 0 load ingestion - strategic approach | C31: Syeda S | D31: 46126 | E31: 46126 | F31: - | G31: - | K31: Milestone 2 - Customer-360 Individual | L31: 10 days | M31: Wed 3/4/26 | N31: Tue 3/17/26
B32: CRM-PROD Dataverse Continuous streaming (Micro batches) | C32: Syeda S | D32: 46129 | E32: 46129 | F32: - | G32: - | K32: ADF microbatch pipeline (Databricks bronze to Dataverse) | L32: 11 days | M32: Wed 3/4/26 | N32: Wed 3/18/26
B33: Data movement testing - PROD env - Bronze, SQL (incl. CDC) | C33: Amit P | D33: 46133 | E33: 46139 | F33: 46163 | G33: 46163 | K33: Milestone 1 - Foundational Capabilities | L33: 11 days | M33: Wed 3/4/26 | N33: Wed 3/18/26
B34: Data movement testing - PROD environment - Dataverse (incl CDC) | C34: Rana F | D34: 46134 | E34: 46134 | F34: - | G34: - | K34: Milestone 2 - Customer-360 Individual | L34: 11 days | M34: Wed 3/4/26 | N34: Wed 3/18/26
K35: CRM_DEV SQL Day 0 load ingestion - strategic approach | L35: 21 days | M35: Thu 3/12/26 | N35: Thu 4/9/26
K36: Milestone 1 - Foundational Capabilities | L36: 4 days | M36: Thu 3/12/26 | N36: Wed 3/18/26
K37: Milestone 2 - Customer-360 Individual | L37: 6 days | M37: Thu 3/12/26 | N37: Fri 3/20/26
K38: Milestone 3 - Portfolio Drilldown | L38: 9 days | M38: Mon 3/30/26 | N38: Thu 4/9/26
K39: Milestone 4 - Enquiries and Interactions | L39: 9 days | M39: Mon 3/30/26 | N39: Thu 4/9/26
K40: CRM_DEV SQL Continuous streaming - strategic approach | L40: 22.4 days | M40: Wed 3/18/26 | N40: Fri 4/17/26
K41: Milestone 1 - Foundational Capabilities | L41: 6 days | M41: Wed 3/18/26 | N41: Thu 3/26/26
K42: Milestone 2 - Customer-360 Individual | L42: 6 days | M42: Fri 3/20/26 | N42: Mon 3/30/26
K43: Milestone 3 - Portfolio Drilldown | L43: 6 days | M43: Fri 4/10/26 | N43: Fri 4/17/26
K44: Milestone 4 - Enquiries and Interactions | L44: 6 days | M44: Fri 4/10/26 | N44: Fri 4/17/26
K45: CRM_DEV SQL Batch system ingestion - strategic approach | L45: 19 days | M45: Fri 3/13/26 | N45: Wed 4/8/26
K46: Milestone 1 - Foundational Capabilities | L46: 3 days | M46: Fri 3/13/26 | N46: Tue 3/17/26
... K136: Milestone 2 - Customer-360 Individual | L136: 3 days | M136: Mon 4/20/26 | N136: Wed 4/22/26

Sheet New_IngestionSummary
D1: STRATEGIC APPROACH - FINAL
A2: Source Systems | B2: CRM DB (SQL) completion | L2: Dataverse completion
B3: Count of total tables - SQL DB | C3: Day-0 load in SQL DB DB : DEV Source : UAT 2 | D3: Continuous load in SQL DB DB : DEV Source : UAT 2 | E3: Batch load in SQL DB DB : DEV Source : UAT2 | F3: Day-0 load in SQL DB DB : PT Source : UAT 2 | G3: Continuous load in SQL DB DB : PT Source : UAT 2 | H3: Batch load in SQL DB DB : PT Source : UAT2 | I3: Day-0 load in SQL DB DB : PREPROD Source : UAT 1 | J3: Continuous load in SQL DB DB : PREPROD Source : UAT 1 | K3: Batch load in SQL DB DB : PREPROD Source : UAT1 | L3: Count of tables - Dataverse | M3: Day-0 load in Dataverse DB : DEV Source : UAT2 | N3: Continuous load in Dataverse DB : DEV Source : UAT2 | O3: Day-0 load in Dataverse DB : UAT Source : UAT2 | P3: Continuous load in Dataverse DB : UAT Source : UAT2 | Q3: Day-0 load in Dataverse DB : PT Source : UAT2 | R3: Continuous load in Dataverse DB : PT Source : UAT2 | S3: Day-0 load in Dataverse DB : PREPROD Source : UAT1 | T3: Continuous load in Dataverse DB : PREPROD Source : UAT1 | AD3: Tech owners | AG3: TXN tables
A4: Finacle | B4: =COUNTIF(New_SQL_Ing!C:C,New_IngestionSummary!A4) -> 116 | C4: =COUNTIFS(New_SQL_Ing!C:C,New_IngestionSummary!A4, New_SQL_Ing!R:R,"Done") -> 104 | D4: =COUNTIFS(New_SQL_Ing!C:C,New_IngestionSummary!A4,New_SQL_Ing!S:S,"Done") -> 59 | E4: - | F4: =COUNTIFS(New_SQL_Ing!C:C,New_IngestionSummary!A4, New_SQL_Ing!U:U,"Done") -> 65 | G4: =COUNTIFS(New_SQL_Ing!C:C,New_IngestionSummary!A4, New_SQL_Ing!V:V,"Done") -> 0 | H4: - | I4: =COUNTIFS(New_SQL_Ing!C:C,New_IngestionSummary!A4, New_SQL_Ing!X:X,"Done") -> 0 | J4: =COUNTIFS(New_SQL_Ing!C:C,New_IngestionSummary!A4, New_SQL_Ing!Y:Y,"Done") -> 0 | K4: - | L4: =COUNTIF(New_DV_Ing!I:I,New_IngestionSummary!A4) -> 12 | M4: =COUNTIFS(New_DV_Ing!I:I,New_IngestionSummary!A4,New_DV_Ing!O:O,"Done") -> 12 | N4: =COUNTIFS(New_DV_Ing!I:I,New_IngestionSummary!B4,New_DV_Ing!P:P,"Done") -> 0 | O4: =COUNTIFS(New_DV_Ing!I:I,New_IngestionSummary!E4,New_DV_Ing!Q:Q,"Done") -> 0 | P4: =COUNTIFS(New_DV_Ing!I:I,New_IngestionSummary!F4,New_DV_Ing!R:R,"Done") -> 0 | Q4: =COUNTIFS(New_DV_Ing!I:I,New_IngestionSummary!G4,New_DV_Ing!S:S,"Done") -> 0 | R4: =COUNTIFS(New_DV_Ing!I:I,New_IngestionSummary!H4,New_DV_Ing!T:T,"Done") -> 0 | S4: =COUNTIFS(New_DV_Ing!I:I,New_IngestionSummary!I4,New_DV_Ing!U:U,"Done") -> 0 | T4: =COUNTIFS(New_DV_Ing!I:I,New_IngestionSummary!J4,New_DV_Ing!V:V,"Done") -> 0 | AD4: Aananth | AG4: Product
A5: PRIME | B5: =COUNTIF(New_SQL_Ing!C:C,New_IngestionSummary!A5) -> 41 | C5: =COUNTIFS(New_SQL_Ing!C:C,New_IngestionSummary!A5, New_SQL_Ing!R:R,"Done") -> 38 | D5: =COUNTIFS(New_SQL_Ing!C:C,New_IngestionSummary!A5,New_SQL_Ing!S:S,"Done") -> 0 | E5: - | F5: =COUNTIFS(New_SQL_Ing!C:C,New_IngestionSummary!A5, New_SQL_Ing!U:U,"Done") -> 32 | G5: =COUNTIFS(New_SQL_Ing!C:C,New_IngestionSummary!A5, New_SQL_Ing!V:V,"Done") -> 0 | H5: - | I5: =COUNTIFS(New_SQL_Ing!C:C,New_IngestionSummary!A5, New_SQL_Ing!X:X,"Done") -> 0 | J5: =COUNTIFS(New_SQL_Ing!C:C,New_IngestionSummary!A5, New_SQL_Ing!Y:Y,"Done") -> 0 | K5: - | L5: =COUNTIF(New_DV_Ing!I:I,New_IngestionSummary!A5) -> 1 | M5: =COUNTIFS(New_DV_Ing!I:I,New_IngestionSummary!A5,New_DV_Ing!O:O,"Done") -> 1 | N5: =COUNTIFS(New_DV_Ing!I:I,New_IngestionSummary!B5,New_DV_Ing!P:P,"Done") -> 0 | O5: =COUNTIFS(New_DV_Ing!I:I,New_IngestionSummary!E5,New_DV_Ing!Q:Q,"Done") -> 0 | P5: =COUNTIFS(New_DV_Ing!I:I,New_IngestionSummary!F5,New_DV_Ing!R:R,"Done") -> 0 | Q5: =COUNTIFS(New_DV_Ing!I:I,New_IngestionSummary!G5,New_DV_Ing!S:S,"Done") -> 0 | R5: =COUNTIFS(New_DV_Ing!I:I,New_IngestionSummary!H5,New_DV_Ing!T:T,"Done") -> 0 | S5: =COUNTIFS(New_DV_Ing!I:I,New_IngestionSummary!I5,New_DV_Ing!U:U,"Done") -> 0 | T5: =COUNTIFS(New_DV_Ing!I:I,New_IngestionSummary!J5,New_DV_Ing!V:V,"Done") -> 0 | AD5: Srikanth or Abay | AG5: product
A6: ONLINE | B6: =COUNTIF(New_SQL_Ing!C:C,New_IngestionSummary!A6) -> 7 | C6: =COUNTIFS(New_SQL_Ing!C:C,New_IngestionSummary!A6, New_SQL_Ing!R:R,"Done") -> 5 | D6: =COUNTIFS(New_SQL_Ing!C:C,New_IngestionSummary!A6,New_SQL_Ing!S:S,"Done") -> 2 | E6: - | F6: =COUNTIFS(New_SQL_Ing!C:C,New_IngestionSummary!A6, New_SQL_Ing!U:U,"Done") -> 5 | G6: =COUNTIFS(New_SQL_Ing!C:C,New_IngestionSummary!A6, New_SQL_Ing!V:V,"Done") -> 0 | H6: - | I6: =COUNTIFS(New_SQL_Ing!C:C,New_IngestionSummary!A6, New_SQL_Ing!X:X,"Done") -> 0 | J6: =COUNTIFS(New_SQL_Ing!C:C,New_IngestionSummary!A6, New_SQL_Ing!Y:Y,"Done") -> 0 | K6: - | L6: - | M6: - | N6: - | O6: - | P6: - | Q6: - | R6: - | S6: - | T6: -
A7: WMS | B7: =COUNTIF(New_SQL_Ing!C:C,New_IngestionSummary!A7) -> 23 | C7: =COUNTIFS(New_SQL_Ing!C:C,New_IngestionSummary!A7, New_SQL_Ing!R:R,"Done") -> 1 | D7: =COUNTIFS(New_SQL_Ing!C:C,New_IngestionSummary!A7,New_SQL_Ing!S:S,"Done") -> 1 | E7: - | F7: =COUNTIFS(New_SQL_Ing!C:C,New_IngestionSummary!A7, New_SQL_Ing!U:U,"Done") -> 1 | G7: =COUNTIFS(New_SQL_Ing!C:C,New_IngestionSummary!A7, New_SQL_Ing!V:V,"Done") -> 0 | H7: - | I7: =COUNTIFS(New_SQL_Ing!C:C,New_IngestionSummary!A7, New_SQL_Ing!X:X,"Done") -> 0 | J7: =COUNTIFS(New_SQL_Ing!C:C,New_IngestionSummary!A7, New_SQL_Ing!Y:Y,"Done") -> 0 | K7: - | L7: =COUNTIF(New_DV_Ing!I:I,New_IngestionSummary!A7) -> 1 | M7: =COUNTIFS(New_DV_Ing!I:I,New_IngestionSummary!A7,New_DV_Ing!O:O,"Done") -> 1 | N7: =COUNTIFS(New_DV_Ing!I:I,New_IngestionSummary!B7,New_DV_Ing!P:P,"Done") -> 0 | O7: =COUNTIFS(New_DV_Ing!I:I,New_IngestionSummary!E7,New_DV_Ing!Q:Q,"Done") -> 0 | P7: =COUNTIFS(New_DV_Ing!I:I,New_IngestionSummary!F7,New_DV_Ing!R:R,"Done") -> 0 | Q7: =COUNTIFS(New_DV_Ing!I:I,New_IngestionSummary!G7,New_DV_Ing!S:S,"Done") -> 0 | R7: =COUNTIFS(New_DV_Ing!I:I,New_IngestionSummary!H7,New_DV_Ing!T:T,"Done") -> 0 | S7: =COUNTIFS(New_DV_Ing!I:I,New_IngestionSummary!I7,New_DV_Ing!U:U,"Done") -> 0 | T7: =COUNTIFS(New_DV_Ing!I:I,New_IngestionSummary!J7,New_DV_Ing!V:V,"Done") -> 0 | AD7: Aananth | AG7: Product
A8: IBPS | B8: =COUNTIF(New_SQL_Ing!C:C,New_IngestionSummary!A8) -> 219 | C8: =COUNTIFS(New_SQL_Ing!C:C,New_IngestionSummary!A8, New_SQL_Ing!R:R,"Done") -> 39 | D8: =COUNTIFS(New_SQL_Ing!C:C,New_IngestionSummary!A8,New_SQL_Ing!S:S,"Done") -> 39 | E8: - | F8: =COUNTIFS(New_SQL_Ing!C:C,New_IngestionSummary!A8, New_SQL_Ing!U:U,"Done") -> 39 | G8: =COUNTIFS(New_SQL_Ing!C:C,New_IngestionSummary!A8, New_SQL_Ing!V:V,"Done") -> 0 | H8: - | I8: =COUNTIFS(New_SQL_Ing!C:C,New_IngestionSummary!A8, New_SQL_Ing!X:X,"Done") -> 0 | J8: =COUNTIFS(New_SQL_Ing!C:C,New_IngestionSummary!A8, New_SQL_Ing!Y:Y,"Done") -> 0 | K8: - | L8: =COUNTIF(New_DV_Ing!I:I,New_IngestionSummary!A8) -> 1 | M8: =COUNTIFS(New_DV_Ing!I:I,New_IngestionSummary!A8,New_DV_Ing!O:O,"Done") -> 1 | N8: =COUNTIFS(New_DV_Ing!I:I,New_IngestionSummary!B8,New_DV_Ing!P:P,"Done") -> 0 | O8: =COUNTIFS(New_DV_Ing!I:I,New_IngestionSummary!E8,New_DV_Ing!Q:Q,"Done") -> 0 | P8: =COUNTIFS(New_DV_Ing!I:I,New_IngestionSummary!F8,New_DV_Ing!R:R,"Done") -> 0 | Q8: =COUNTIFS(New_DV_Ing!I:I,New_IngestionSummary!G8,New_DV_Ing!S:S,"Done") -> 0 | R8: =COUNTIFS(New_DV_Ing!I:I,New_IngestionSummary!H8,New_DV_Ing!T:T,"Done") -> 0 | S8: =COUNTIFS(New_DV_Ing!I:I,New_IngestionSummary!I8,New_DV_Ing!U:U,"Done") -> 0 | T8: =COUNTIFS(New_DV_Ing!I:I,New_IngestionSummary!J8,New_DV_Ing!V:V,"Done") -> 0 | AD8: NA
A9: CCM | B9: =COUNTIF(New_SQL_Ing!C:C,New_IngestionSummary!A9) -> 6 | C9: =COUNTIFS(New_SQL_Ing!C:C,New_IngestionSummary!A9, New_SQL_Ing!R:R,"Done") -> 1 | D9: =COUNTIFS(New_SQL_Ing!C:C,New_IngestionSummary!A9,New_SQL_Ing!S:S,"Done") -> 1 | E9: - | F9: =COUNTIFS(New_SQL_Ing!C:C,New_IngestionSummary!A9, New_SQL_Ing!U:U,"Done") -> 1 | G9: =COUNTIFS(New_SQL_Ing!C:C,New_IngestionSummary!A9, New_SQL_Ing!V:V,"Done") -> 0 | H9: - | I9: =COUNTIFS(New_SQL_Ing!C:C,New_IngestionSummary!A9, New_SQL_Ing!X:X,"Done") -> 0 | J9: =COUNTIFS(New_SQL_Ing!C:C,New_IngestionSummary!A9, New_SQL_Ing!Y:Y,"Done") -> 0 | K9: - | L9: - | M9: - | N9: - | O9: - | P9: - | Q9: - | R9: - | S9: - | T9: - | AD9: Charu
A10: CPF | B10: =COUNTIF(New_SQL_Ing!C:C,New_IngestionSummary!A10) -> 4 | C10: =COUNTIFS(New_SQL_Ing!C:C,New_IngestionSummary!A10, New_SQL_Ing!R:R,"Done") -> 4 | D10: =COUNTIFS(New_SQL_Ing!C:C,New_IngestionSummary!A10,New_SQL_Ing!S:S,"Done") -> 4 | E10: - | F10: =COUNTIFS(New_SQL_Ing!C:C,New_IngestionSummary!A10, New_SQL_Ing!U:U,"Done") -> 4 | G10: =COUNTIFS(New_SQL_Ing!C:C,New_IngestionSummary!A10, New_SQL_Ing!V:V,"Done") -> 0 | H10: - | I10: =COUNTIFS(New_SQL_Ing!C:C,New_IngestionSummary!A10, New_SQL_Ing!X:X,"Done") -> 0 | J10: =COUNTIFS(New_SQL_Ing!C:C,New_IngestionSummary!A10, New_SQL_Ing!Y:Y,"Done") -> 0 | K10: - | L10: - | M10: - | N10: - | O10: - | P10: - | Q10: - | R10: - | S10: - | T10: - | AD10: NA
A11: CASMEX | B11: =COUNTIF(New_SQL_Ing!C:C,New_IngestionSummary!A11) -> 8 | C11: =COUNTIFS(New_SQL_Ing!C:C,New_IngestionSummary!A11, New_SQL_Ing!R:R,"Done") -> 8 | D11: =COUNTIFS(New_SQL_Ing!C:C,New_IngestionSummary!A11,New_SQL_Ing!S:S,"Done") -> 8 | E11: - | F11: =COUNTIFS(New_SQL_Ing!C:C,New_IngestionSummary!A11, New_SQL_Ing!U:U,"Done") -> 7 | G11: =COUNTIFS(New_SQL_Ing!C:C,New_IngestionSummary!A11, New_SQL_Ing!V:V,"Done") -> 0 | H11: - | I11: =COUNTIFS(New_SQL_Ing!C:C,New_IngestionSummary!A11, New_SQL_Ing!X:X,"Done") -> 0 | J11: =COUNTIFS(New_SQL_Ing!C:C,New_IngestionSummary!A11, New_SQL_Ing!Y:Y,"Done") -> 0 | K11: - | L11: - | M11: - | N11: - | O11: - | P11: - | Q11: - | R11: - | S11: - | T11: - | AD11: Guru shetty | AG11: product
A12: Pay Hub Plus (NPSS Unity) | B12: =COUNTIF(New_SQL_Ing!C:C,New_IngestionSummary!A12) -> 13 | C12: =COUNTIFS(New_SQL_Ing!C:C,New_IngestionSummary!A12, New_SQL_Ing!R:R,"Done") -> 9 | D12: =COUNTIFS(New_SQL_Ing!C:C,New_IngestionSummary!A12,New_SQL_Ing!S:S,"Done") -> 0 | E12: - | F12: =COUNTIFS(New_SQL_Ing!C:C,New_IngestionSummary!A12, New_SQL_Ing!U:U,"Done") -> 9 | G12: =COUNTIFS(New_SQL_Ing!C:C,New_IngestionSummary!A12, New_SQL_Ing!V:V,"Done") -> 0 | H12: - | I12: =COUNTIFS(New_SQL_Ing!C:C,New_IngestionSummary!A12, New_SQL_Ing!X:X,"Done") -> 0 | J12: =COUNTIFS(New_SQL_Ing!C:C,New_IngestionSummary!A12, New_SQL_Ing!Y:Y,"Done") -> 0 | K12: - | L12: - | M12: - | N12: - | O12: - | P12: - | Q12: - | R12: - | S12: - | T12: - | AD12: Guru shetty | AG12: product
A13: Digital Onboarding Tracking | B13: =COUNTIF(New_SQL_Ing!C:C,New_IngestionSummary!A13) -> 8 | C13: =COUNTIFS(New_SQL_Ing!C:C,New_IngestionSummary!A13, New_SQL_Ing!R:R,"Done") -> 0 | D13: =COUNTIFS(New_SQL_Ing!C:C,New_IngestionSummary!A13,New_SQL_Ing!S:S,"Done") -> 0 | E13: - | F13: =COUNTIFS(New_SQL_Ing!C:C,New_IngestionSummary!A13, New_SQL_Ing!U:U,"Done") -> 0 | G13: =COUNTIFS(New_SQL_Ing!C:C,New_IngestionSummary!A13, New_SQL_Ing!V:V,"Done") -> 0 | H13: - | I13: =COUNTIFS(New_SQL_Ing!C:C,New_IngestionSummary!A13, New_SQL_Ing!X:X,"Done") -> 0 | J13: =COUNTIFS(New_SQL_Ing!C:C,New_IngestionSummary!A13, New_SQL_Ing!Y:Y,"Done") -> 0 | K13: - | L13: - | M13: - | N13: - | O13: - | P13: - | Q13: - | R13: - | S13: - | T13: - | AD13: NA
A14: ICCS | B14: =COUNTIF(New_SQL_Ing!C:C,New_IngestionSummary!A14) -> 4 | C14: =COUNTIFS(New_SQL_Ing!C:C,New_IngestionSummary!A14, New_SQL_Ing!R:R,"Done") -> 4 | D14: =COUNTIFS(New_SQL_Ing!C:C,New_IngestionSummary!A14,New_SQL_Ing!S:S,"Done") -> 0 | E14: - | F14: =COUNTIFS(New_SQL_Ing!C:C,New_IngestionSummary!A14, New_SQL_Ing!U:U,"Done") -> 4 | G14: =COUNTIFS(New_SQL_Ing!C:C,New_IngestionSummary!A14, New_SQL_Ing!V:V,"Done") -> 0 | H14: - | I14: =COUNTIFS(New_SQL_Ing!C:C,New_IngestionSummary!A14, New_SQL_Ing!X:X,"Done") -> 0 | J14: =COUNTIFS(New_SQL_Ing!C:C,New_IngestionSummary!A14, New_SQL_Ing!Y:Y,"Done") -> 0 | K14: - | L14: - | M14: - | N14: - | O14: - | P14: - | Q14: - | R14: - | S14: - | T14: - | AD14: NA | AG14: product
A15: Infobip | B15: =COUNTIF(New_SQL_Ing!C:C,New_IngestionSummary!A15) -> 1 | C15: =COUNTIFS(New_SQL_Ing!C:C,New_IngestionSummary!A15, New_SQL_Ing!R:R,"Done") -> 1 | D15: =COUNTIFS(New_SQL_Ing!C:C,New_IngestionSummary!A15,New_SQL_Ing!S:S,"Done") -> 0 | E15: - | F15: =COUNTIFS(New_SQL_Ing!C:C,New_IngestionSummary!A15, New_SQL_Ing!U:U,"Done") -> 0 | G15: =COUNTIFS(New_SQL_Ing!C:C,New_IngestionSummary!A15, New_SQL_Ing!V:V,"Done") -> 0 | H15: - | I15: =COUNTIFS(New_SQL_Ing!C:C,New_IngestionSummary!A15, New_SQL_Ing!X:X,"Done") -> 0 | J15: =COUNTIFS(New_SQL_Ing!C:C,New_IngestionSummary!A15, New_SQL_Ing!Y:Y,"Done") -> 0 | K15: - | L15: - | M15: - | N15: - | O15: - | P15: - | Q15: - | R15: - | S15: - | T15: - | AD15: Shiju | AE15: 6 months | AG15: interactions
A16: Digital Banking Admin | B16: =COUNTIF(New_SQL_Ing!C:C,New_IngestionSummary!A16) -> 8 | C16: - | D16: - | E16: =COUNTIFS(New_SQL_Ing!C:C,New_IngestionSummary!A16,New_SQL_Ing!T:T,"Done") -> 4 | F16: - | G16: - | H16: =COUNTIFS(New_SQL_Ing!C:C,New_IngestionSummary!A16, New_SQL_Ing!W:W,"Done") -> 3 | I16: - | J16: - | K16: =COUNTIFS(New_SQL_Ing!C:C,New_IngestionSummary!A16, New_SQL_Ing!Z:Z,"Done") -> 0 | L16: =COUNTIF(New_DV_Ing!I:I,New_IngestionSummary!A16) -> 2 | M16: =COUNTIFS(New_DV_Ing!I:I,New_IngestionSummary!A16,New_DV_Ing!O:O,"Done") -> 1 | N16: =COUNTIFS(New_DV_Ing!I:I,New_IngestionSummary!B16,New_DV_Ing!P:P,"Done") -> 0 | O16: =COUNTIFS(New_DV_Ing!I:I,New_IngestionSummary!E16,New_DV_Ing!Q:Q,"Done") -> 0 | P16: =COUNTIFS(New_DV_Ing!I:I,New_IngestionSummary!F16,New_DV_Ing!R:R,"Done") -> 0 | Q16: =COUNTIFS(New_DV_Ing!I:I,New_IngestionSummary!G16,New_DV_Ing!S:S,"Done") -> 0 | R16: =COUNTIFS(New_DV_Ing!I:I,New_IngestionSummary!H16,New_DV_Ing!T:T,"Done") -> 0 | S16: =COUNTIFS(New_DV_Ing!I:I,New_IngestionSummary!I16,New_DV_Ing!U:U,"Done") -> 0 | T16: =COUNTIFS(New_DV_Ing!I:I,New_IngestionSummary!J16,New_DV_Ing!V:V,"Done") -> 0 | AD16: NA | AE16: should be NA
A17: RLS | B17: =COUNTIF(New_SQL_Ing!C:C,New_IngestionSummary!A17) -> 23 | C17: - | D17: - | E17: =COUNTIFS(New_SQL_Ing!C:C,New_IngestionSummary!A17,New_SQL_Ing!T:T,"Done") -> 6 | F17: - | G17: - | H17: =COUNTIFS(New_SQL_Ing!C:C,New_IngestionSummary!A17, New_SQL_Ing!W:W,"Done") -> 6 | I17: - | J17: - | K17: =COUNTIFS(New_SQL_Ing!C:C,New_IngestionSummary!A17, New_SQL_Ing!Z:Z,"Done") -> 0 | L17: =COUNTIF(New_DV_Ing!I:I,New_IngestionSummary!A17) -> 1 | M17: =COUNTIFS(New_DV_Ing!I:I,New_IngestionSummary!A17,New_DV_Ing!O:O,"Done") -> 1 | N17: =COUNTIFS(New_DV_Ing!I:I,New_IngestionSummary!B17,New_DV_Ing!P:P,"Done") -> 0 | O17: =COUNTIFS(New_DV_Ing!I:I,New_IngestionSummary!E17,New_DV_Ing!Q:Q,"Done") -> 0 | P17: =COUNTIFS(New_DV_Ing!I:I,New_IngestionSummary!F17,New_DV_Ing!R:R,"Done") -> 0 | Q17: =COUNTIFS(New_DV_Ing!I:I,New_IngestionSummary!G17,New_DV_Ing!S:S,"Done") -> 0 | R17: =COUNTIFS(New_DV_Ing!I:I,New_IngestionSummary!H17,New_DV_Ing!T:T,"Done") -> 0 | S17: =COUNTIFS(New_DV_Ing!I:I,New_IngestionSummary!I17,New_DV_Ing!U:U,"Done") -> 0 | T17: =COUNTIFS(New_DV_Ing!I:I,New_IngestionSummary!J17,New_DV_Ing!V:V,"Done") -> 0 | AD17: Mani / Semeer | AG17: product
A18: CPPS | B18: =COUNTIF(New_SQL_Ing!C:C,New_IngestionSummary!A18) -> 3 | C18: - | D18: - | E18: =COUNTIFS(New_SQL_Ing!C:C,New_IngestionSummary!A18,New_SQL_Ing!T:T,"Done") -> 0 | F18: - | G18: - | H18: =COUNTIFS(New_SQL_Ing!C:C,New_IngestionSummary!A18, New_SQL_Ing!W:W,"Done") -> 0 | I18: - | J18: - | K18: =COUNTIFS(New_SQL_Ing!C:C,New_IngestionSummary!A18, New_SQL_Ing!Z:Z,"Done") -> 0 | L18: - | M18: - | N18: - | O18: - | P18: - | Q18: - | R18: - | S18: - | T18: - | AD18: Srikanth or Abay | AG18: product
A19: CAPS | B19: =COUNTIF(New_SQL_Ing!C:C,New_IngestionSummary!A19) -> 5 | C19: - | D19: - | E19: =COUNTIFS(New_SQL_Ing!C:C,New_IngestionSummary!A19,New_SQL_Ing!T:T,"Done") -> 3 | F19: - | G19: - | H19: =COUNTIFS(New_SQL_Ing!C:C,New_IngestionSummary!A19, New_SQL_Ing!W:W,"Done") -> 3 | I19: - | J19: - | K19: =COUNTIFS(New_SQL_Ing!C:C,New_IngestionSummary!A19, New_SQL_Ing!Z:Z,"Done") -> 0 | L19: - | M19: - | N19: - | O19: - | P19: - | Q19: - | R19: - | S19: - | T19: - | AD19: Srikanth or Abay | AG19: product
A20: IDD | B20: =COUNTIF(New_SQL_Ing!C:C,New_IngestionSummary!A20) -> 1 | C20: =COUNTIFS(New_SQL_Ing!C:C,New_IngestionSummary!A20, New_SQL_Ing!R:R,"Done") -> 1 | D20: =COUNTIFS(New_SQL_Ing!C:C,New_IngestionSummary!A20,New_SQL_Ing!S:S,"Done") -> 0 | E20: - | F20: - | G20: - | H20: - | I20: - | J20: - | K20: - | L20: =COUNTIF(New_DV_Ing!I:I,New_IngestionSummary!A20) -> 1 | M20: =COUNTIFS(New_DV_Ing!I:I,New_IngestionSummary!A20,New_DV_Ing!O:O,"Done") -> 0 | N20: =COUNTIFS(New_DV_Ing!I:I,New_IngestionSummary!B20,New_DV_Ing!P:P,"Done") -> 0 | O20: =COUNTIFS(New_DV_Ing!I:I,New_IngestionSummary!E20,New_DV_Ing!Q:Q,"Done") -> 0 | P20: =COUNTIFS(New_DV_Ing!I:I,New_IngestionSummary!F20,New_DV_Ing!R:R,"Done") -> 0 | Q20: =COUNTIFS(New_DV_Ing!I:I,New_IngestionSummary!G20,New_DV_Ing!S:S,"Done") -> 0 | R20: =COUNTIFS(New_DV_Ing!I:I,New_IngestionSummary!H20,New_DV_Ing!T:T,"Done") -> 0 | S20: =COUNTIFS(New_DV_Ing!I:I,New_IngestionSummary!I20,New_DV_Ing!U:U,"Done") -> 0 | T20: =COUNTIFS(New_DV_Ing!I:I,New_IngestionSummary!J20,New_DV_Ing!V:V,"Done") -> 0 | AD20: Gaurav | AG20: NA
A21: Prospect | B21: =COUNTIF(New_SQL_Ing!C:C,New_IngestionSummary!A21) -> 1 | C21: =COUNTIFS(New_SQL_Ing!C:C,New_IngestionSummary!A21, New_SQL_Ing!R:R,"Done") -> 1 | D21: =COUNTIFS(New_SQL_Ing!C:C,New_IngestionSummary!A21,New_SQL_Ing!S:S,"Done") -> 0 | E21: - | F21: - | G21: - | H21: - | I21: - | J21: - | K21: - | L21: =COUNTIF(New_DV_Ing!I:I,New_IngestionSummary!A21) -> 1 | M21: =COUNTIFS(New_DV_Ing!I:I,New_IngestionSummary!A21,New_DV_Ing!O:O,"Done") -> 1 | N21: =COUNTIFS(New_DV_Ing!I:I,New_IngestionSummary!B21,New_DV_Ing!P:P,"Done") -> 0 | O21: =COUNTIFS(New_DV_Ing!I:I,New_IngestionSummary!E21,New_DV_Ing!Q:Q,"Done") -> 0 | P21: =COUNTIFS(New_DV_Ing!I:I,New_IngestionSummary!F21,New_DV_Ing!R:R,"Done") -> 0 | Q21: =COUNTIFS(New_DV_Ing!I:I,New_IngestionSummary!G21,New_DV_Ing!S:S,"Done") -> 0 | R21: =COUNTIFS(New_DV_Ing!I:I,New_IngestionSummary!H21,New_DV_Ing!T:T,"Done") -> 0 | S21: =COUNTIFS(New_DV_Ing!I:I,New_IngestionSummary!I21,New_DV_Ing!U:U,"Done") -> 0 | T21: =COUNTIFS(New_DV_Ing!I:I,New_IngestionSummary!J21,New_DV_Ing!V:V,"Done") -> 0 | AD21: Gaurav | AG21: NA
A22: Grand Total | B22: =SUM(B4:B21) -> 491 | C22: =SUM(C4:C21) -> 216 | D22: =SUM(D4:D21) -> 114 | E22: =SUM(E4:E21) -> 13 | F22: =SUM(F4:F21) -> 167 | G22: =SUM(G4:G21) -> 0 | H22: =SUM(H4:H21) -> 12 | I22: =SUM(I4:I21) -> 0 | ... T22: =SUM(T4:T21) -> 0

Sheet DT_IngestionSummary
D1: STRATEGIC APPROACH - FINAL
B2: CRM DB (SQL) completion DEV | L2: Dataverse completion
A3: Source Systems | B3: Count of total tables - SQL DB | C3: Day-0 load in SQL DB DB : DEV Source : UAT 2 | D3: Continuous load in SQL DB DB : DEV Source : UAT 2 | E3: Batch load in SQL DB DB : DEV Source : UAT2 | F3: Day-0 load in SQL DB DB : PT Source : UAT 2 | G3: Continuous load in SQL DB DB : PT Source : UAT 2 | H3: Batch load in SQL DB DB : PT Source : UAT2 | I3: Day-0 load in SQL DB DB : PREPROD Source : UAT 1 | J3: Continuous load in SQL DB DB : PREPROD Source : UAT 1 | K3: Batch load in SQL DB DB : PREPROD Source : UAT1 | L3: Count of tables - Dataverse | M3: Day-0 load in Dataverse DB : DEV Source : UAT2 | N3: Continuous load in Dataverse DB : DEV Source : UAT2 | O3: Day-0 load in Dataverse DB : UAT Source : UAT2 | P3: Continuous load in Dataverse DB : UAT Source : UAT2 | Q3: Day-0 load in Dataverse DB : PT Source : UAT2 | R3: Continuous load in Dataverse DB : PT Source : UAT2 | S3: Day-0 load in Dataverse DB : PREPROD Source : UAT1 | T3: Continuous load in Dataverse DB : PREPROD Source : UAT1 | AD3: Tech owners | AG3: TXN tables
A4: Finacle | B4: =COUNTIF(New_SQL_Ing!C:C,DT_IngestionSummary!A4) -> 116 | C4: =COUNTIFS(New_SQL_Ing!C:C,DT_IngestionSummary!A4, New_SQL_Ing!R:R,"Done") -> 104 | D4: =COUNTIFS(New_SQL_Ing!C:C,DT_IngestionSummary!A4,New_SQL_Ing!S:S,"Done") -> 59 | E4: - | F4: =COUNTIFS(New_SQL_Ing!C:C,DT_IngestionSummary!A4, New_SQL_Ing!U:U,"Done") -> 65 | G4: =COUNTIFS(New_SQL_Ing!C:C,DT_IngestionSummary!A4, New_SQL_Ing!V:V,"Done") -> 0 | H4: - | I4: =COUNTIFS(New_SQL_Ing!C:C,DT_IngestionSummary!A4, New_SQL_Ing!X:X,"Done") -> 0 | J4: =COUNTIFS(New_SQL_Ing!C:C,DT_IngestionSummary!A4, New_SQL_Ing!Y:Y,"Done") -> 0 | K4: - | L4: =COUNTIF(New_DV_Ing!I:I,DT_IngestionSummary!A4) -> 12 | M4: =COUNTIFS(New_DV_Ing!I:I,DT_IngestionSummary!A4,New_DV_Ing!O:O,"Done") -> 12 | N4: =COUNTIFS(New_DV_Ing!I:I,DT_IngestionSummary!B4,New_DV_Ing!P:P,"Done") -> 0 | O4: =COUNTIFS(New_DV_Ing!I:I,DT_IngestionSummary!E4,New_DV_Ing!Q:Q,"Done") -> 0 | P4: =COUNTIFS(New_DV_Ing!I:I,DT_IngestionSummary!F4,New_DV_Ing!R:R,"Done") -> 0 | Q4: =COUNTIFS(New_DV_Ing!I:I,DT_IngestionSummary!G4,New_DV_Ing!S:S,"Done") -> 0 | R4: =COUNTIFS(New_DV_Ing!I:I,DT_IngestionSummary!H4,New_DV_Ing!T:T,"Done") -> 0 | S4: =COUNTIFS(New_DV_Ing!I:I,DT_IngestionSummary!I4,New_DV_Ing!U:U,"Done") -> 0 | T4: =COUNTIFS(New_DV_Ing!I:I,DT_IngestionSummary!J4,New_DV_Ing!V:V,"Done") -> 0 | AD4: Aananth | AG4: Product
A5: Finacle-M1 | B5: 8 | C5: 8 | D5: 8
A6: Finacle-M2 | B6: 9 | C6: 9 | D6: 9
A7: Finacle-M3 | B7: 38 | C7: 34 | D7: 28
A8: Finacle-M4 | B8: 19 | C8: 14 | D8: 14
A9: PRIME | B9: =COUNTIF(New_SQL_Ing!C:C,DT_IngestionSummary!A9) -> 41 | C9: =COUNTIFS(New_SQL_Ing!C:C,DT_IngestionSummary!A9, New_SQL_Ing!R:R,"Done") -> 38 | D9: =COUNTIFS(New_SQL_Ing!C:C,DT_IngestionSummary!A9,New_SQL_Ing!S:S,"Done") -> 0 | E9: - | F9: =COUNTIFS(New_SQL_Ing!C:C,DT_IngestionSummary!A9, New_SQL_Ing!U:U,"Done") -> 32 | G9: =COUNTIFS(New_SQL_Ing!C:C,DT_IngestionSummary!A9, New_SQL_Ing!V:V,"Done") -> 0 | H9: - | I9: =COUNTIFS(New_SQL_Ing!C:C,DT_IngestionSummary!A9, New_SQL_Ing!X:X,"Done") -> 0 | J9: =COUNTIFS(New_SQL_Ing!C:C,DT_IngestionSummary!A9, New_SQL_Ing!Y:Y,"Done") -> 0 | K9: - | L9: =COUNTIF(New_DV_Ing!I:I,DT_IngestionSummary!A9) -> 1 | M9: =COUNTIFS(New_DV_Ing!I:I,DT_IngestionSummary!A9,New_DV_Ing!O:O,"Done") -> 1 | N9: =COUNTIFS(New_DV_Ing!I:I,DT_IngestionSummary!B9,New_DV_Ing!P:P,"Done") -> 0 | O9: =COUNTIFS(New_DV_Ing!I:I,DT_IngestionSummary!E9,New_DV_Ing!Q:Q,"Done") -> 0 | P9: =COUNTIFS(New_DV_Ing!I:I,DT_IngestionSummary!F9,New_DV_Ing!R:R,"Done") -> 0 | Q9: =COUNTIFS(New_DV_Ing!I:I,DT_IngestionSummary!G9,New_DV_Ing!S:S,"Done") -> 0 | R9: =COUNTIFS(New_DV_Ing!I:I,DT_IngestionSummary!H9,New_DV_Ing!T:T,"Done") -> 0 | S9: =COUNTIFS(New_DV_Ing!I:I,DT_IngestionSummary!I9,New_DV_Ing!U:U,"Done") -> 0 | T9: =COUNTIFS(New_DV_Ing!I:I,DT_IngestionSummary!J9,New_DV_Ing!V:V,"Done") -> 0 | AD9: Srikanth or Abay | AG9: product
A10: PRIME-M1 | B10: 2 | C10: 2 | D10: 0
A11: PRIME-M2 | B11: 7 | C11: 7 | D11: 0
A12: PRIME-M3 | B12: 25 | C12: 21 | D12: 0
A13: PRIME-M4 | B13: 1 | C13: 0 | D13: 0
A14: ONLINE | B14: =COUNTIF(New_SQL_Ing!C:C,DT_IngestionSummary!A14) -> 7 | C14: =COUNTIFS(New_SQL_Ing!C:C,DT_IngestionSummary!A14, New_SQL_Ing!R:R,"Done") -> 5 | D14: =COUNTIFS(New_SQL_Ing!C:C,DT_IngestionSummary!A14,New_SQL_Ing!S:S,"Done") -> 2 | E14: - | F14: =COUNTIFS(New_SQL_Ing!C:C,DT_IngestionSummary!A14, New_SQL_Ing!U:U,"Done") -> 5 | G14: =COUNTIFS(New_SQL_Ing!C:C,DT_IngestionSummary!A14, New_SQL_Ing!V:V,"Done") -> 0 | H14: - | I14: =COUNTIFS(New_SQL_Ing!C:C,DT_IngestionSummary!A14, New_SQL_Ing!X:X,"Done") -> 0 | J14: =COUNTIFS(New_SQL_Ing!C:C,DT_IngestionSummary!A14, New_SQL_Ing!Y:Y,"Done") -> 0 | K14: - | L14: - | M14: - | N14: - | O14: - | P14: - | Q14: - | R14: - | S14: - | T14: -
A15: Online-M1 | B15: 0 | C15: 0 | D15: 0
A16: Online-M2 | B16: 2 | C16: 2 | D16: 0
A17: Online-M3 | B17: 2 | C17: 0 | D17: 0
A18: Online-M4 | B18: 1 | C18: 0 | D18: 0
A19: WMS | B19: =COUNTIF(New_SQL_Ing!C:C,DT_IngestionSummary!A19) -> 23 | C19: =COUNTIFS(New_SQL_Ing!C:C,DT_IngestionSummary!A19, New_SQL_Ing!R:R,"Done") -> 1 | D19: =COUNTIFS(New_SQL_Ing!C:C,DT_IngestionSummary!A19,New_SQL_Ing!S:S,"Done") -> 1 | E19: - | F19: =COUNTIFS(New_SQL_Ing!C:C,DT_IngestionSummary!A19, New_SQL_Ing!U:U,"Done") -> 1 | G19: =COUNTIFS(New_SQL_Ing!C:C,DT_IngestionSummary!A19, New_SQL_Ing!V:V,"Done") -> 0 | H19: - | I19: =COUNTIFS(New_SQL_Ing!C:C,DT_IngestionSummary!A19, New_SQL_Ing!X:X,"Done") -> 0 | J19: =COUNTIFS(New_SQL_Ing!C:C,DT_IngestionSummary!A19, New_SQL_Ing!Y:Y,"Done") -> 0 | K19: - | L19: =COUNTIF(New_DV_Ing!I:I,DT_IngestionSummary!A19) -> 1 | M19: =COUNTIFS(New_DV_Ing!I:I,DT_IngestionSummary!A19,New_DV_Ing!O:O,"Done") -> 1 | N19: =COUNTIFS(New_DV_Ing!I:I,DT_IngestionSummary!B19,New_DV_Ing!P:P,"Done") -> 0 | O19: =COUNTIFS(New_DV_Ing!I:I,DT_IngestionSummary!E19,New_DV_Ing!Q:Q,"Done") -> 0 | P19: =COUNTIFS(New_DV_Ing!I:I,DT_IngestionSummary!F19,New_DV_Ing!R:R,"Done") -> 0 | Q19: =COUNTIFS(New_DV_Ing!I:I,DT_IngestionSummary!G19,New_DV_Ing!S:S,"Done") -> 0 | R19: =COUNTIFS(New_DV_Ing!I:I,DT_IngestionSummary!H19,New_DV_Ing!T:T,"Done") -> 0 | S19: =COUNTIFS(New_DV_Ing!I:I,DT_IngestionSummary!I19,New_DV_Ing!U:U,"Done") -> 0 | T19: =COUNTIFS(New_DV_Ing!I:I,DT_IngestionSummary!J19,New_DV_Ing!V:V,"Done") -> 0 | AD19: Aananth | AG19: Product
A20: WMS-M1 | B20: 1 | C20: 1 | D20: 1
A21: IBPS | B21: =COUNTIF(New_SQL_Ing!C:C,DT_IngestionSummary!A21) -> 219 | C21: =COUNTIFS(New_SQL_Ing!C:C,DT_IngestionSummary!A21, New_SQL_Ing!R:R,"Done") -> 39 | D21: =COUNTIFS(New_SQL_Ing!C:C,DT_IngestionSummary!A21,New_SQL_Ing!S:S,"Done") -> 39 | E21: - | F21: =COUNTIFS(New_SQL_Ing!C:C,DT_IngestionSummary!A21, New_SQL_Ing!U:U,"Done") -> 39 | G21: =COUNTIFS(New_SQL_Ing!C:C,DT_IngestionSummary!A21, New_SQL_Ing!V:V,"Done") -> 0 | H21: - | I21: =COUNTIFS(New_SQL_Ing!C:C,DT_IngestionSummary!A21, New_SQL_Ing!X:X,"Done") -> 0 | J21: =COUNTIFS(New_SQL_Ing!C:C,DT_IngestionSummary!A21, New_SQL_Ing!Y:Y,"Done") -> 0 | K21: - | L21: =COUNTIF(New_DV_Ing!I:I,DT_IngestionSummary!A21) -> 1 | M21: =COUNTIFS(New_DV_Ing!I:I,DT_IngestionSummary!A21,New_DV_Ing!O:O,"Done") -> 1 | N21: =COUNTIFS(New_DV_Ing!I:I,DT_IngestionSummary!B21,New_DV_Ing!P:P,"Done") -> 0 | O21: =COUNTIFS(New_DV_Ing!I:I,DT_IngestionSummary!E21,New_DV_Ing!Q:Q,"Done") -> 0 | P21: =COUNTIFS(New_DV_Ing!I:I,DT_IngestionSummary!F21,New_DV_Ing!R:R,"Done") -> 0 | Q21: =COUNTIFS(New_DV_Ing!I:I,DT_IngestionSummary!G21,New_DV_Ing!S:S,"Done") -> 0 | R21: =COUNTIFS(New_DV_Ing!I:I,DT_IngestionSummary!H21,New_DV_Ing!T:T,"Done") -> 0 | S21: =COUNTIFS(New_DV_Ing!I:I,DT_IngestionSummary!I21,New_DV_Ing!U:U,"Done") -> 0 | T21: =COUNTIFS(New_DV_Ing!I:I,DT_IngestionSummary!J21,New_DV_Ing!V:V,"Done") -> 0 | AD21: NA
A22: IBPS-M1 | B22: 43 | C22: 0 | D22: 0
A23: IBPS-M2 | B23: 1 | C23: 0 | D23: 0
A24: CCM | B24: =COUNTIF(New_SQL_Ing!C:C,DT_IngestionSummary!A24) -> 6 | C24: =COUNTIFS(New_SQL_Ing!C:C,DT_IngestionSummary!A24, New_SQL_Ing!R:R,"Done") -> 1 | D24: =COUNTIFS(New_SQL_Ing!C:C,DT_IngestionSummary!A24,New_SQL_Ing!S:S,"Done") -> 1 | E24: - | F24: =COUNTIFS(New_SQL_Ing!C:C,DT_IngestionSummary!A24, New_SQL_Ing!U:U,"Done") -> 1 | G24: =COUNTIFS(New_SQL_Ing!C:C,DT_IngestionSummary!A24, New_SQL_Ing!V:V,"Done") -> 0 | H24: - | I24: =COUNTIFS(New_SQL_Ing!C:C,DT_IngestionSummary!A24, New_SQL_Ing!X:X,"Done") -> 0 | J24: =COUNTIFS(New_SQL_Ing!C:C,DT_IngestionSummary!A24, New_SQL_Ing!Y:Y,"Done") -> 0 | K24: - | L24: - | M24: - | N24: - | O24: - | P24: - | Q24: - | R24: - | S24: - | T24: - | AD24: Charu
A25: CCM-M1 | B25: 1 | C25: 1 | D25: 1
A26: CPF | B26: =COUNTIF(New_SQL_Ing!C:C,DT_IngestionSummary!A26) -> 4 | C26: =COUNTIFS(New_SQL_Ing!C:C,DT_IngestionSummary!A26, New_SQL_Ing!R:R,"Done") -> 4 | D26: =COUNTIFS(New_SQL_Ing!C:C,DT_IngestionSummary!A26,New_SQL_Ing!S:S,"Done") -> 4 | E26: - | F26: =COUNTIFS(New_SQL_Ing!C:C,DT_IngestionSummary!A26, New_SQL_Ing!U:U,"Done") -> 4 | G26: =COUNTIFS(New_SQL_Ing!C:C,DT_IngestionSummary!A26, New_SQL_Ing!V:V,"Done") -> 0 | H26: - | I26: =COUNTIFS(New_SQL_Ing!C:C,DT_IngestionSummary!A26, New_SQL_Ing!X:X,"Done") -> 0 | J26: =COUNTIFS(New_SQL_Ing!C:C,DT_IngestionSummary!A26, New_SQL_Ing!Y:Y,"Done") -> 0 | K26: - | L26: - | M26: - | N26: - | O26: - | P26: - | Q26: - | R26: - | S26: - | T26: - | AD26: NA
A27: CPF-M2 | B27: 3 | C27: 3 | D27: 3
A28: CPF-M3 | B28: 1 | C28: 0 | D28: 0
A29: CASMEX | B29: =COUNTIF(New_SQL_Ing!C:C,DT_IngestionSummary!A29) -> 8 | C29: =COUNTIFS(New_SQL_Ing!C:C,DT_IngestionSummary!A29, New_SQL_Ing!R:R,"Done") -> 8 | D29: =COUNTIFS(New_SQL_Ing!C:C,DT_IngestionSummary!A29,New_SQL_Ing!S:S,"Done") -> 8 | E29: - | F29: =COUNTIFS(New_SQL_Ing!C:C,DT_IngestionSummary!A29, New_SQL_Ing!U:U,"Done") -> 7 | G29: =COUNTIFS(New_SQL_Ing!C:C,DT_IngestionSummary!A29, New_SQL_Ing!V:V,"Done") -> 0 | H29: - | I29: =COUNTIFS(New_SQL_Ing!C:C,DT_IngestionSummary!A29, New_SQL_Ing!X:X,"Done") -> 0 | J29: =COUNTIFS(New_SQL_Ing!C:C,DT_IngestionSummary!A29, New_SQL_Ing!Y:Y,"Done") -> 0 | K29: - | L29: - | M29: - | N29: - | O29: - | P29: - | Q29: - | R29: - | S29: - | T29: - | AD29: Guru shetty | AG29: product
A30: CASMEX-M3 | B30: 8 | C30: 7 | D30: 0
A31: Pay Hub Plus (NPSS Unity) | B31: =COUNTIF(New_SQL_Ing!C:C,DT_IngestionSummary!A31) -> 13 | C31: =COUNTIFS(New_SQL_Ing!C:C,DT_IngestionSummary!A31, New_SQL_Ing!R:R,"Done") -> 9 | D31: =COUNTIFS(New_SQL_Ing!C:C,DT_IngestionSummary!A31,New_SQL_Ing!S:S,"Done") -> 0 | E31: - | F31: =COUNTIFS(New_SQL_Ing!C:C,DT_IngestionSummary!A31, New_SQL_Ing!U:U,"Done") -> 9 | G31: =COUNTIFS(New_SQL_Ing!C:C,DT_IngestionSummary!A31, New_SQL_Ing!V:V,"Done") -> 0 | H31: - | I31: =COUNTIFS(New_SQL_Ing!C:C,DT_IngestionSummary!A31, New_SQL_Ing!X:X,"Done") -> 0 | J31: =COUNTIFS(New_SQL_Ing!C:C,DT_IngestionSummary!A31, New_SQL_Ing!Y:Y,"Done") -> 0 | K31: - | L31: - | M31: - | N31: - | O31: - | P31: - | Q31: - | R31: - | S31: - | T31: - | AD31: Guru shetty | AG31: product
A32: NPSS-M3 | B32: 9 | C32: 0 | D32: 0
A33: Digital Onboarding Tracking | B33: =COUNTIF(New_SQL_Ing!C:C,DT_IngestionSummary!A33) -> 8 | C33: =COUNTIFS(New_SQL_Ing!C:C,DT_IngestionSummary!A33, New_SQL_Ing!R:R,"Done") -> 0 | D33: =COUNTIFS(New_SQL_Ing!C:C,DT_IngestionSummary!A33,New_SQL_Ing!S:S,"Done") -> 0 | E33: - | F33: =COUNTIFS(New_SQL_Ing!C:C,DT_IngestionSummary!A33, New_SQL_Ing!U:U,"Done") -> 0 | G33: =COUNTIFS(New_SQL_Ing!C:C,DT_IngestionSummary!A33, New_SQL_Ing!V:V,"Done") -> 0 | H33: - | I33: =COUNTIFS(New_SQL_Ing!C:C,DT_IngestionSummary!A33, New_SQL_Ing!X:X,"Done") -> 0 | J33: =COUNTIFS(New_SQL_Ing!C:C,DT_IngestionSummary!A33, New_SQL_Ing!Y:Y,"Done") -> 0 | K33: - | L33: - | M33: - | N33: - | O33: - | P33: - | Q33: - | R33: - | S33: - | T33: - | AD33: NA
A34: ICCS | B34: =COUNTIF(New_SQL_Ing!C:C,DT_IngestionSummary!A34) -> 4 | C34: =COUNTIFS(New_SQL_Ing!C:C,DT_IngestionSummary!A34, New_SQL_Ing!R:R,"Done") -> 4 | D34: =COUNTIFS(New_SQL_Ing!C:C,DT_IngestionSummary!A34,New_SQL_Ing!S:S,"Done") -> 0 | E34: - | F34: =COUNTIFS(New_SQL_Ing!C:C,DT_IngestionSummary!A34, New_SQL_Ing!U:U,"Done") -> 4 | G34: =COUNTIFS(New_SQL_Ing!C:C,DT_IngestionSummary!A34, New_SQL_Ing!V:V,"Done") -> 0 | H34: - | I34: =COUNTIFS(New_SQL_Ing!C:C,DT_IngestionSummary!A34, New_SQL_Ing!X:X,"Done") -> 0 | J34: =COUNTIFS(New_SQL_Ing!C:C,DT_IngestionSummary!A34, New_SQL_Ing!Y:Y,"Done") -> 0 | K34: - | L34: - | M34: - | N34: - | O34: - | P34: - | Q34: - | R34: - | S34: - | T34: - | AD34: NA | AG34: product
A35: ICCS -M3 | B35: 4 | C35: 4
A36: Infobip | B36: =COUNTIF(New_SQL_Ing!C:C,DT_IngestionSummary!A36) -> 1 | C36: =COUNTIFS(New_SQL_Ing!C:C,DT_IngestionSummary!A36, New_SQL_Ing!R:R,"Done") -> 1 | D36: =COUNTIFS(New_SQL_Ing!C:C,DT_IngestionSummary!A36,New_SQL_Ing!S:S,"Done") -> 0 | E36: - | F36: =COUNTIFS(New_SQL_Ing!C:C,DT_IngestionSummary!A36, New_SQL_Ing!U:U,"Done") -> 0 | G36: =COUNTIFS(New_SQL_Ing!C:C,DT_IngestionSummary!A36, New_SQL_Ing!V:V,"Done") -> 0 | H36: - | I36: =COUNTIFS(New_SQL_Ing!C:C,DT_IngestionSummary!A36, New_SQL_Ing!X:X,"Done") -> 0 | J36: =COUNTIFS(New_SQL_Ing!C:C,DT_IngestionSummary!A36, New_SQL_Ing!Y:Y,"Done") -> 0 | K36: - | L36: - | M36: - | N36: - | O36: - | P36: - | Q36: - | R36: - | S36: - | T36: - | AD36: Shiju | AE36: 6 months | AG36: interactions
A37: Digital Banking Admin | B37: =COUNTIF(New_SQL_Ing!C:C,DT_IngestionSummary!A37) -> 8 | C37: - | D37: 4 | E37: =COUNTIFS(New_SQL_Ing!C:C,DT_IngestionSummary!A37,New_SQL_Ing!T:T,"Done") -> 4 | F37: - | G37: - | H37: =COUNTIFS(New_SQL_Ing!C:C,DT_IngestionSummary!A37, New_SQL_Ing!W:W,"Done") -> 3 | I37: - | J37: - | K37: =COUNTIFS(New_SQL_Ing!C:C,DT_IngestionSummary!A37, New_SQL_Ing!Z:Z,"Done") -> 0 | L37: =COUNTIF(New_DV_Ing!I:I,DT_IngestionSummary!A37) -> 2 | M37: =COUNTIFS(New_DV_Ing!I:I,DT_IngestionSummary!A37,New_DV_Ing!O:O,"Done") -> 1 | N37: =COUNTIFS(New_DV_Ing!I:I,DT_IngestionSummary!B37,New_DV_Ing!P:P,"Done") -> 0 | O37: =COUNTIFS(New_DV_Ing!I:I,DT_IngestionSummary!E37,New_DV_Ing!Q:Q,"Done") -> 0 | P37: =COUNTIFS(New_DV_Ing!I:I,DT_IngestionSummary!F37,New_DV_Ing!R:R,"Done") -> 0 | Q37: =COUNTIFS(New_DV_Ing!I:I,DT_IngestionSummary!G37,New_DV_Ing!S:S,"Done") -> 0 | R37: =COUNTIFS(New_DV_Ing!I:I,DT_IngestionSummary!H37,New_DV_Ing!T:T,"Done") -> 0 | S37: =COUNTIFS(New_DV_Ing!I:I,DT_IngestionSummary!I37,New_DV_Ing!U:U,"Done") -> 0 | T37: =COUNTIFS(New_DV_Ing!I:I,DT_IngestionSummary!J37,New_DV_Ing!V:V,"Done") -> 0 | AD37: NA | AE37: should be NA
A38: RLS | B38: =COUNTIF(New_SQL_Ing!C:C,DT_IngestionSummary!A38) -> 23 | C38: - | D38: - | E38: =COUNTIFS(New_SQL_Ing!C:C,DT_IngestionSummary!A38,New_SQL_Ing!T:T,"Done") -> 6 | F38: - | G38: - | H38: =COUNTIFS(New_SQL_Ing!C:C,DT_IngestionSummary!A38, New_SQL_Ing!W:W,"Done") -> 6 | I38: - | J38: - | K38: =COUNTIFS(New_SQL_Ing!C:C,DT_IngestionSummary!A38, New_SQL_Ing!Z:Z,"Done") -> 0 | L38: =COUNTIF(New_DV_Ing!I:I,DT_IngestionSummary!A38) -> 1 | M38: =COUNTIFS(New_DV_Ing!I:I,DT_IngestionSummary!A38,New_DV_Ing!O:O,"Done") -> 1 | N38: =COUNTIFS(New_DV_Ing!I:I,DT_IngestionSummary!B38,New_DV_Ing!P:P,"Done") -> 0 | O38: =COUNTIFS(New_DV_Ing!I:I,DT_IngestionSummary!E38,New_DV_Ing!Q:Q,"Done") -> 0 | P38: =COUNTIFS(New_DV_Ing!I:I,DT_IngestionSummary!F38,New_DV_Ing!R:R,"Done") -> 0 | Q38: =COUNTIFS(New_DV_Ing!I:I,DT_IngestionSummary!G38,New_DV_Ing!S:S,"Done") -> 0 | R38: =COUNTIFS(New_DV_Ing!I:I,DT_IngestionSummary!H38,New_DV_Ing!T:T,"Done") -> 0 | S38: =COUNTIFS(New_DV_Ing!I:I,DT_IngestionSummary!I38,New_DV_Ing!U:U,"Done") -> 0 | T38: =COUNTIFS(New_DV_Ing!I:I,DT_IngestionSummary!J38,New_DV_Ing!V:V,"Done") -> 0 | AD38: Mani / Semeer | AG38: product
A39: RLS-M1 | B39: 3 | E39: 3
A40: RLS-M2 | B40: 2 | E40: 2
A41: RLS-M3 | B41: 1 | E41: 1
A42: CPPS | B42: =COUNTIF(New_SQL_Ing!C:C,DT_IngestionSummary!A42) -> 3 | C42: - | D42: - | E42: =COUNTIFS(New_SQL_Ing!C:C,DT_IngestionSummary!A42,New_SQL_Ing!T:T,"Done") -> 0 | F42: - | G42: - | H42: =COUNTIFS(New_SQL_Ing!C:C,DT_IngestionSummary!A42, New_SQL_Ing!W:W,"Done") -> 0 | I42: - | J42: - | K42: =COUNTIFS(New_SQL_Ing!C:C,DT_IngestionSummary!A42, New_SQL_Ing!Z:Z,"Done") -> 0 | L42: - | M42: - | N42: - | O42: - | P42: - | Q42: - | R42: - | S42: - | T42: - | AD42: Srikanth or Abay | AG42: product
A43: CAPS | B43: =COUNTIF(New_SQL_Ing!C:C,DT_IngestionSummary!A43) -> 5 | C43: - | D43: - | E43: =COUNTIFS(New_SQL_Ing!C:C,DT_IngestionSummary!A43,New_SQL_Ing!T:T,"Done") -> 3 | F43: - | G43: - | H43: =COUNTIFS(New_SQL_Ing!C:C,DT_IngestionSummary!A43, New_SQL_Ing!W:W,"Done") -> 3 | I43: - | J43: - | K43: =COUNTIFS(New_SQL_Ing!C:C,DT_IngestionSummary!A43, New_SQL_Ing!Z:Z,"Done") -> 0 | L43: - | M43: - | N43: - | O43: - | P43: - | Q43: - | R43: - | S43: - | T43: - | AD43: Srikanth or Abay | AG43: product
A44: IDD | B44: =COUNTIF(New_SQL_Ing!C:C,DT_IngestionSummary!A44) -> 1 | C44: =COUNTIFS(New_SQL_Ing!C:C,DT_IngestionSummary!A44, New_SQL_Ing!R:R,"Done") -> 1 | D44: =COUNTIFS(New_SQL_Ing!C:C,DT_IngestionSummary!A44,New_SQL_Ing!S:S,"Done") -> 0 | E44: - | F44: - | G44: - | H44: - | I44: - | J44: - | K44: - | L44: =COUNTIF(New_DV_Ing!I:I,DT_IngestionSummary!A44) -> 1 | M44: =COUNTIFS(New_DV_Ing!I:I,DT_IngestionSummary!A44,New_DV_Ing!O:O,"Done") -> 0 | N44: =COUNTIFS(New_DV_Ing!I:I,DT_IngestionSummary!B44,New_DV_Ing!P:P,"Done") -> 0 | O44: =COUNTIFS(New_DV_Ing!I:I,DT_IngestionSummary!E44,New_DV_Ing!Q:Q,"Done") -> 0 | P44: =COUNTIFS(New_DV_Ing!I:I,DT_IngestionSummary!F44,New_DV_Ing!R:R,"Done") -> 0 | Q44: =COUNTIFS(New_DV_Ing!I:I,DT_IngestionSummary!G44,New_DV_Ing!S:S,"Done") -> 0 | R44: =COUNTIFS(New_DV_Ing!I:I,DT_IngestionSummary!H44,New_DV_Ing!T:T,"Done") -> 0 | S44: =COUNTIFS(New_DV_Ing!I:I,DT_IngestionSummary!I44,New_DV_Ing!U:U,"Done") -> 0 | T44: =COUNTIFS(New_DV_Ing!I:I,DT_IngestionSummary!J44,New_DV_Ing!V:V,"Done") -> 0 | AD44: Gaurav | AG44: NA
A45: Prospect | B45: =COUNTIF(New_SQL_Ing!C:C,DT_IngestionSummary!A45) -> 1 | C45: =COUNTIFS(New_SQL_Ing!C:C,DT_IngestionSummary!A45, New_SQL_Ing!R:R,"Done") -> 1 | D45: =COUNTIFS(New_SQL_Ing!C:C,DT_IngestionSummary!A45,New_SQL_Ing!S:S,"Done") -> 0 | E45: - | F45: - | G45: - | H45: - | I45: - | J45: - | K45: - | L45: =COUNTIF(New_DV_Ing!I:I,DT_IngestionSummary!A45) -> 1 | M45: =COUNTIFS(New_DV_Ing!I:I,DT_IngestionSummary!A45,New_DV_Ing!O:O,"Done") -> 1 | N45: =COUNTIFS(New_DV_Ing!I:I,DT_IngestionSummary!B45,New_DV_Ing!P:P,"Done") -> 0 | O45: =COUNTIFS(New_DV_Ing!I:I,DT_IngestionSummary!E45,New_DV_Ing!Q:Q,"Done") -> 0 | P45: =COUNTIFS(New_DV_Ing!I:I,DT_IngestionSummary!F45,New_DV_Ing!R:R,"Done") -> 0 | Q45: =COUNTIFS(New_DV_Ing!I:I,DT_IngestionSummary!G45,New_DV_Ing!S:S,"Done") -> 0 | R45: =COUNTIFS(New_DV_Ing!I:I,DT_IngestionSummary!H45,New_DV_Ing!T:T,"Done") -> 0 | S45: =COUNTIFS(New_DV_Ing!I:I,DT_IngestionSummary!I45,New_DV_Ing!U:U,"Done") -> 0 | T45: =COUNTIFS(New_DV_Ing!I:I,DT_IngestionSummary!J45,New_DV_Ing!V:V,"Done") -> 0 | AD45: Gaurav | AG45: NA
A46: Grand Total | B46: =SUM(B4,B9,B14,B19,B21,B24,B26,B29,B31,B33,B34,B36,B37,B38,B42,B43,B44,B45) -> 491 | C46: =SUM(C4,C9,C14,C19,C21,C24,C26,C29,C31,C33,C34,C36,C37,C38,C42,C43,C44,C45) -> 216 | D46: =SUM(D4,D9,D14,D19,D21,D24,D26,D29,D31,D33,D34,D36,D37,D38,D42,D43,D44,D45) -> 118 | E46: =SUM(E4,E9,E14,E19,E21,E24,E26,E29,E31,E33,E34,E36,E37,E38,E42,E43,E44,E45) -> 13 | F46: =SUM(F4:F45) -> 167 | G46: =SUM(G4:G45) -> 0 | H46: =SUM(H4:H45) -> 12 | I46: =SUM(I4:I45) -> 0 | J46: =SUM(J4:J45) -> 0 | K46: =SUM(K4:K45) -> 0 | L46: =SUM(L4:L45) -> 20 | M46: =SUM(M4:M45) -> 18 | ... T46: =SUM(T4:T45) -> 0

Sheet pivot_f
A3: Count of Source table name | B3: Column Labels
A4: Row Labels | B4: Milestone 1 | C4: Milestone 2 | D4: Milestone 3 | E4: Milestone 4 | F4: TBD | G4: (blank) | H4: Grand Total
A5: CAPS | D5: 2 | E5: 1 | F5: 2 | H5: 5
A6: CASMEX | D6: 8 | H6: 8
A7: CCM | C7: 1 | F7: 5 | H7: 6
A8: CPF | C8: 3 | D8: 1 | H8: 4
A9: CPPS | E9: 3 | H9: 3
A10: Digital Banking Admin | B10: 3 | C10: 2 | F10: 3 | H10: 8
A11: Digital Onboarding Tracking | F11: 8 | H11: 8
A12: Finacle | B12: 8 | C12: 9 | D12: 38 | E12: 19 | F12: 42 | H12: 116
A13: IBPS | B13: 38 | C13: 1 | E13: 38 | F13: 142 | H13: 219
A14: ICCS | D14: 4 | H14: 4
A15: IDD | B15: 1 | H15: 1
A16: Infobip | C16: 1 | H16: 1
A17: ONLINE | C17: 2 | D17: 2 | E17: 2 | F17: 1 | H17: 7
A18: Pay Hub Plus (NPSS Unity) | D18: 12 | F18: 1 | H18: 13
A19: PRIME | B19: 2 | C19: 7 | D19: 26 | E19: 1 | F19: 5 | H19: 41
A20: Prospect | B20: 1 | H20: 1
A21: RLS | B21: 3 | C21: 2 | E21: 1 | F21: 17 | H21: 23
A22: WMS | B22: 1 | F22: 22 | H22: 23
A23: (blank)
A24: Grand Total | B24: 57 | C24: 28 | D24: 93 | E24: 65 | F24: 248 | H24: 491

Sheet New_SQL_Ing
A1: Milestone | B1: ADF Batch? | C1: System | D1: Schema Name | E1: DB name | F1: Source table name | G1: Data Team Remarks/Data Ingestion Start Date in DEV | H1: Table Size in PROD(inGb) | I1: Source Enforced Primary Key | J1: Primary key | K1: ConfluentKey in Topic | L1: Transactional table? | M1: Date column | N1: CRM DB table name | O1: Source to Kafka | P1: Kafka to ADLS | Q1: ADLS to Databrick (DLT) | R1: Day-0 load in SQL DB DB : DEV Source : UAT 2 Approach : ADF approach | S1: Continuous load in SQL DB DB : DEV Source : UAT 2 Approach : Confluent RTS (SQL Sink) | T1: Batch load in SQL DB DB : DEV Source : UAT2 Approach : ADF | U1: Day-0 load in SQL DB DB : CRM_PT Source : UAT 2 Approach :ADF | V1: Continuous load in SQL DB DB : CRM_PT Source : UAT 2 Approach : Confluent RTS (SQL Sink) | W1: Batch load in SQL DB DB : CRM_PT Source : UAT2 Approach : ADF | X1: Day-0 load in SQL DB DB : CRM_PREPROD Source : UAT 2 Approach :ADF | Y1: Continuous load in SQL DB DB : CRM_PREPROD Source : UAT 2 Approach : Confluent RTS (SQL Sink) | Z1: Batch load in SQL DB DB : CRM_PREPROD Source : UAT2 Approach : ADF | AA1: Was the table available in Databricks Bronze DEV/TEST instances already or being developed for CRM? | AB1: Was the table Available in Databricks Bronze PROD instances already or being developed for CRM?
A2: TBD | B2: N | C2: Finacle | D2: TBAADM | E2: FINUAT | F2: HIST_TRAN_DTL_TABLE | G2: 01-June to 15-June 2026 | H2: 2097.104 | I2: ACID, TRAN_DATE | J2: ACID,REF_NUM,PSTD_DATE | L2: Y | M2: TRAN_DATE | O2: Done | P2: Done | Q2: Done | R2: Done | S2: Not Done | T2: NA | U2: Not Done | V2: Not Done | W2: NA | X2: Not Done | Y2: Not Done | Z2: NA | AA2: Yes | AB2: yes
A3: Milestone 3 | B3: N | C3: PRIME | D3: TCTDBS | E3: PRIMEDB | F3: APPLOG | H3: 177.805 | I3: NA | J3: EODSERNO,TABNAME,COLNAME,ROWSERNO | L3: Y | M3: DATETIMESTAMP | N3: CRM_DEV.prime4.TCTDBS_APPLOG | O3: Done | P3: Done | Q3: Done | R3: Not Done | S3: Not Done | T3: NA | U3: Not Done | V3: Not Done | W3: NA | X3: Not Done | Y3: Not Done | Z3: NA | AA3: Yes | AB3: No
A4: Milestone 4 | B4: N | C4: Finacle | D4: TBAADM | E4: FINUAT | F4: CHRG_TRAN_LOG_TBL | G4: NonPK | H4: 134.402 | I4: CUST_ID, TARGET_ACID, CHRG_TRAN_DATE | J4: CUST_ID TARGET_ACID, CHRG_TRAN_DATE CHRG_TRAN_ID, COMP_B2KID, SYS_NC00054$, BANK_ID | L4: Y | M4: CHRG_TRAN_DATE | O4: Done | P4: Done | Q4: Done | R4: Done | S4: Not Done | T4: NA | U4: Done | V4: Not Done | W4: NA | X4: Not Done | Y4: Not Done | Z4: NA | AA4: Yes | AB4: No
A5: TBD | B5: N | C5: CCM | E5: Dealing | F5: EmailDetail | G5: 17-June to 20-June 2026 | H5: 129.484 | J5: TARGET_ACID, CHRG_TRAN_DATE | O5: Done | P5: Done | Q5: Done | R5: Not Done | S5: Not Done | T5: NA | U5: Not Done | V5: Not Done | W5: NA | X5: Not Done | Y5: Not Done | Z5: NA | AA5: Yes | AB5: No
A6: Milestone 3 | B6: N | C6: PRIME | D6: TCTDBS | E6: PRIMEDB | F6: CTRANSACTIONS | H6: 120.597 | I6: SERNO , PARTITIONKEY | J6: CHRG_TRAN_ID, COMP_B2KID, SYS_NC00054$, BANK_ID | L6: Y | M6: I013_TRXN_DATE | N6: CRM_DEV.prime4.TCTDBS_CTRANSACTIONS | O6: Done | P6: Done | Q6: Done | R6: Done | S6: Not Done | T6: NA | U6: Done | V6: Not Done | W6: NA | X6: Not Done | Y6: Not Done | Z6: NA | AA6: Yes | AB6: No
A7: Milestone 2 | B7: N | C7: PRIME | D7: TCTDBS | E7: PRIMEDB | F7: tbalances | H7: 118.532 | I7: SERNO, PARTITIONKEY | J7: SERNO | L7: N | N7: CRM_DEV.prime4.TCTDBS_TBALANCES | O7: Done | P7: Done | Q7: Done | R7: Done | S7: Dev Done | T7: NA | U7: Not Done | V7: Not Done | W7: NA | X7: Not Done | Y7: Not Done | Z7: NA | AA7: No | AB7: No
A8: Milestone 3 | B8: N | C8: Finacle | D8: TBAADM | E8: FINUAT | F8: SWIFT_MSG_HISTORY_TABLE | H8: 104.608 | I8: TRAN_ID, PTRAN_SRL_NUM, TRAN_DATE | J8: SW_SRL_NUM | L8: N | M8: LCHG_TIME | N8: CRM_DEV.finacle.TBAADM_SWIFT_MSG_HISTORY_TABLE | O8: Done | P8: Done | Q8: Done | R8: Done | S8: Done | T8: NA | U8: Done | V8: Not Done | W8: NA | X8: Not Done | Y8: Not Done | Z8: NA | AA8: No | AB8: No
A9: TBD | B9: N | C9: CCM | E9: Dealing | F9: Email | G9: 17-June to 20-June 2026 | H9: 69.927 | O9: Done | P9: Done | Q9: Done | R9: Not Done | S9: Not Done | T9: NA | U9: Not Done | V9: Not Done | W9: NA | X9: Not Done | Y9: Not Done | Z9: NA | AA9: No | AB9: yes
A10: Milestone 3 | B10: N | C10: PRIME | D10: TCTDBS | E10: PRIMEDB | F10: CISOTRXNS | H10: 69.469 | I10: NA | J10: SERNO | L10: Y | M10: I012_TRXN_TIME | N10: CRM_DEV.prime4.TCTDBS_CISOTRXNS | O10: Done | P10: Done | Q10: Done | R10: Done | S10: Not Done | T10: NA | U10: Done | V10: Not Done | W10: NA | X10: Not Done | Y10: Not Done | Z10: NA | AA10: No | AB10: No
A11: Milestone 4 | B11: N | C11: Finacle | D11: TBAADM | E11: FINUAT | F11: ACCOUNT_LIEN_HISTORY_TABLE | G11: NonPK | H11: 68.842 | I11: ACID, MODIFY_BOD_DATE, SRL_NUM, BANK_ID | J11: ACID,TRAN_ID,TRAN_DATE | L11: N | M11: LCHG_TIME | N11: CRM_DEV.finacle.TBAADM_ACCOUNT_LIEN_HISTORY_TABLE | O11: Done | P11: Done | Q11: Done | R11: Done | S11: Not Done | T11: NA | U11: Done | V11: Not Done | W11: NA | X11: Not Done | Y11: Not Done | Z11: NA | AA11: No | AB11: No
A12: Milestone 3 | B12: N | C12: Finacle | D12: TBAADM | E12: FINUAT | F12: PAYMENT_ORDER_DETAIL_TABLE | H12: 56.279 | I12: TRAN_REF_NUM, SENDER_CHANNEL, BANK_ID | J12: PYMT_REF_NUM | L12: N | M12: LCHG_TIME | N12: CRM_DEV.finacle.TBAADM_PAYMENT_ORDER_DETAIL_TABLE | O12: Done | P12: Done | Q12: Done | R12: Done | S12: Done | T12: NA | U12: Done | V12: Not Done | W12: NA | X12: Not Done | Y12: Not Done | Z12: NA | AA12: No | AB12: yes
A13: Milestone 3 | B13: N | C13: Finacle | D13: TBAADM | E13: FINUAT | F13: PAYMENT_ORDER_HEADER_TABLE | H13: 40.821 | I13: REQ_EXEC_DATE, DR_ACCT, TRAN_DATE, TRAN_ID | J13: PYMT_REF_NUM | L13: N | M13: LCHG_TIME | N13: CRM_DEV.finacle.TBAADM_PAYMENT_ORDER_HEADER_TABLE | O13: Done | P13: Done | Q13: Done | R13: Done | S13: Done | T13: NA | U13: Not Done | V13: Not Done | W13: NA | X13: Not Done | Y13: Not Done | Z13: NA | AA13: No | AB13: No
A14: Milestone 3 | B14: N | C14: Pay Hub Plus (NPSS Unity) | D14: dbo | E14: npss-epayment | F14: NPSS_RTPaymentsHdr_Inw | G14: Due to AWS issue, End point has changed , Requested to FCR to replace with new end point | H14: 35.357 | I14: RTH_MsgGenDt,RTH_RefID | L14: Y | M14: RTH_MsgGenDt | N14: CRM_DEV.npss.DBO_NPSS_RTPAYMENTSHDR_INW | O14: Done | P14: Done | Q14: Done | R14: Done | S14: Not Done | T14: NA | U14: Done | V14: Not Done | W14: NA | X14: Not Done | Y14: Not Done | Z14: NA | AA14: No | AB14: yes
A15: TBD | B15: Y | C15: Digital Banking Admin | D15: ECECUSER | E15: CNVGNIB | F15: RQSTHISTORYTABLE | G15: 20-June to 22-June 2026 | H15: 21.917 | I15: BANK_ID, REQUEST_SRL_NUM | J15: REQUEST_SRL_NUM | L15: Y | M15: R_cre_time | O15: NA | P15: NA | Q15: NA | R15: NA | S15: NA | T15: Not Done | U15: NA | V15: NA | W15: Not Done | X15: NA | Y15: NA | Z15: Not Done | AA15: No | AB15: No
A16: Milestone 1 | B16: N | C16: IBPS | D16: DBO | E16: RAKCAS | F16: wfinstrumenttable | H16: 19.841 | I16: ProcessInstanceID,WorkItemId | J16: ProcessInstanceID,WorkItemId | L16: Y | M16: Createddatetime column under Wfinstrumenttable | N16: CRM_DEV.ibps.DBO_WFINSTRUMENTTABLE | O16: Done | P16: Done | Q16: Done | R16: Done | S16: Done | T16: NA | U16: Done | V16: Not Done | W16: NA | X16: Not Done | Y16: Not Done | Z16: NA | AA16: No | AB16: No
A17: Milestone 3 | B17: N | C17: CASMEX | D17: REMIT_SL | E17: REMITPRD | F17: DX_TRNS_REMITTANCE | H17: 18.351 | I17: refno | J17: REFNO | L17: Y | M17: Trandate | N17: CRM_DEV.casmex.REMIT_SL_DX_TRNS_REMITTANCE | O17: Done | P17: Done | Q17: Done | R17: Done | S17: Done | T17: NA | U17: Done | V17: Not Done | W17: NA | X17: Not Done | Y17: Not Done | Z17: NA | AA17: No | AB17: yes
A18: Milestone 3 | B18: N | C18: PRIME | D18: TCTDBS | E18: PRIMEDB | F18: CEXTENSION | H18: 17.05 | I18: NA | J18: FIELDNO,ROWSERNO,TABINDICATOR | L18: N | N18: CRM_DEV.prime4.TCTDBS_CEXTENSION | O18: Done | P18: Done | Q18: Done | R18: Done | S18: Dev Done | T18: NA | U18: Done | V18: Not Done | W18: NA | X18: Not Done | Y18: Not Done | Z18: NA | AA18: No | AB18: No
A19: TBD | B19: Y | C19: CAPS | D19: CAPSADMIN | E19: CAPS | F19: DELINQUENCYCALENDAR | G19: 15-June to 19-June 2026 | H19: 16.832 | I19: NA | O19: NA | P19: NA | Q19: NA | R19: NA | S19: NA | T19: Not Done | U19: NA | V19: NA | W19: Not Done | X19: NA | Y19: NA | Z19: Not Done | AA19: No | AB19: No
A20: Milestone 2 | B20: N | C20: PRIME | D20: TCTDBS | E20: PRIMEDB | F20: CSTATEMENTS | H20: 15.944 | I20: SERNO, PARTITIONKEY | J20: SERNO | L20: Y | M20: billingdate | N20: CRM_DEV.prime4.TCTDBS_CSTATEMENTS | O20: Done | P20: Done | Q20: Done | R20: Done | S20: Dev Done | T20: NA | U20: Done | V20: Not Done | W20: NA | X20: Not Done | Y20: Not Done | Z20: NA | AA20: No | AB20: No
A21: Milestone 3 | B21: N | C21: CASMEX | D21: REMIT_SL | E21: REMITPRD | F21: DX_REF_ACTIVITY_LOG | H21: 12.774 | I21: NA | L21: Y | M21: Authdate | N21: CRM_DEV.casmex.REMIT_SL_DX_REF_ACTIVITY_LOG | O21: Done | P21: Done | Q21: Done | R21: Done | S21: Done | T21: NA | U21: Done | V21: Not Done | W21: NA | X21: Not Done | Y21: Not Done | Z21: NA | AA21: No | AB21: yes
A22: Milestone 3 | B22: N | C22: Pay Hub Plus (NPSS Unity) | D22: dbo | E22: npss-epayment | F22: NPSS_RTPaymentsDtl_Inw | G22: Due to AWS issue, End point has changed , Requested to FCR to replace with new end point | H22: 11.544 | I22: RTD_MsgGenDt,RTD_RefID | L22: Y | M22: RTD_MsgGenDt | N22: CRM_DEV.npss.DBO_NPSS_RTPAYMENTSDTL_INW | O22: Done | P22: Done | Q22: Done | R22: Done | S22: Dev Done | T22: NA | U22: Done | V22: Not Done | W22: NA | X22: Not Done | Y22: Not Done | Z22: NA | AA22: No | AB22: yes
A23: Milestone 3 | B23: N | C23: PRIME | D23: TCTDBS | E23: PRIMEDB | F23: Cinstalmentamortization | H23: 6.676 | I23: SERNO , PARTITIONKEY | J23: SERNO | L23: N | N23: CRM_DEV.prime4.TCTDBS_CINSTALMENTAMORTIZATION | O23: Done | P23: Done | Q23: Done | R23: Done | S23: Dev Done | T23: NA | U23: Done | V23: Not Done | W23: NA | X23: Not Done | Y23: Not Done | Z23: NA | AA23: No | AB23: No
A24: Milestone 3 | B24: N | C24: Pay Hub Plus (NPSS Unity) | D24: dbo | E24: npss-epayment | F24: NPSS_RTPaymentsDtl_Out | G24: Due to AWS issue, End point has changed , Requested to FCR to replace with new end point | H24: 6.527 | I24: RTD_MsgGenDt,RTD_RefID | L24: Y | M24: RTD_MsgGenDt | N24: CRM_DEV.npss.DBO_NPSS_RTPAYMENTSDTL_OUT | O24: Done | P24: Done | Q24: Done | R24: Done | S24: Dev Done | T24: NA | U24: Done | V24: Not Done | W24: NA | X24: Not Done | Y24: Not Done | Z24: NA | AA24: No | AB24: No
A25: Milestone 3 | B25: N | C25: PRIME | D25: TCTDBS | E25: PRIMEDB | F25: archtBalances | H25: 6.182 | I25: NA | L25: N | N25: CRM_DEV.prime4.TCTDBS_ARCHTBALANCES | O25: Done | P25: Done | Q25: Done | R25: Done | S25: Dev Done | T25: NA | U25: Done | V25: Not Done | W25: NA | X25: Not Done | Y25: Not Done | Z25: NA | AA25: No | AB25: No
A26: Milestone 3 | B26: N | C26: PRIME | D26: TCTDBS | E26: PRIMEDB | F26: BATCHES | H26: 6.158 | I26: NA | L26: Y | M26: BATCHDATE | N26: CRM_DEV.prime4.TCTDBS_BATCHES | O26: Done | P26: Done | Q26: Done | R26: Done | S26: Not Done | T26: NA | U26: Done | V26: Not Done | W26: NA | X26: Not Done | Y26: Not Done | Z26: NA | AA26: No | AB26: No
A27: Milestone 1 | B27: N | C27: IBPS | D27: dbo | E27: RAKCAS | F27: NG_TT_EXT_TABLE | H27: 5.28 | I27: ITEMINDEX,ITEMTYPE | J27: ITEMINDEX,ITEMTYPE | L27: Y | M27: Createddatetime column under Wfinstrumenttable | N27: CRM_DEV.ibps.DBO_NG_TT_EXT_TABLE | O27: Done | P27: Done | Q27: Done | R27: Done | S27: Done | T27: NA | U27: Done | V27: Not Done | W27: NA | X27: Not Done | Y27: Not Done | Z27: NA | AA27: No | AB27: No
A28: TBD | B28: N | C28: Digital Onboarding Tracking | D28: DEHUSEROB | E28: rakdehsit | F28: CREDIT_CARDS_REQUEST_DET | G28: 20-June to 25-June 2026 | H28: 5.2539062 | J28: PROSPECT_ID | O28: Not Done | P28: Not Done | Q28: Not Done | R28: Not Done | S28: Not Done | T28: NA | U28: Not Done | V28: Not Done | W28: NA | X28: Not Done | Y28: Not Done | Z28: NA | AA28: No | AB28: No
A29: Milestone 1 | B29: N | C29: Finacle | D29: CRMUSER | E29: FINUAT | F29: Incidents | H29: 4.749 | I29: INCIDENTID, BANK_ID | J29: INCIDENTID,BANK_ID | L29: N | M29: BODATEMODIFIED | N29: CRM_DEV.finacle.CRMUSER_INCIDENTS | O29: Done | P29: Done | Q29: Done | R29: Done | S29: Done | T29: NA | U29: Done | V29: Not Done | W29: NA | X29: Not Done | Y29: Not Done | Z29: NA | AA29: No | AB29: yes
A30: Milestone 3 | B30: N | C30: Pay Hub Plus (NPSS Unity) | D30: dbo | E30: npss-epayment | F30: NPSS_RTPaymentsDtl_OutExn | G30: Due to AWS issue, End point has changed , Requested to FCR to replace with new end point | H30: 4.448 | I30: RTD_MsgGenDt,RTD_RefID | L30: Y | M30: RTD_MsgGenDt | N30: CRM_DEV.npss.DBO_NPSS_RTPAYMENTSDTL_OUTEXN | O30: Done | P30: Done | Q30: Done | R30: Done | S30: Dev Done | T30: NA | U30: Done | V30: Not Done | W30: NA | X30: Not Done | Y30: Not Done | Z30: NA | AA30: No | AB30: yes
A31: TBD | B31: N | C31: PRIME | D31: TCTDBS | E31: PRIMEDB | F31: SERVICES | G31: 15-June to 19-June 2026 | H31: 4.034 | L31: N | O31: Not Done | P31: Done | Q31: Done | R31: Done | S31: Not Done | T31: NA | U31: Not Done | V31: Not Done | W31: NA | X31: Not Done | Y31: Not Done | Z31: NA | AA31: No | AB31: No
A32: TBD | B32: N | C32: PRIME | D32: TCTDBS | E32: PRIMEDB | F32: ctrxncampaignlinks | G32: 15-June to 19-June 2026 | H32: 3.811 | L32: N | O32: Not Done | P32: Not Done | Q32: Not Done | R32: Not Done | S32: Not Done | T32: NA | U32: Not Done | V32: Not Done | W32: NA | X32: Not Done | Y32: Not Done | Z32: NA | AA32: No | AB32: No
A33: Milestone 2 | B33: Y | C33: RLS | D33: RAK_JSITPH3 | E33: RLSPROD | F33: CS_CASE_INFO | H33: 3.694 | I33: APPL_ID | J33: CS_CASE_INFO_ID, APPL_ID | L33: N | N33: CRM_DEV.cpf.DBO_CUSTOMER_CONSENT_AUDIT | O33: NA | P33: NA | Q33: NA | R33: NA | S33: NA | T33: Done | U33: NA | V33: NA | W33: Done | X33: Not Done | Y33: NA | Z33: Not Done | AA33: No | AB33: No
A34: Milestone 2 | B34: N | C34: PRIME | D34: TCTDBS | E34: PRIMEDB | F34: CACCOUNTS | H34: 3.547 | I34: SERNO | J34: SERNO | L34: N | N34: CRM_DEV.prime4.TCTDBS_CACCOUNTS | O34: Done | P34: Done | Q34: Done | R34: Done | S34: Dev Done | T34: NA | U34: Done | V34: Not Done | W34: NA | X34: Not Done | Y34: Not Done | Z34: NA | AA34: No | AB34: No
A35: TBD | B35: Y | C35: RLS | D35: FIN_LEAM | E35: RLSPROD | F35: NBFC_CHEQUE_DTL | G35: 27-June to 01-July 2026 | H35: 3.407 | J35: CHEQUE_ID | L35: N | O35: NA | P35: NA | Q35: NA | R35: NA | S35: NA | T35: Not Done | U35: NA | V35: NA | W35: Not Done | X35: NA | Y35: NA | Z35: Not Done | AA35: No | AB35: Yes
A36: Milestone 4 | B36: Y | C36: CPPS | D36: CPPUSER | E36: CPPSUAT | F36: PAYMENT_TRANS_ONLINE_NOTIFY_T | G36: Data will be ingested by Control-M job. it is in progress | H36: 3 | I36: SEQ_NO | O36: NA | P36: NA | Q36: NA | R36: NA | S36: Dev Done | T36: Not Done | U36: NA | V36: NA | W36: Not Done | X36: NA | Y36: NA | Z36: Not Done | AA36: No | AB36: No
A37: Milestone 2 | B37: N | C37: Finacle | D37: TBAADM | E37: FINUAT | F37: GENERAL_ACCT_MAST_TABLE | H37: 2.819 | I37: CIF_ID,CUST_ID,FORACID,POOL_ID,SCHM_CODE, SOL_ID,ACCT_SHORT_NAME, SOL_ID,IBAN_NUMBE,LIMIT_B2KID | J37: ACID | L37: N | M37: LCHG_TIME | N37: CRM_DEV.finacle.TBAADM_GENERAL_ACCT_MAST_TABLE | O37: Done | P37: Done | Q37: Done | R37: Done | S37: Done | T37: NA | U37: Done | V37: Not Done | W37: NA | X37: Not Done | Y37: Not Done | Z37: NA | AA37: No | AB37: yes
A38: Milestone 2 | B38: Y | C38: RLS | D38: FIN_LEAM | E38: RLSPROD | F38: LEA_REPAYSCH_DTL | H38: 2.462 | I38: Agreementid | J38: PROPINSTLID | L38: N | N38: CRM_DEV.rls.LOS0909_LEA_REPAYSCH_DTL | O38: NA | P38: NA | Q38: NA | R38: NA | S38: NA | T38: Done | U38: NA | V38: NA | W38: Done | X38: Not Done | Y38: NA | Z38: Not Done | AA38: No | AB38: No
A39: Milestone 3 | B39: N | C39: Finacle | D39: CRMUSER | E39: FINUAT | F39: Address | H39: 2.422 | I39: ADDRESSID, BANK_ID | J39: ADDRESSID,BANK_ID | L39: N | M39: TMDATE | N39: CRM_DEV.finacle.CRMUSER_ADDRESS | O39: Done | P39: Done | Q39: Done | R39: Done | S39: Done | T39: NA | U39: Done | V39: Not Done | W39: NA | X39: Not Done | Y39: Not Done | Z39: NA | AA39: No | AB39: yes
A40: TBD | B40: Y | C40: RLS | D40: RAK_JSITPH3 | E40: RLSPROD | F40: PAYMENT_DETAILS_V | G40: 27-June to 01-July 2026 | H40: 2.332 | J40: CASE_DETAIL_SEQ, APPL_ID | L40: Y | N40: CRM_DEV.infobip._TO BE DECIDED | O40: NA | P40: NA | Q40: NA | R40: NA | S40: NA | T40: Not Done | U40: NA | V40: NA | W40: Not Done | X40: NA | Y40: NA | Z40: Not Done | AA40: No | AB40: No
A41: Milestone 3 | B41: N | C41: Pay Hub Plus (NPSS Unity) | D41: dbo | E41: npss-epayment | F41: NPSS_RTPaymentsHdr_Out | G41: Due to AWS issue, End point has changed , Requested to FCR to replace with new end point | H41: 2.329 | I41: RTH_MsgGenDt,RTH_RefID | L41: Y | M41: RTH_MsgGenDt | N41: CRM_DEV.npss.DBO_NPSS_RTPAYMENTSHDR_OUT | O41: Done | P41: Done | Q41: Done | R41: Done | S41: Dev Done | T41: NA | U41: Done | V41: Not Done | W41: NA | X41: Not Done | Y41: Not Done | Z41: NA | AA41: No | AB41: No
A42: TBD | B42: N | C42: Digital Onboarding Tracking | D42: DEHUSEROB | E42: rakdehsit | F42: RETAIL_ACCOUNTS_REQUEST_DET | G42: 20-June to 25-June 2026 | H42: 2.3115234 | O42: Not Done | P42: Not Done | Q42: Not Done | R42: Not Done | S42: Not Done | T42: NA | U42: Not Done | V42: Not Done | W42: NA | X42: Not Done | Y42: Not Done | Z42: NA | AA42: No | AB42: No
A43: Milestone 3 | B43: N | C43: PRIME | D43: TCTDBS | E43: PRIMEDB | F43: MEMOS | H43: 2.261 | I43: SERNO | J43: SERNO | L43: Y | M43: DATETIMESTAMP | N43: CRM_DEV.prime4.TCTDBS_MEMOS | O43: Done | P43: Done | Q43: Done | R43: Done | S43: Not Done | T43: NA | U43: Done | V43: Not Done | W43: NA | X43: Not Done | Y43: Not Done | Z43: NA | AA43: No | AB43: No
A44: Milestone 1 | B44: N | C44: IBPS | D44: dbo | E44: RAKCAS | F44: RB_KYC_REM_EXTTABLE | H44: 2.24 | I44: ITEMINDEX,ITEMTYPE | J44: ITEMINDEX,ITEMTYPE | L44: Y | M44: Createddatetime column under Wfinstrumenttable | N44: CRM_DEV.ibps.DBO_RB_KYC_REM_EXTTABLE | O44: Done | P44: Done | Q44: Done | R44: Done | S44: Done | T44: NA | U44: Done | V44: Not Done | W44: NA | X44: Not Done | Y44: Not Done | Z44: NA | AA44: No | AB44: No
A45: Milestone 1 | B45: N | C45: PRIME | D45: TCTDBS | E45: PRIMEDB | F45: CARDX | H45: 2.186 | I45: SERNO | J45: SERNO | L45: N | N45: CRM_DEV.prime4.TCTDBS_CARDX | O45: Done | P45: Done | Q45: Done | R45: Done | S45: Dev Done | T45: NA | U45: Done | V45: Not Done | W45: NA | X45: Not Done | Y45: Not Done | Z45: NA | AA45: No | AB45: No
A46: Milestone 1 | B46: N | C46: Finacle | D46: CRMUSER | E46: FINUAT | F46: accounts | H46: 2.185326 | I46: ACCOUNTID, BANK_ID | J46: org_key | L46: N | M46: BODATEMODIFIED | N46: CRM_DEV.finacle.CRMUSER_ACCOUNTS | O46: Done | P46: Done | Q46: Done | R46: Done | S46: Done | T46: NA | U46: Done | V46: Not Done | W46: NA | X46: Not Done | Y46: Not Done | Z46: NA | AA46: No | AB46: yes
A47: Milestone 3 | B47: N | C47: Finacle | D47: CUSTOM | E47: FINUAT | F47: CUST_PAYGEN_ORD_TABLE | H47: 2.092 | I47: PYMT_REF_NUM | J47: pymt_ref_num | L47: N | M47: LCHG_TIME | N47: CRM_DEV.finacle.CUSTOM_CUST_PAYGEN_ORD_TABLE | O47: Done | P47: Done | Q47: Done | R47: Done | S47: Done | T47: NA | U47: Done | V47: Not Done | W47: NA | X47: Not Done | Y47: Not Done | Z47: NA | AA47: No | AB47: No
A48: TBD | B48: N | C48: Digital Onboarding Tracking | D48: DEHUSEROB | E48: rakdehsit | F48: CARDS_ACCOUNTS_MASTER | G48: 20-June to 25-June 2026 | H48: 1.9746094 | J48: PROSPECT_ID | O48: Not Done | P48: Not Done | Q48: Not Done | R48: Not Done | S48: Not Done | T48: NA | U48: Not Done | V48: Not Done | W48: NA | X48: Not Done | Y48: Not Done | Z48: NA | AA48: No | AB48: No
A49: Milestone 3 | B49: N | C49: PRIME | D49: TCTDBS | E49: PRIMEDB | F49: CADDRESSES | H49: 1.879 | I49: SERNO | J49: SERNO | L49: N | N49: CRM_DEV.prime4.TCTDBS_CADDRESSES | O49: Done | P49: Done | Q49: Done | R49: Done | S49: Not Done | T49: NA | U49: Done | V49: Not Done | W49: NA | X49: Not Done | Y49: Not Done | Z49: NA | AA49: No | AB49: No
A50: Milestone 4 | B50: N | C50: Finacle | D50: CRMUSER | E50: FINUAT | F50: Request | H50: 1.82 | I50: REQUESTID, BANK_ID | J50: REQUESTID,BANK_ID | L50: N | M50: BODATEMODIFIED | N50: CRM_DEV.finacle.CRMUSER_REQUEST | O50: Done | P50: Done | Q50: Done | R50: Done | S50: Done | T50: NA | U50: Done | V50: Not Done | W50: NA | X50: Not Done | Y50: Not Done | Z50: NA | AA50: No | AB50: No
A51: Milestone 2 | B51: N | C51: Finacle | D51: CRMUSER | E51: FINUAT | F51: MiscellaneousInfo | H51: 1.624 | I51: MISCELLANEOUSID, BANK_ID | J51: MISCELLANEOUSID,BANK_ID | L51: N | M51: TMDATE | N51: CRM_DEV.finacle.CRMUSER_MISCELLANEOUSINFO | O51: Done | P51: Done | Q51: Done | R51: Done | S51: Done | T51: NA | U51: Done | V51: Not Done | W51: NA | X51: Not Done | Y51: Not Done | Z51: NA | AA51: No | AB51: yes
A52: Milestone 3 | B52: N | C52: Finacle | D52: TBAADM | E52: FINUAT | F52: DAILY_TRAN_DETAIL_TABLE | H52: 1.53 | I52: SOL_ID, TRAN_CRNCY_CODE, GL_SUB_HEAD_CODE, SI_SRL_NUM, ACID | J52: ACID,TRAN_ID, PART_TRAN_SRL_NUM | L52: Y | M52: TRAN_DATE | N52: CRM_DEV.finacle.TBAADM_DAILY_TRAN_DETAIL_TABLE | O52: Done | P52: Done | Q52: Done | R52: Done | S52: Done | T52: NA | U52: Done | V52: Not Done | W52: NA | X52: Not Done | Y52: Not Done | Z52: NA | AA52: No | AB52: yes
A53: Milestone 1 | B53: Y | C53: Digital Banking Admin | D53: ECECUSER | E53: CNVGNIB | F53: CORPORATE_USER | H53: 1.497 | I53: ORG_ID, BANK_ID, USER_ID | L53: N | N53: CRM_DEV.digital_banking_admin.ECECUSER_CORPORATE_USER | O53: NA | P53: NA | Q53: NA | R53: NA | S53: Done | T53: Done | U53: NA | V53: NA | W53: Done | X53: Not Done | Y53: NA | Z53: Not Done | AA53: No | AB53: No
A54: Milestone 1 | B54: N | C54: PRIME | D54: TCTDBS | E54: PRIMEDB | F54: PEOPLE | H54: 1.489 | I54: SERNO | J54: SERNO | L54: N | N54: CRM_DEV.digital_banking_admin.REQUEST_DETAILS | O54: Done | P54: Done | Q54: Done | R54: Done | S54: Dev Done | T54: NA | U54: Done | V54: Not Done | W54: NA | X54: Not Done | Y54: Not Done | Z54: NA | AA54: No | AB54: No
A55: Milestone 4 | B55: N | C55: Finacle | D55: TBAADM | E55: FINUAT | F55: INT_TBL_CODE_TABLE | H55: 1.377 | I55: ENTITY_ID, ENTITY_TYPE, START_DATE, INT_TBL_CODE_SRL_NUM | J55: ENTITY_ID,RECORD_DATE | L55: N | M55: LCHG_TIME | N55: CRM_DEV.digital_banking_admin.MULTI_LEVEL_WORKFLOW_TABLE | O55: Done | P55: Done | Q55: Done | R55: Done | S55: Done | T55: NA | U55: Done | V55: Not Done | W55: NA | X55: Not Done | Y55: Not Done | Z55: NA | AA55: No | AB55: yes
A56: Milestone 1 | B56: N | C56: IBPS | D56: DBO | E56: RAKCAS | F56: RB_TF_EXTTABLE | H56: 1.354 | I56: ITEMINDEX,ITEMTYPE | J56: ITEMINDEX,ITEMTYPE | L56: Y | M56: Createddatetime column under Wfinstrumenttable | N56: CRM_DEV.digital_banking_admin.CUSTOMER_MASTER | O56: Done | P56: Done | Q56: Done | R56: Done | S56: Done | T56: NA | U56: Done | V56: Not Done | W56: NA | X56: Not Done | Y56: Not Done | Z56: NA | AA56: No | AB56: No
A57: Milestone 2 | B57: N | C57: Finacle | D57: TBAADM | E57: FINUAT | F57: ENTITY_INTEREST_TABLE | H57: 1.321 | I57: ENTITY_ID, ENTITY_TYPE, BANK_ID | J57: ENTITY_ID | L57: N | M57: LCHG_TIME | N57: CRM_DEV.finacle.TBAADM_ENTITY_INTEREST_TABLE | O57: Done | P57: Done | Q57: Done | R57: Done | S57: Done | T57: NA | U57: Done | V57: Not Done | W57: NA | X57: Not Done | Y57: Not Done | Z57: NA | AA57: No | AB57: yes
A58: Milestone 2 | B58: Y | C58: Digital Banking Admin | D58: ECECUSER | E58: CNVGNIB | F58: REQUEST_DETAILS | H58: 1.312 | I58: BANK_ID, FTXN_ID | L58: N | N58: CRM_DEV.digital_banking_admin.ECECUSER_REQUEST_DETAILS | O58: NA | P58: NA | Q58: NA | R58: NA | S58: Done | T58: Done | U58: NA | V58: NA | W58: Done | X58: NA | Y58: NA | Z58: Not Done | AA58: No | AB58: No
A59: TBD | B59: N | C59: PRIME | D59: TCTDBS | E59: PRIMEDB | F59: CARDTOKENS | G59: 15-June to 19-June 2026 | H59: 1.305 | L59: N | O59: Not Done | P59: Done | Q59: Done | R59: Done | S59: Not Done | T59: NA | U59: Not Done | V59: Not Done | W59: NA | X59: Not Done | Y59: Not Done | Z59: NA | AA59: No | AB59: No
A60: Milestone 1 | B60: N | C60: Finacle | D60: CRMUSER | E60: FINUAT | F60: ENTITYDOCUMENT | H60: 1.247 | I60: ENTITYDOCUMENTID, BANK_ID | J60: ENTITYDOCUMENTID,BANK_ID | L60: N | M60: BODATEMODIFIED | N60: CRM_DEV.finacle.CRMUSER_ENTITYDOCUMENT | O60: Done | P60: Done | Q60: Done | R60: Done | S60: Done | T60: NA | U60: Done | V60: Not Done | W60: NA | X60: Not Done | Y60: Not Done | Z60: NA | AA60: No | AB60: yes
A61: TBD | B61: N | C61: Digital Onboarding Tracking | D61: DEHUSEROB | E61: rakdehsit | F61: RETAIL_ACCOUNTS_MASTER | G61: 20-June to 25-June 2026 | H61: 1.2275391 | J61: PROSPECT_ID | O61: Not Done | P61: Not Done | Q61: Not Done | R61: Not Done | S61: Not Done | T61: NA | U61: Not Done | V61: Not Done | W61: NA | X61: Not Done | Y61: Not Done | Z61: NA | AA61: No | AB61: No
A62: Milestone 3 | B62: N | C62: Pay Hub Plus (NPSS Unity) | D62: dbo | E62: npss-epayment | F62: NPSS_RTPaymentsDtl_InwExn | G62: Due to AWS issue, End point has changed , Requested to FCR to replace with new end point | H62: 1.223 | I62: RTD_MsgGenDt,RTD_RefID | L62: Y | M62: RTD_MsgGenDt | N62: CRM_DEV.npss.DBO_NPSS_RTPAYMENTSDTL_INWEXN | O62: Done | P62: Done | Q62: Done | R62: Done | S62: Not Done | T62: NA | U62: Done | V62: Not Done | W62: NA | X62: Not Done | Y62: Not Done | Z62: NA | AA62: No | AB62: No
A63: Milestone 1 | B63: N | C63: IBPS | D63: dbo | E63: RAKCAS | F63: RB_SRO_EXTTABLE | H63: 1.197 | I63: ITEMINDEX,ITEMTYPE | J63: ITEMINDEX,ITEMTYPE | L63: Y | M63: Createddatetime column under Wfinstrumenttable | N63: CRM_DEV.ibps.DBO_RB_SRO_EXTTABLE | O63: Done | P63: Done | Q63: Done | R63: Done | S63: Done | T63: NA | U63: Done | V63: Not Done | W63: NA | X63: Not Done | Y63: Not Done | Z63: NA | AA63: No | AB63: No
A64: Milestone 1 | B64: N | C64: Finacle | D64: CRMUSER | E64: FINUAT | F64: PhoneEmail | H64: 1.123 | I64: PHONEEMAILID, BANK_ID | J64: PHONEEMAILID, BANK_ID | L64: N | M64: TMDATE | N64: CRM_DEV.finacle.CRMUSER_PHONEEMAIL | O64: Done | P64: Done | Q64: Done | R64: Done | S64: Done | T64: NA | U64: Done | V64: Not Done | W64: NA | X64: Not Done | Y64: Not Done | Z64: NA | AA64: No | AB64: yes
A65: Milestone 3 | B65: N | C65: PRIME | D65: TCTDBS | E65: PRIMEDB | F65: CINSTALMENTS | H65: 1.11 | I65: SERNO , PARTITIONKEY | J65: SERNO | L65: N | N65: CRM_DEV.prime4.TCTDBS_CINSTALMENTS | O65: Done | P65: Done | Q65: Done | R65: Done | S65: Not Done | T65: NA | U65: Done | V65: Not Done | W65: NA | X65: Not Done | Y65: Not Done | Z65: NA | AA65: No | AB65: No
A66: TBD | B66: Y | C66: Digital Banking Admin | D66: ECECUSER | E66: CNVGNIB | F66: RAK_USER_ENDI_TABLE | G66: 20-June to 22-June 2026 | H66: 0.958 | L66: Y | M66: R_cre_time | O66: NA | P66: NA | Q66: NA | R66: NA | S66: NA | T66: Not Done | U66: NA | V66: NA | W66: Not Done | X66: NA | Y66: NA | Z66: Not Done | AA66: No | AB66: No
A67: Milestone 3 | B67: N | C67: PRIME | D67: TCTDBS | E67: PRIMEDB | F67: CACCOUNTSTMT | H67: 0.955 | I67: NA | J67: SERNO | L67: Y | M67: STMTNEXTDATE | N67: CRM_DEV.prime4.TCTDBS_CACCOUNTSTMT | O67: Done | P67: Done | Q67: Done | R67: Done | S67: Not Done | T67: NA | U67: Done | V67: Not Done | W67: NA | X67: Not Done | Y67: Not Done | Z67: NA | AA67: No | AB67: No
A68: Milestone 1 | B68: N | C68: IBPS | D68: DBO | E68: RAKCAS | F68: RB_SRB_EXTTABLE | H68: 0.915 | I68: ITEMINDEX,ITEMTYPE | J68: ITEMINDEX,ITEMTYPE | L68: Y | M68: Createddatetime column under Wfinstrumenttable | N68: CRM_DEV.ibps.DBO_RB_SRB_EXTTABLE | O68: Done | P68: Done | Q68: Done | R68: Done | S68: Done | T68: NA | U68: Done | V68: Not Done | W68: NA | X68: Not Done | Y68: Not Done | Z68: NA | AA68: No | AB68: No
A69: Milestone 2 | B69: N | C69: PRIME | D69: TCTDBS | E69: PRIMEDB | F69: CARDEMBOSSING | H69: 0.791 | I69: SERNO | J69: SERNO | L69: N | N69: CRM_DEV.prime4.TCTDBS_CARDEMBOSSING | O69: Done | P69: Done | Q69: Done | R69: Done | S69: Dev Done | T69: NA | U69: Done | V69: Not Done | W69: NA | X69: Not Done | Y69: Not Done | Z69: NA | AA69: No | AB69: No
A70: Milestone 1 | B70: N | C70: IBPS | D70: dbo | E70: RAKCAS | F70: RB_SRM_EXTTABLE | H70: 0.79 | I70: ITEMINDEX,ITEMTYPE | J70: ITEMINDEX,ITEMTYPE | L70: Y | M70: Createddatetime column under Wfinstrumenttable | N70: CRM_DEV.ibps.DBO_RB_SRM_EXTTABLE | O70: Done | P70: Done | Q70: Done | R70: Done | S70: Done | T70: NA | U70: Done | V70: Not Done | W70: NA | X70: Not Done | Y70: Not Done | Z70: NA | AA70: No | AB70: No
A71: Milestone 3 | B71: N | C71: Finacle | D71: TBAADM | E71: FINUAT | F71: ACCT_AUTH_SIGN_TABLE | H71: 0.728 | I71: NMA_KEY_ID, CUST_ID, STMT_CUST_ID | J71: ACID, ACCT_POA_AS_SRL_NUM, BANK_ID | L71: N | M71: LCHG_TIME | N71: CRM_DEV.finacle.TBAADM_ACCT_AUTH_SIGN_TABLE | O71: Done | P71: Done | Q71: Done | R71: Done | S71: Done | T71: NA | U71: Done | V71: Not Done | W71: NA | X71: Not Done | Y71: Not Done | Z71: NA | AA71: No | AB71: No
A72: Milestone 1 | B72: N | C72: IBPS | D72: DBO | E72: RAKCAS | F72: RB_BSR_EXTTABLE | H72: 0.727 | I72: ITEMINDEX,ITEMTYPE | J72: ITEMINDEX,ITEMTYPE | L72: Y | M72: Createddatetime column under Wfinstrumenttable | N72: CRM_DEV.ibps.DBO_RB_BSR_EXTTABLE | O72: Done | P72: Done | Q72: Done | R72: Done | S72: Done | T72: NA | U72: Done | V72: Not Done | W72: NA | X72: Not Done | Y72: Not Done | Z72: NA | AA72: No | AB72: No
A73: Milestone 1 | B73: N | C73: IBPS | D73: dbo | E73: RAKCAS | F73: NG_DCC_EXTTABLE | H73: 0.712 | I73: ITEMINDEX,ITEMTYPE | J73: ITEMINDEX,ITEMTYPE | L73: Y | M73: Createddatetime column under Wfinstrumenttable | N73: CRM_DEV.ibps.DBO_NG_DCC_EXTTABLE | O73: Done | P73: Done | Q73: Done | R73: Done | S73: Done | T73: NA | U73: Done | V73: Not Done | W73: NA | X73: Not Done | Y73: Not Done | Z73: NA | AA73: No | AB73: No
A74: Milestone 1 | B74: N | C74: IBPS | D74: dbo | E74: RAKCAS | F74: NG_DAO_EXTTABLE | H74: 0.7 | I74: ITEMINDEX,ITEMTYPE | J74: ITEMINDEX,ITEMTYPE | L74: Y | M74: Createddatetime column under Wfinstrumenttable | N74: CRM_DEV.ibps.DBO_NG_DAO_EXTTABLE | O74: Done | P74: Done | Q74: Done | R74: Done | S74: Done | T74: NA | U74: Done | V74: Not Done | W74: NA | X74: Not Done | Y74: Not Done | Z74: NA | AA74: No | AB74: No
A75: Milestone 3 | B75: N | C75: Pay Hub Plus (NPSS Unity) | D75: dbo | E75: npss-epayment | F75: NPSS_RTS_PmtStatusDtl_Dbtr | G75: Due to AWS issue, End point has changed , Requested to FCR to replace with new end point | H75: 0.655 | I75: RT_STD_MsgGenDt,RT_STD_RefId | L75: N | M75: RT_STD_MsgGenDt | N75: CRM_DEV.npss.DBO_NPSS_RTS_PMTSTATUSDTL_DBTR | O75: Done | P75: Done | Q75: Done | R75: Done | S75: Not Done | T75: NA | U75: Done | V75: Not Done | W75: NA | X75: Not Done | Y75: Not Done | Z75: NA | AA75: No | AB75: No
A76: Milestone 2 | B76: N | C76: Finacle | D76: CRMUSER | E76: FINUAT | F76: DEMOGRAPHIC | H76: 0.641 | I76: DEMOGRAPHICID, BANK_ID | J76: DEMOGRAPHICID,BANK_ID | L76: N | M76: BODATEMODIFIED | N76: CRM_DEV.finacle.CRMUSER_DEMOGRAPHIC | O76: Done | P76: Done | Q76: Done | R76: Done | S76: Done | T76: NA | U76: Done | V76: Not Done | W76: NA | X76: Not Done | Y76: Not Done | Z76: NA | AA76: No | AB76: yes
A77: TBD | B77: N | C77: Digital Onboarding Tracking | D77: DEHUSEROB | E77: rakdehsit | F77: RETAIL_ONBOARDING_MASTER | G77: 20-June to 25-June 2026 | H77: 0.63378906 | J77: PROSPECT_ID | O77: Not Done | P77: Not Done | Q77: Not Done | R77: Not Done | S77: Not Done | T77: NA | U77: Not Done | V77: Not Done | W77: NA | X77: Not Done | Y77: Not Done | Z77: NA | AA77: No | AB77: No
A78: TBD | B78: N | C78: Finacle | D78: TBAADM | E78: FINUAT | F78: GL_SUB_HEAD_TABLE | G78: 01-June to 15-June 2026 | H78: 0.618 | I78: SOL_ID, GL_SUB_HEAD_CODE, CRNCY_CODE, BANK_ID | J78: SOL_ID, GL_SUB_HEAD_CODE, CRNCY_CODE, BANK_ID | L78: N | M78: LCHG_TIME | O78: Done | P78: Done | Q78: Done | R78: Done | S78: Not Done | T78: NA | U78: Not Done | V78: Not Done | W78: NA | X78: Not Done | Y78: Not Done | Z78: NA | AA78: No | AB78: yes
A79: Milestone 1 | B79: N | C79: IBPS | D79: dbo | E79: RAKCAS | F79: RB_CU_EXTTABLE | H79: 0.616 | I79: ITEMINDEX,ITEMTYPE | J79: ITEMINDEX,ITEMTYPE | L79: Y | M79: Createddatetime column under Wfinstrumenttable | N79: CRM_DEV.ibps.DBO_RB_CU_EXTTABLE | O79: Done | P79: Done | Q79: Done | R79: Done | S79: Done | T79: NA | U79: Done | V79: Not Done | W79: NA | X79: Not Done | Y79: Not Done | Z79: NA | AA79: No | AB79: No
A80: Milestone 3 | B80: N | C80: PRIME | D80: TCTDBS | E80: PRIMEDB | F80: CCUSTOMERS | H80: 0.612 | I80: SERNO | J80: SERNO | L80: N | N80: CRM_DEV.prime4.TCTDBS_CCUSTOMERS | O80: Done | P80: Done | Q80: Done | R80: Done | S80: Not Done | T80: NA | U80: Done | V80: Not Done | W80: NA | X80: Not Done | Y80: Not Done | Z80: NA | AA80: No | AB80: No
A81: Milestone 3 | B81: N | C81: CPF | D81: DBO | E81: cpf_platform_dev | F81: customer_consent_audit | H81: 0.597 | I81: id | J81: consent_config_id,id | K81: id | L81: Y | M81: last_updated_at | N81: CRM_DEV.cpf.DBO_CUSTOMER_CONSENT_AUDIT | O81: Done | P81: Done | Q81: Done | R81: Done | S81: Done | T81: NA | U81: Done | V81: Not Done | W81: NA | X81: Not Done | Y81: Not Done | Z81: NA | AA81: No | AB81: yes
A82: Milestone 2 | B82: N | C82: CCM | D82: WRM | E82: WRM | F82: DeliveryRegistration | H82: 0.58984375 | I82: ID | L82: Y | M82: CreationDate | N82: CRM_DEV.ccm.DBO_DELIVERYREGISTRATION | O82: Done | P82: Done | Q82: Done | R82: Done | S82: Done | T82: NA | U82: Done | V82: Not Done | W82: NA | X82: Not Done | Y82: Not Done | Z82: NA | AA82: No | AB82: No
A83: Milestone 3 | B83: N | C83: Finacle | D83: TBAADM | E83: FINUAT | F83: GEN_ACCT_CLASS_TABLE | H83: 0.537 | I83: INT_CR_ACID, INT_DR_ACID, ACID, BANK_ID | J83: ACID | L83: N | M83: LCHG_TIME | N83: CRM_DEV.finacle.TBAADM_GEN_ACCT_CLASS_TABLE | O83: Done | P83: Done | Q83: Done | R83: Done | S83: Done | T83: NA | U83: Done | V83: Not Done | W83: NA | X83: Not Done | Y83: Not Done | Z83: NA | AA83: No | AB83: yes
A84: Milestone 2 | B84: N | C84: CPF | D84: DBO | E84: cpf_platform_dev | F84: customer_consent | H84: 0.537 | I84: id | J84: consent_config_id,customer_id,id | K84: id | L84: N | N84: CRM_DEV.cpf.DBO_CUSTOMER_CONSENT | O84: Done | P84: Done | Q84: Done | R84: Done | S84: Done | T84: NA | U84: Done | V84: Not Done | W84: NA | X84: Not Done | Y84: Not Done | Z84: NA | AA84: No | AB84: yes
A85: Milestone 1 | B85: N | C85: IBPS | D85: dbo | E85: RAKCAS | F85: RB_TL_EXTTABLE | H85: 0.448 | I85: ITEMINDEX,ITEMTYPE | J85: ITEMINDEX,ITEMTYPE | L85: Y | M85: Createddatetime column under Wfinstrumenttable | N85: CRM_DEV.ibps.DBO_RB_TL_EXTTABLE | O85: Done | P85: Done | Q85: Done | R85: Done | S85: Done | T85: NA | U85: Done | V85: Not Done | W85: NA | X85: Not Done | Y85: Not Done | Z85: NA | AA85: No | AB85: No
A86: TBD | B86: Y | C86: CAPS | D86: CAPSADMIN | E86: CAPS | F86: ACCOUNTS | G86: 15-June to 19-June 2026 | H86: 0.429 | I86: ACCOUNTNO | J86: org_key | O86: NA | P86: NA | Q86: NA | R86: NA | S86: NA | T86: Not Done | U86: NA | V86: NA | W86: Not Done | X86: NA | Y86: NA | Z86: Not Done | AA86: No | AB86: No
A87: Milestone 3 | B87: Y | C87: CAPS | D87: CAPSADMIN | E87: Dealing | F87: CARDS | H87: 0.409 | I87: CRNNO | J87: CRNNO | N87: CRM_DEV.caps.CAPSADMIN_CARDS | O87: NA | P87: NA | Q87: NA | R87: NA | S87: NA | T87: Done | U87: NA | V87: NA | W87: Done | X87: Not Done | Y87: NA | Z87: Not Done | AA87: No | AB87: No
A88: Milestone 3 | B88: N | C88: Finacle | D88: DEDUPADM | E88: FINUAT | F88: OPERATIONSREASONCODES_DEDUP | H88: 0.381 | I88: REASONCODEID, BANK_ID, BLACKLISTDATASETID, NEGATIVELISTDATASETID | J88: reasoncodeid | L88: N | N88: CRM_DEV.finacle.DEDUPADM_OPERATIONSREASONCODES_DEDUP | O88: Done | P88: Done | Q88: Done | R88: Done | S88: Done | T88: NA | U88: Done | V88: Not Done | W88: NA | X88: Not Done | Y88: Not Done | Z88: NA | AA88: No | AB88: No
A89: TBD | B89: N | C89: Digital Onboarding Tracking | D89: DEHUSEROB | E89: rakdehsit | F89: PERSONAL_LOAN_REQUEST_DET | G89: 20-June to 25-June 2026 | H89: 0.375 | J89: PROSPECT_ID | O89: Not Done | P89: Not Done | Q89: Not Done | R89: Not Done | S89: Not Done | T89: NA | U89: Not Done | V89: Not Done | W89: NA | X89: Not Done | Y89: Not Done | Z89: NA | AA89: No | AB89: No
A90: Milestone 3 | B90: N | C90: Finacle | D90: CRMUSER | E90: FINUAT | F90: psychographic | H90: 0.366 | I90: PSYCHOGRAPHICID, BANK_ID | J90: PSYCHOGRAPHICID,BANK_ID | L90: N | M90: BODATEMODIFIED | N90: CRM_DEV.finacle.CRMUSER_PSYCHOGRAPHIC | O90: Done | P90: Done | Q90: Done | R90: Done | S90: Done | T90: NA | U90: Done | V90: Not Done | W90: NA | X90: Not Done | Y90: Not Done | Z90: NA | AA90: No | AB90: yes
A91: Milestone 4 | B91: N | C91: Finacle | D91: TBAADM | E91: FINUAT | F91: CHQ_BOOK_TABLE | H91: 0.358 | I91: BEGIN_CHQ_NUM, ACID, BEGIN_CHQ_ALPHA, BANK_ID | J91: ACID,BEGIN_CHQ_NUM | L91: N | M91: LCHG_TIME | N91: CRM_DEV.finacle.TBAADM_CHQ_BOOK_TABLE | O91: Done | P91: Done | Q91: Done | R91: Done | S91: Done | T91: NA | U91: Done | V91: Not Done | W91: NA | X91: Not Done | Y91: Not Done | Z91: NA | AA91: No | AB91: No
A92: TBD | B92: N | C92: Finacle | D92: TBAADM | E92: FINUAT | F92: LIM_HISTORY_TABLE | G92: 01-June to 15-June 2026 | H92: 0.358 | I92: ACID, SERIAL_NUM, BANK_ID | J92: ACID, SERIAL_NUM, BANK_ID | L92: N | M92: LCHG_TIME | O92: Done | P92: Done | Q92: Done | R92: Done | S92: Not Done | T92: NA | U92: Not Done | V92: Not Done | W92: NA | X92: Not Done | Y92: Not Done | Z92: NA | AA92: No | AB92: yes
A93: Milestone 3 | B93: N | C93: Finacle | D93: CUSTOM | E93: FINUAT | F93: C_PORD_REMIT_INR | G93: NonPK | H93: 0.348 | I93: PYMT_REF_NUM, BANK_ID | J93: PYMT_REF_NUM, BANK_ID | L93: N | M93: LCHG_TIME | N93: CRM_DEV.finacle.CUSTOM_C_PORD_REMIT_INR | O93: Done | P93: Done | Q93: Done | R93: Done | S93: Not Done | T93: NA | U93: Done | V93: Not Done | W93: NA | X93: Not Done | Y93: Not Done | Z93: NA | AA93: No | AB93: No
A94: TBD | B94: Y | C94: Digital Banking Admin | D94: ECECUSER | E94: CNVGNIB | F94: SECUREIDTABLE | G94: 20-June to 22-June 2026 | H94: 0.304 | I94: ORG_ID, BANK_ID, USER_ID, AUTH_MODE | L94: N | O94: NA | P94: NA | Q94: NA | R94: NA | S94: NA | T94: Not Done | U94: NA | V94: NA | W94: Not Done | X94: NA | Y94: NA | Z94: Not Done | AA94: No | AB94: No
A95: Milestone 3 | B95: Y | C95: CAPS | D95: CAPSADMIN | E95: Dealing | F95: CARD_GENERAL | H95: 0.273 | I95: CRNNO | J95: CRNNO | N95: CRM_DEV.caps.CAPSADMIN_CARD_GENERAL | O95: NA | P95: NA | Q95: NA | R95: NA | S95: NA | T95: Done | U95: NA | V95: NA | W95: Done | X95: Not Done | Y95: NA | Z95: Not Done | AA95: No | AB95: No
A96: Milestone 1 | B96: Y | C96: RLS | D96: FIN_LEAM | E96: RLSPROD | F96: NBFC_CUSTOMER_M | H96: 0.267 | I96: GCDNO | J96: CUSTOMERID | L96: N | N96: CRM_DEV.rls.LOS0909_NBFC_CUSTOMER_M | O96: NA | P96: NA | Q96: NA | R96: NA | S96: NA | T96: Done | U96: NA | V96: NA | W96: Done | X96: Not Done | Y96: NA | Z96: Not Done | AA96: No | AB96: Yes
A97: Milestone 3 | B97: N | C97: Finacle | D97: TBAADM | E97: FINUAT | F97: MEMO_PAD_TABLE | H97: 0.265 | I97: ACID, MP_INTENT, MP_FUNC,KEY_WORD, TRAN_DATE, TRAN_ID, PART_TRAN_SRL_NUM | J97: MP_SRL_NUM | L97: N | M97: LCHG_TIME | N97: CRM_DEV.finacle.TBAADM_MEMO_PAD_TABLE | O97: Done | P97: Done | Q97: Done | R97: Done | S97: Done | T97: NA | U97: Done | V97: Not Done | W97: NA | X97: Not Done | Y97: Not Done | Z97: NA | AA97: No | AB97: yes
A98: TBD | B98: N | C98: Finacle | D98: CRMUSER | E98: FINUAT | F98: CorpMiscellaneousInfo | G98: 01-June to 15-June 2026 | H98: 0.264 | I98: CORP_MISC_ID, BANK_ID | J98: CORP_MISC_ID,BANK_ID | L98: N | M98: TMDATE | N98: CRM_DEV.prime.TCTDBS_CARDSTATUSX | O98: Done | P98: Done | Q98: Done | R98: Done | S98: Not Done | T98: NA | U98: Not Done | V98: Not Done | W98: NA | X98: Not Done | Y98: Not Done | Z98: NA | AA98: No | AB98: yes
A99: Milestone 1 | B99: Y | C99: RLS | D99: FIN_LEAM | E99: RLSPROD | F99: LEA_AGREEMENT_DTL | H99: 0.24 | I99: Agreementid | J99: PROPOSALID | L99: N | N99: CRM_DEV.rls.FIN_LEAM_LEA_AGREEMENT_DTL | O99: NA | P99: NA | Q99: NA | R99: NA | S99: NA | T99: Done | U99: NA | V99: NA | W99: Done | X99: Not Done | Y99: NA | Z99: Not Done | AA99: No | AB99: No
A100: Milestone 1 | B100: N | C100: Finacle | D100: CRMUSER | E100: FINUAT | F100: corporate | H100: 0.226 | I100: CORP_ID, BANK_ID | J100: CORP_ID, BANK_ID | L100: N | M100: BODATEMODIFIED | N100: CRM_DEV.finacle.CRMUSER_CORPORATE | O100: Done | P100: Done | Q100: Done | R100: Done | S100: Done | T100: NA | U100: Done | V100: Not Done | W100: NA | X100: Not Done | Y100: Not Done | Z100: NA | AA100: No | AB100: yes
...

Sheet New_DV_Ing
A1: Source system | B1: Source table name | C1: Data ingestion CRM_DEV | D1: Data ingestion CRM_SIT from UAT2 | E1: Data ingestion CRM_UAT from UAT2 | H1: Milestone | I1: System | J1: Schema Name | K1: Dataverse Table name | L1: Source table name | M1: Source Enforced Primary Key | N1: Primary key | O1: Day-0 load in Dataverse DEV Source : UAT2 Approach : ADF | P1: Continuous load in Dataverse DEV Source : UAT2 Approach :ADF Microbatch | Q1: Day-0 load in Dataverse UAT Source : UAT2 Approach : ADF | R1: Continuous load in Dataverse UAT Source : UAT2 Approach : ADF Microbatch | S1: Day-0 load in Dataverse PT Source : UAT2 Approach : ADF | T1: Continuous load in in Dataverse PT Source : UAT2 Approach : ADF Microbatch | U1: Day-0 load in Dataverse Preprod Source : UAT1 Approach : ADF | V1: Continuous load inin Dataverse Preprod Source : UAT1 Approach : ADF Microbatch
A2: Finacle | B2: accounts | H2: Milestone 1 | I2: Finacle | J2: CRMUSER | K2: Contact | L2: Accounts | N2: org_key | O2: Done | P2: Not done | Q2: Not done | R2: Not done | S2: Not done | T2: Not done | U2: Not done | V2: Not done
A3: Finacle | B3: ENTITYDOCUMENT | H3: Milestone 1 | I3: Finacle | J3: CRMUSER | K3: Finacle_CRMUser_EntityDocument | L3: ENTITYDOCUMENT | N3: ENTITYDOCUMENTID,BANK_ID | O3: Done | P3: Not done | Q3: Not done | R3: Not done | S3: Not done | T3: Not done | U3: Not done | V3: Not done
A4: Finacle | B4: MiscellaneousInfo | H4: Milestone 2 | I4: Finacle | J4: CRMUSER | K4: Finacle_CRMUser_MiscellaneousInfo | L4: MiscellaneousInfo | N4: MISCELLANEOUSID,BANK_ID | O4: Done | P4: Not done | Q4: Not done | R4: Not done | S4: Not done | T4: Not done | U4: Not done | V4: Not done
A5: Finacle | B5: corporate | H5: Milestone 1 | I5: Finacle | J5: CRMUSER | K5: Account | L5: corporate | N5: CORP_ID, BANK_ID | O5: Done | P5: Not done | Q5: Done | R5: Not done | S5: Not done | T5: Not done | U5: Not done | V5: Not done
H6: Milestone 3 | I6: Finacle | J6: CRMUSER | K6: Account | L6: Accounts | N6: org_key | O6: Done | P6: Not done | Q6: Done | R6: Not done | S6: Not done | T6: Not done | U6: Not done | V6: Not done
A7: Finacle | B7: PhoneEmail | H7: Milestone 1 | I7: Finacle | J7: CRMUSER | K7: Finacle_CRMUser_PhoneEmail | L7: PhoneEmail | N7: PHONEEMAILID, BANK_ID | O7: Done | P7: Not done | Q7: Not done | R7: Not done | S7: Not done | T7: Not done | U7: Not done | V7: Not done
A8: Finacle | B8: Person | H8: Milestone 1 | I8: Finacle | J8: CRMUSER | K8: Customer RM | L8: Person | N8: PERSONID | O8: Done | P8: Not done | Q8: Not done | R8: Not done | S8: Not done | T8: Not done | U8: Not done | V8: Not done
A9: Finacle | B9: agent_entity_details | H9: Milestone 2 | I9: Finacle | J9: CRMUSER | K9: Customer RM | L9: agent_entity_details | N9: DETAIL_RECORD_ID,PERSONID,BANK_ID | O9: Done | P9: Not done | Q9: Not done | R9: Not done | S9: Not done | T9: Not done | U9: Not done | V9: Not done
A10: Finacle | B10: bizcenter | H10: Milestone 2 | I10: Finacle | J10: CRMUSER | K10: Fincale_CRMUser_BizCenter | L10: bizcenter | N10: BCID | O10: Done | P10: Not done | Q10: Not done | R10: Not done | S10: Not done | T10: Not done | U10: Not done | V10: Not done
A11: Finacle | B11: DEMOGRAPHIC | H11: Milestone 2 | I11: Finacle | J11: CRMUSER | K11: Finacle_CRMUser_Demographic | L11: DEMOGRAPHIC | N11: DEMOGRAPHICID,BANK_ID | O11: Done | P11: Not done | Q11: Not done | R11: Not done | S11: Not done | T11: Not done | U11: Not done | V11: Not done
A12: Finacle | B12: GENERAL_ACCT_MAST_TABLE | H12: Milestone 2 | I12: Finacle | J12: TBAADM | K12: Customer Products | L12: GENERAL_ACCT_MAST_TABLE | N12: ACID | O12: Done | P12: Not done | Q12: Not done | R12: Not done | S12: Not done | T12: Not done | U12: Not done | V12: Not done
A13: Finacle | B13: Incidents | H13: Milestone 1 | I13: Finacle | J13: CRMUSER | K13: Customer Products | L13: Incidents | N13: INCIDENTID,BANK_ID | O13: Done | P13: Not done | Q13: Not done | R13: Not done | S13: Not done | T13: Not done | U13: Not done | V13: Not done
A14: PRIME | B14: CARDX | H14: Milestone 1 | I14: PRIME | J14: TCTDBS | K14: Customer Products | L14: CARDX | N14: SERNO | O14: Done | P14: Not done | Q14: Not done | R14: Not done | S14: Not done | T14: Not done | U14: Not done | V14: Not done
A15: RLS | B15: LEA_AGREEMENT_DTL | H15: Milestone 1 | I15: RLS | J15: FIN_LEAM | K15: Customer Products | L15: LEA_AGREEMENT_DTL | N15: PROPOSALID | O15: Done | P15: Not done | Q15: Not done | R15: Not done | S15: Not done | T15: Not done | U15: Not done | V15: Not done
A16: WMS | B16: WMS_INV_GEN_DTLS_TBL | H16: Milestone 1 | I16: WMS | J16: TBAADM | K16: Customer Products | L16: WMS_INV_GEN_DTLS_TBL | N16: INV_ID | O16: Done | P16: Not done | Q16: Not done | R16: Not done | S16: Not done | T16: Not done | U16: Not done | V16: Not done
A17: Digital Banking Admin | B17: MULTI_LEVEL_WORKFLOW_TABLE | H17: Milestone 1 | I17: Digital Banking Admin | J17: ECECUSER | K17: Customer Services | L17: MULTI_LEVEL_WORKFLOW_TABLE | O17: Done | P17: Not done | Q17: Not done | R17: Not done | S17: Not done | T17: Not done | U17: Not done | V17: Not done
A18: IBPS | B18: wfinstrumenttable | H18: Milestone 1 | I18: IBPS | J18: DBO | K18: Customer Services | L18: wfinstrumenttable | N18: ProcessInstanceID,WorkItemId | O18: Done | P18: Not done | Q18: Not done | R18: Not done | S18: Not done | T18: Not done | U18: Not done | V18: Not done
A19: IDD | B19: IDD_INSURANCE_POLICY_DTL_T | H19: Milestone 1 | I19: IDD | J19: dbo | K19: Customer Services | L19: IDD_INSURANCE_POLICY_DTL_T | O19: Not done | P19: Not done | Q19: Not done | R19: Not done | S19: Not done | T19: Not done | U19: Not done | V19: Not done
A20: Prospect | B20: PROSPECT_CALLS | H20: Milestone 1 | I20: Prospect | J20: dbo | K20: Customer Services | L20: PROSPECT_CALLS | O20: Done | P20: Not done | Q20: Not done | R20: Not done | S20: Not done | T20: Not done | U20: Not done | V20: Not done
H21: Milestone 1 | I21: Digital Banking Admin | J21: ECECUSER | K21: Customer Services | L21: CUSTOMER_MASTER | N21: BANK_ID,BAY_USER_ID

Sheet DataIngestion_SQLfulllist
A1: Milestone | B1: ADF Batch? | C1: System | D1: Schema Name | E1: DB name | F1: Source table name | G1: Table Size in PROD(inGb) | H1: Source Enforced Primary Key | I1: Primary key | J1: Transactional table? | K1: Date column | L1: CRM DB table name | M1: Day-0 load in SQL DB DB : DEV Source : UAT 2 Approach : Confluent snapshot or ADF (SQL SINK) | N1: Continuous load in SQL DB DB : DEV Source : UAT 2 Approach : Confluent RTS (SQL Sink) | O1: Batch load in SQL DB DB : DEV Source : UAT2 Approach : ADF
A2: Milestone 1 | B2: N | C2: Finacle | D2: CRMUSER | E2: FINUAT | F2: accounts | G2: 2.185326 | H2: ACCOUNTID, BANK_ID | I2: org_key | J2: N | K2: BODATEMODIFIED | L2: CRM_DEV.finacle.CRMUSER_ACCOUNTS | M2: DONE | N2: DONE | O2: NA
A3: Milestone 1 | B3: N | C3: Finacle | D3: CRMUSER | E3: FINUAT | F3: corporate | G3: 0.226 | H3: CORP_ID, BANK_ID | I3: CORP_ID, BANK_ID | J3: N | K3: BODATEMODIFIED | L3: CRM_DEV.finacle.CRMUSER_CORPORATE | M3: DONE | N3: DONE | O3: NA
A4: Milestone 1 | B4: N | C4: Finacle | D4: CRMUSER | E4: FINUAT | F4: ENTITYDOCUMENT | G4: 1.247 | H4: ENTITYDOCUMENTID, BANK_ID | I4: ENTITYDOCUMENTID,BANK_ID | J4: N | K4: BODATEMODIFIED | L4: CRM_DEV.finacle.CRMUSER_ENTITYDOCUMENT | M4: DONE | N4: DONE | O4: NA
A5: Milestone 1 | B5: N | C5: Finacle | D5: CRMUSER | E5: FINUAT | F5: Person | G5: 0.001 | H5: PERSONID | I5: PERSONID | J5: N | K5: TMDATE | L5: CRM_DEV.finacle.CRMUSER_PERSON | M5: DONE | N5: DONE | O5: NA
A6: Milestone 1 | B6: N | C6: Finacle | D6: CRMUSER | E6: FINUAT | F6: PhoneEmail | G6: 1.123 | H6: PHONEEMAILID, BANK_ID | I6: PHONEEMAILID, BANK_ID | J6: N | K6: TMDATE | L6: CRM_DEV.finacle.CRMUSER_PHONEEMAIL | M6: DONE | N6: DONE | O6: NA
A7: Milestone 1 | B7: N | C7: Finacle | D7: CRMUSER | E7: FINUAT | F7: categories | G7: 0.204 | H7: CATEGORYID, BANK_ID | I7: CATEGORYID,BANK_ID | J7: N | K7: TMDATE | L7: CRM_DEV.finacle.CRMUSER_CATEGORIES | M7: DONE | N7: DONE | O7: NA
A8: Milestone 1 | B8: N | C8: Finacle | D8: CRMUSER | E8: FINUAT | F8: category_lang | G8: 0.144 | H8: CATEGORYLANGID, BANK_ID | I8: CATEGORYLANGID,BANK_ID | J8: N | K8: TMDATE | L8: CRM_DEV.finacle.CRMUSER_CATEGORY_LANG | M8: DONE | N8: DONE | O8: NA
A9: Milestone 1 | B9: N | C9: Finacle | D9: CRMUSER | E9: FINUAT | F9: Incidents | G9: 4.749 | H9: INCIDENTID, BANK_ID | I9: INCIDENTID,BANK_ID | J9: N | K9: BODATEMODIFIED | L9: CRM_DEV.finacle.CRMUSER_INCIDENTS | M9: DONE | N9: DONE | O9: NA
A10: Milestone 2 | B10: N | C10: Finacle | D10: CRMUSER | E10: FINUAT | F10: agent_entity_details | G10: 0 | H10: DETAIL_RECORD_ID, PERSONID, BANK_ID | I10: DETAIL_RECORD_ID,PERSONID,BANK_ID | J10: N | K10: TMDATE | L10: CRM_DEV.finacle.CRMUSER_AGENT_ENTITY_DETAILS | M10: DONE | N10: DONE | O10: NA
A11: Milestone 2 | B11: N | C11: Finacle | D11: CRMUSER | E11: FINUAT | F11: bizcenter | G11: 0 | H11: BCID | I11: BCID | J11: N | K11: BODATEMODIFIED | L11: CRM_DEV.finacle.CRMUSER_BIZCENTER | M11: DONE | N11: DONE | O11: NA
A12: Milestone 2 | B12: N | C12: Finacle | D12: CRMUSER | E12: FINUAT | F12: DEMOGRAPHIC | G12: 0.641 | H12: DEMOGRAPHICID, BANK_ID | I12: DEMOGRAPHICID,BANK_ID | J12: N | K12: BODATEMODIFIED | L12: CRM_DEV.finacle.CRMUSER_DEMOGRAPHIC | M12: DONE | N12: DONE | O12: NA
A13: Milestone 2 | B13: N | C13: Finacle | D13: CRMUSER | E13: FINUAT | F13: EXTN_BODATA | H13: EXTENSIONID, BANK_ID | I13: extensionid | J13: N | K13: TMDATE | L13: CRM_DEV.finacle.CRMUSER_EXTN_BODATA | M13: DONE | N13: DONE | O13: NA
A14: Milestone 2 | B14: N | C14: Finacle | D14: CRMUSER | E14: FINUAT | F14: MiscellaneousInfo | G14: 1.624 | H14: MISCELLANEOUSID, BANK_ID | I14: MISCELLANEOUSID,BANK_ID | J14: N | K14: TMDATE | L14: CRM_DEV.finacle.CRMUSER_MISCELLANEOUSINFO | M14: DONE | N14: DONE | O14: NA
A15: Milestone 3 | B15: N | C15: Finacle | D15: CRMUSER | E15: FINUAT | F15: Address | G15: 2.422 | H15: ADDRESSID, BANK_ID | I15: ADDRESSID,BANK_ID | J15: N | K15: TMDATE | L15: CRM_DEV.finacle.CRMUSER_ADDRESS | M15: DONE | N15: DONE | O15: NA
A16: Milestone 3 | B16: N | C16: Finacle | D16: CRMUSER | E16: FINUAT | F16: entityrelationship | G16: 0.045 | H16: ENTITYRELATIONSHIPID, BANK_ID | I16: ENTITYRELATIONSHIPID,BANK_ID | J16: N | K16: BODATEMODIFIED | L16: CRM_DEV.finacle.CRMUSER_ENTITYRELATIONSHIP | M16: DONE | N16: DONE | O16: NA
A17: Milestone 3 | B17: N | C17: Finacle | D17: CRMUSER | E17: FINUAT | F17: memberships | G17: 0.109 | H17: MEMBERSHIPSID, BANK_ID | I17: MEMBERSHIPSID,BANK_ID | J17: N | K17: TMDATE | L17: CRM_DEV.finacle.CRMUSER_MEMBERSHIPS | M17: DONE | N17: DONE | O17: NA
A18: Milestone 3 | B18: N | C18: Finacle | D18: CRMUSER | E18: FINUAT | F18: preferences | G18: 0.047 | H18: PREFERENCE_ID, BANK_ID | I18: PREFERENCE,BANK_ID | J18: N | K18: BODATEMODIFIED | L18: CRM_DEV.finacle.CRMUSER_PREFERENCES | M18: DONE | N18: DONE | O18: NA
A19: Milestone 3 | B19: N | C19: Finacle | D19: CRMUSER | E19: FINUAT | F19: psychographic | G19: 0.366 | H19: PSYCHOGRAPHICID, BANK_ID | I19: PSYCHOGRAPHICID,BANK_ID | J19: N | K19: BODATEMODIFIED | L19: CRM_DEV.finacle.CRMUSER_PSYCHOGRAPHIC | M19: DONE | N19: DONE | O19: NA
A20: Milestone 3 | B20: N | C20: Finacle | D20: CRMUSER | E20: FINUAT | F20: users | G20: 0.001 | H20: PERSONID | I20: PERSONID | J20: N | K20: TMDATE | L20: CRM_DEV.finacle.CRMUSER_USERS | M20: DONE | N20: DONE | O20: NA
A21: Milestone 4 | B21: N | C21: Finacle | D21: CRMUSER | E21: FINUAT | F21: FinancialDetails | G21: 0.147 | H21: FINANCIAL_DETAILS_ID, BANK_ID | I21: FINANCIAL_DETAILS_ID,BANK_ID | J21: N | K21: TMDATE | L21: CRM_DEV.finacle.CRMUSER_FINANCIALDETAILS | M21: DONE | N21: DONE | O21: NA
A22: Milestone 4 | B22: N | C22: Finacle | D22: CRMUSER | E22: FINUAT | F22: Request | G22: 1.82 | H22: REQUESTID, BANK_ID | I22: REQUESTID,BANK_ID | J22: N | K22: BODATEMODIFIED | L22: CRM_DEV.finacle.CRMUSER_REQUEST | M22: DONE | N22: DONE | O22: NA
A23: TBD | B23: N | C23: Finacle | D23: CRMUSER | E23: FINUAT | F23: CorpMiscellaneousInfo | G23: 0.264 | H23: CORP_MISC_ID, BANK_ID | I23: CORP_MISC_ID,BANK_ID | J23: N | K23: TMDATE | L23: CRM_DEV.prime.TCTDBS_CARDSTATUSX | M23: DONE | N23: DONE | O23: NA
A24: TBD | B24: N | C24: Finacle | D24: CRMUSER | E24: FINUAT | F24: FINANCIAL | G24: 0.035 | H24: FINANCIAL_ID, BANK_ID | I24: FINANCIAL_ID,BANK_ID | J24: N | K24: BODATEMODIFIED | M24: Not Done | N24: Not Done | O24: NA
A25: TBD | B25: N | C25: Finacle | D25: CRMUSER | E25: FINUAT | F25: GROUPHOUSEHOLD | G25: 0.004 | H25: GROUPHOUSEHOLDID, BANK_ID | I25: GROUPHOUSEHOLDID,BANK_ID | J25: N | K25: TMDATE | M25: Not Done | N25: Not Done | O25: NA
A26: TBD | B26: N | C26: Finacle | D26: CRMUSER | E26: FINUAT | F26: GROUPHOUSEHOLDMASTER | G26: 0.001 | H26: GROUPHOUSEHOLDMASTERID, BANK_ID | I26: GROUPHOUSEHOLDMASTERID,BANK_ID | J26: N | K26: BODATEMODIFIED | M26: Not Done | N26: Not Done | O26: NA
A27: Milestone 3 | B27: N | C27: Finacle | D27: CUSTOM | E27: FINUAT | F27: CUST_LDFEE | G27: 0.001 | H27: CIF_TYPE, SCHM_CODE, AC_CURRENCY | J27: N | K27: LCHG_TIME | L27: CRM_DEV.finacle.CUSTOM_CUST_LDFEE | M27: DONE | N27: DONE | O27: NA
A28: Milestone 3 | B28: N | C28: Finacle | D28: CUSTOM | E28: FINUAT | F28: CUST_PAYGEN_ORD_TABLE | G28: 2.092 | H28: PYMT_REF_NUM | I28: pymt_ref_num | J28: N | K28: LCHG_TIME | L28: CRM_DEV.finacle.CUSTOM_CUST_PAYGEN_ORD_TABLE | M28: DONE | N28: DONE | O28: NA
A29: Milestone 3 | B29: N | C29: Finacle | D29: CUSTOM | E29: FINUAT | F29: C_PORD_REMIT_INR | G29: 0.348 | H29: PYMT_REF_NUM, BANK_ID | I29: pymt_ref_num | J29: N | K29: LCHG_TIME | L29: CRM_DEV.finacle.CUSTOM_C_PORD_REMIT_INR | M29: DONE | N29: DONE | O29: NA
A30: Milestone 3 | B30: N | C30: Finacle | D30: CUSTOM | E30: FINUAT | F30: CUST_REJECT | H30: PYMT_REF_NUM | J30: N | K30: VALUE_DATE | L30: CRM_DEV.finacle.CUSTOM_CUST_REJECT | M30: DONE | N30: DONE | O30: NA
A31: Milestone 3 | B31: N | C31: Finacle | D31: CUSTOM | E31: FINUAT | F31: CUST_CALBK | G31: 0.069 | H31: FORACID, PYMT_REF_NUM | I31: pymt_ref_num | J31: N | K31: LCHG_TIME | L31: CRM_DEV.finacle.CUSTOM_CUST_CALBK | M31: DONE | N31: DONE | O31: NA
A32: Milestone 3 | B32: N | C32: Finacle | D32: CUSTOM | E32: FINUAT | F32: C_PORDM_DELETE | G32: 0.034 | H32: PYMT_REF_NUM | J32: N | K32: Its a custom table and dependent on PROD/PORH table, mapping field pymt_ref_num | L32: CRM_DEV.finacle.CUSTOM_C_PORDM_DELETE | M32: DONE | N32: DONE | O32: NA
A33: Milestone 4 | B33: N | C33: Finacle | D33: CUSTOM | E33: FINUAT | F33: C_CPARAM_VALUE_TABLE | G33: 0.004 | H33: PARAMETER_ID, LEVELCODE_1, LEVELCODE_2, MODULE_NAME | I33: PARAMETER_ID, LEVELCODE_1, LEVELCODE_2, MODULE_NAME, BANK_ID | J33: N | K33: LCHG_TIME | L33: CRM_DEV.finacle.CUSTOM_C_CPARAM_VALUE_TABLE | M33: DONE | N33: DONE | O33: NA
A34: Milestone 4 | B34: N | C34: Finacle | D34: CUSTOM | E34: FINUAT | F34: C_CHQ_REJ_DET | G34: 0.169 | H34: ACID, INSTRMNT_TYPE, INSTRMNT_NUM, INSTRMNT_ALPHA, REJECTED_DATE, ACID | J34: N | K34: LCHG_TIME | L34: CRM_DEV.finacle.CUSTOM_C_CHQ_REJ_DET | M34: DONE | N34: DONE | O34: NA
A35: TBD | B35: N | C35: Finacle | D35: CUSTOM | E35: FINUAT | F35: C_LNM_DETAIL_TBL_MOD | G35: 0 | H35: REF_NUM, LIMIT_PREFIX, LIMIT_SUFFIX, LIST_FUNC | J35: N | K35: LCHG_TIME | L35: CRM_DEV.finacle.CUSTOM_C_LNM_DETAIL_TBL_MOD | M35: DONE | N35: DONE | O35: NA
A36: TBD | B36: N | C36: Finacle | D36: CUSTOM | E36: FINUAT | F36: CUST_CBDSME_DOCDET_TABLE | G36: 0.061 | H36: LIMIT_B2KID,DOC_SRL_NUM,BANK_ID | I36: DOC_SRL_NUM | J36: N | K36: LCHG_TIME | M36: Not Done | N36: Not Done | O36: NA
A37: TBD | B37: N | C37: Finacle | D37: CUSTOM | E37: FINUAT | F37: CUST_CASA_HISTDTL | G37: 0.002 | H37: ACCOUNT_NUMBER, BANK_ID | I37: CIF_ID | J37: N | K37: LCHG_TIME | M37: Not Done | N37: Not Done | O37: NA
A38: TBD | B38: N | C38: Finacle | D38: CUSTOM | E38: FINUAT | F38: CUST_CASA_PACKAGE | G38: 0 | H38: PACKAGE_TYPE, PROD_PROCESSOR | I38: Event_ID, Package_ID | J38: N | K38: LCHG_TIME | M38: Not Done | N38: Not Done | O38: NA
A39: TBD | B39: N | C39: Finacle | D39: CUSTOM | E39: FINUAT | F39: CUST_CASA_PACKAGE_CHRG | G39: 0.011 | H39: FORACID,EVENT_ID | I39: CIF_ID,Event_ID | J39: N | K39: LCHG_TIME | M39: Not Done | N39: Not Done | O39: NA
A40: TBD | B40: N | C40: Finacle | D40: CUSTOM | E40: FINUAT | F40: CUST_CASA_PACKAGE_MAIN | G40: 0.002 | H40: FORACID, CIF_ID | I40: CIF_ID | J40: N | K40: LCHG_TIME | M40: Not Done | N40: Not Done | O40: NA
A41: TBD | B41: N | C41: Finacle | D41: CUSTOM | E41: FINUAT | F41: CUST_CASA_PACKAGE_CHRG_HIS | G41: 0.059 | H41: FORACID, EVENT_ID | J41: N | K41: LCHG_TIME | M41: Not Done | N41: Not Done | O41: NA
A42: TBD | B42: N | C42: Finacle | D42: CUSTOM | E42: FINUAT | F42: TBA_COLTRL_GURNT_DTL_TBL | H42: SECU_LINKAGE_TYPE, ACID, LIMIT_B2KID, SECU_SRL_NUM | J42: N | K42: LCHG_TIME | M42: Not Done | N42: Not Done | O42: NA
A43: Milestone 3 | B43: N | C43: Finacle | D43: DEDUPADM | E43: FINUAT | F43: OPERATIONSREASONCODES_DEDUP | G43: 0.381 | H43: REASONCODEID, BANK_ID, BLACKLISTDATASETID, NEGATIVELISTDATASETID | I43: reasoncodeid | J43: N | K43: STARTDATE | L43: CRM_DEV.finacle.DEDUPADM_OPERATIONSREASONCODES_DEDUP | M43: DONE | N43: DONE | O43: NA
A44: TBD | B44: N | C44: Finacle | D44: SVSUSER | E44: FINUAT | F44: SIGNMAINTANENCE | H44: SIGNID | J44: N | K44: Valid table name - SIGNMAINTENANCE, CREATEDDATE(Newly created record) or MODIFIEDDATE(Last Modified record) | M44: Not Done | N44: Not Done | O44: NA
A45: Milestone 2 | B45: N | C45: Finacle | D45: TBAADM | E45: FINUAT | F45: ENTITY_INTEREST_TABLE | G45: 1.321 | H45: ENTITY_ID, ENTITY_TYPE, BANK_ID | I45: ENTITY_ID | J45: N | K45: LCHG_TIME | L45: CRM_DEV.finacle.TBAADM_ENTITY_INTEREST_TABLE | M45: DONE | N45: DONE | O45: NA
A46: Milestone 2 | B46: N | C46: Finacle | D46: TBAADM | E46: FINUAT | F46: GENERAL_ACCT_MAST_TABLE | G46: 2.819 | H46: CIF_ID,CUST_ID,FORACID,POOL_ID,SCHM_CODE, SOL_ID,ACCT_SHORT_NAME, SOL_ID,IBAN_NUMBE,LIMIT_B2KID | I46: ACID | J46: N | K46: LCHG_TIME | L46: CRM_DEV.finacle.TBAADM_GENERAL_ACCT_MAST_TABLE | M46: DONE | N46: DONE | O46: NA
A47: Milestone 2 | B47: N | C47: Finacle | D47: TBAADM | E47: FINUAT | F47: SBCA_MAST_TABLE | G47: 0.056 | H47: ACID, BANK_ID | I47: ACID | J47: N | K47: LCHG_TIME | L47: CRM_DEV.finacle.TBAADM_SBCA_MAST_TABLE | M47: DONE | N47: DONE | O47: NA
A48: Milestone 2 | B48: N | C48: Finacle | D48: TBAADM | E48: FINUAT | F48: TD_ACCT_MASTER_TABLE | G48: 0.063 | H48: LINK_OPER_ACCOUNT,RELATED_ACID,MASTER_B2K_ID,REPAYMENT_ACID,ACID, BANK_ID,SOL_ID, MATURITY_DATE | I48: ACID | J48: N | K48: LCHG_TIME | L48: CRM_DEV.finacle.TBAADM_TD_ACCT_MASTER_TABLE | M48: DONE | N48: DONE | O48: NA
A49: Milestone 3 | B49: N | C49: Finacle | D49: TBAADM | E49: FINUAT | F49: ACCT_AUTH_SIGN_TABLE | G49: 0.728 | H49: NMA_KEY_ID, CUST_ID, STMT_CUST_ID | I49: ACID,NMA_KEY_ID | J49: N | K49: LCHG_TIME | L49: CRM_DEV.finacle.TBAADM_ACCT_AUTH_SIGN_TABLE | M49: DONE | N49: DONE | O49: NA
A50: Milestone 3 | B50: N | C50: Finacle | D50: TBAADM | E50: FINUAT | F50: ACH_PAYSYS_REASON_TABLE | G50: 0 | H50: PAYSYS_ID, REASON_ID, BANK_ID | J50: N | K50: LCHG_TIME | L50: CRM_DEV.finacle.TBAADM_ACH_PAYSYS_REASON_TABLE | M50: DONE | N50: DONE | O50: NA
A51: Milestone 3 | B51: N | C51: Finacle | D51: TBAADM | E51: FINUAT | F51: ACCT_STATEMENT_TABLE | G51: 0.179 | H51: ACID, BANK_ID | I51: ACID | J51: N | K51: LCHG_TIME | L51: CRM_DEV.finacle.TBAADM_ACCT_STATEMENT_TABLE | M51: DONE | N51: DONE | O51: NA
A52: Milestone 3 | B52: N | C52: Finacle | D52: TBAADM | E52: FINUAT | F52: CMB_CSIS_GEN_ACCT_TABLE | G52: 0 | H52: SOL_ID, CUST_ID, POOL_ID | K52: This is CSIS table and not used in RAK | L52: CRM_DEV.finacle.TBAADM_CMB_CSIS_GEN_ACCT_TABLE | M52: DONE | N52: DONE | O52: NA
A53: Milestone 3 | B53: N | C53: Finacle | D53: TBAADM | E53: FINUAT | F53: DAILY_TRAN_DETAIL_TABLE | G53: 1.53 | H53: SOL_ID, TRAN_CRNCY_CODE, GL_SUB_HEAD_CODE, SI_SRL_NUM, ACID | I53: ACID,TRAN_ID, PART_TRAN_SRL_NUM | J53: Y | K53: TRAN_DATE | L53: CRM_DEV.finacle.TBAADM_DAILY_TRAN_DETAIL_TABLE | M53: DONE | N53: DONE | O53: NA
A54: Milestone 3 | B54: N | C54: Finacle | D54: TBAADM | E54: FINUAT | F54: GEN_ACCT_MAST_MOD_TABLE | G54: 0.005 | H54: ACID, BANK_ID | J54: N | K54: LCHG_TIME | L54: CRM_DEV.finacle.TBAADM_GEN_ACCT_MAST_MOD_TABLE | M54: DONE | N54: DONE | O54: NA
A55: Milestone 3 | B55: N | C55: Finacle | D55: TBAADM | E55: FINUAT | F55: GEN_ACCT_CLASS_TABLE | G55: 0.537 | H55: INT_CR_ACID, INT_DR_ACID, ACID, BANK_ID | I55: ACID | J55: N | K55: LCHG_TIME | L55: CRM_DEV.finacle.TBAADM_GEN_ACCT_CLASS_TABLE | M55: DONE | N55: DONE | O55: NA
A56: Milestone 3 | B56: N | C56: Finacle | D56: TBAADM | E56: FINUAT | F56: SOL_GROUP_CONTROL_TABLE | G56: 0 | H56: SOL_GROUP_ID, BANK_ID | J56: N | K56: LCHG_TIME | L56: CRM_DEV.finacle.TBAADM_SOL_GROUP_CONTROL_TABLE | M56: DONE | N56: DONE | O56: NA
A57: Milestone 3 | B57: N | C57: Finacle | D57: TBAADM | E57: FINUAT | F57: GEN_SCHM_PARM_TABLE | G57: 0.001 | H57: SCHM_TYPE, SCHM_CODE, BANK_ID | I57: SCHM_CODE, BANK_ID | J57: N | K57: LCHG_TIME | L57: CRM_DEV.finacle.TBAADM_GEN_SCHM_PARM_TABLE | M57: DONE | N57: DONE | O57: NA
A58: Milestone 3 | B58: N | C58: Finacle | D58: TBAADM | E58: FINUAT | F58: LOGIN_TABLE | G58: 0.061 | H58: USER_ID, ROLE_ID, SESSION_ID | I58: Session_ID | K58: Its a user login table | L58: CRM_DEV.finacle.TBAADM_LOGIN_TABLE | M58: DONE | N58: DONE | O58: NA
A59: Milestone 3 | B59: N | C59: Finacle | D59: TBAADM | E59: FINUAT | F59: ML_MMSG_TBL | G59: 0.018 | H59: MSG_LITERAL, SOURCE_TYPE, MSG_ID | I59: MSG_ID | K59: Its a message configuration table, it does not have date field | L59: CRM_DEV.finacle.TBAADM_ML_MMSG_TBL | M59: DONE | N59: DONE | O59: NA
A60: Milestone 3 | B60: N | C60: Finacle | D60: TBAADM | E60: FINUAT | F60: MEMO_PAD_TABLE | G60: 0.265 | H60: ACID, MP_INTENT, MP_FUNC,KEY_WORD, TRAN_DATE, TRAN_ID, PART_TRAN_SRL_NUM | I60: MP_SRL_NUM | J60: N | K60: LCHG_TIME | L60: CRM_DEV.finacle.TBAADM_MEMO_PAD_TABLE | M60: DONE | N60: DONE | O60: NA
A61: Milestone 3 | B61: N | C61: Finacle | D61: TBAADM | E61: FINUAT | F61: NAME_AND_ADD_TABLE | G61: 0.078 | H61: ADDR_B2KID, ADDR_ID, BANK_ID | I61: ADDR_B2KID | J61: N | K61: LCHG_TIME | L61: CRM_DEV.finacle.TBAADM_NAME_AND_ADD_TABLE | M61: DONE | N61: DONE | O61: NA
A62: Milestone 3 | B62: N | C62: Finacle | D62: TBAADM | E62: FINUAT | F62: PAYMENT_ORDER_DETAIL_TABLE | G62: 56.279 | H62: TRAN_REF_NUM, SENDER_CHANNEL, BANK_ID | I62: PYMT_REF_NUM | J62: N | K62: LCHG_TIME | L62: CRM_DEV.finacle.TBAADM_PAYMENT_ORDER_DETAIL_TABLE | M62: DONE | N62: DONE | O62: NA
A63: Milestone 3 | B63: N | C63: Finacle | D63: TBAADM | E63: FINUAT | F63: PAYMENT_ORDER_HEADER_TABLE | G63: 40.821 | H63: REQ_EXEC_DATE, DR_ACCT, TRAN_DATE, TRAN_ID | I63: PYMT_REF_NUM | J63: N | K63: LCHG_TIME | L63: CRM_DEV.finacle.TBAADM_PAYMENT_ORDER_HEADER_TABLE | M63: DONE | N63: DONE | O63: NA
A64: Milestone 3 | B64: N | C64: Finacle | D64: TBAADM | E64: FINUAT | F64: SWIFT_MSG_HISTORY_TABLE | G64: 104.608 | H64: TRAN_ID, PTRAN_SRL_NUM, TRAN_DATE | I64: SW_SRL_NUM | J64: N | K64: LCHG_TIME | L64: CRM_DEV.finacle.TBAADM_SWIFT_MSG_HISTORY_TABLE | M64: DONE | N64: DONE | O64: NA
A65: Milestone 1 | B65: N | C65: PRIME | D65: TCTDBS | E65: PRIMEDB | F65: CARDX | G65: 2.186 | H65: SERNO | I65: SERNO | L65: CRM_DEV.prime4.TCTDBS_CARDX | M65: DONE | N65: DONE | O65: NA
A66: Milestone 1 | B66: N | C66: PRIME | D66: TCTDBS | E66: PRIMEDB | F66: PEOPLE | G66: 1.489 | H66: SERNO | I66: SERNO | L66: CRM_DEV.prime4.TCTDBS_PEOPLE | M66: DONE | N66: DONE | O66: NA
A67: Milestone 2 | B67: N | C67: PRIME | D67: TCTDBS | E67: PRIMEDB | F67: CARDEMBOSSING | G67: 0.791 | H67: SERNO | I67: SERNO | L67: CRM_DEV.prime4.TCTDBS_CARDEMBOSSING | M67: DONE | N67: DONE | O67: NA
A68: Milestone 2 | B68: N | C68: PRIME | D68: TCTDBS | E68: PRIMEDB | F68: CACCOUNTS | G68: 3.547 | H68: SERNO | I68: SERNO | L68: CRM_DEV.prime4.TCTDBS_CACCOUNTS | M68: DONE | N68: DONE | O68: NA
A69: Milestone 2 | B69: N | C69: PRIME | D69: TCTDBS | E69: PRIMEDB | F69: CURRENCIES | G69: 0 | H69: SERNO | L69: CRM_DEV.prime4.TCTDBS_CURRENCIES | M69: DONE | N69: DONE | O69: NA
A70: Milestone 2 | B70: N | C70: PRIME | D70: TCTDBS | E70: PRIMEDB | F70: PRODUCTS | G70: 0.001 | H70: SERNO | I70: PRODUCTID,BANK_ID | L70: CRM_DEV.prime4.TCTDBS_PRODUCTS | M70: DONE | N70: DONE | O70: NA
A71: Milestone 2 | B71: N | C71: ONLINE | D71: TCTDBS | E71: OnlineDB | F71: CARDSTATUS | L71: CRM_DEV.online.TCTDBS_CARDSTATUS | M71: DONE | N71: Not Done | O71: NA
A72: Milestone 2 | B72: N | C72: PRIME | D72: TCTDBS | E72: PRIMEDB | F72: CSTATEMENTS | G72: 15.944 | H72: SERNO, PARTITIONKEY | I72: SERNO | L72: CRM_DEV.prime4.TCTDBS_CSTATEMENTS | M72: DONE | N72: DONE | O72: NA
A73: Milestone 2 | B73: N | C73: ONLINE | D73: TCTDBS | E73: OnlineDB | F73: AUTHORIZATIONS | I73: SERNO | L73: CRM_DEV.online.TCTDBS_AUTHORIZATIONS | M73: DONE | N73: Not Done | O73: NA
A74: Milestone 2 | B74: N | C74: PRIME | D74: TCTDBS | E74: PRIMEDB | F74: tbalances | G74: 118.532 | H74: SERNO, PARTITIONKEY | I74: SERNO | L74: CRM_DEV.prime4.TCTDBS_TBALANCES | M74: DONE | N74: DONE | O74: NA
A75: Milestone 3 | B75: N | C75: PRIME | D75: TCTDBS | E75: PRIMEDB | F75: CINSTALMENTS | G75: 1.11 | I75: SERNO | L75: CRM_DEV.prime4.TCTDBS_CINSTALMENTS | M75: DONE | N75: DONE | O75: NA
A76: Milestone 3 | B76: N | C76: PRIME | D76: TCTDBS | E76: PRIMEDB | F76: Cinstalmentamortization | G76: 6.676 | I76: SERNO | L76: CRM_DEV.prime4.TCTDBS_CINSTALMENTAMORTIZATION | M76: DONE | N76: DONE | O76: NA
A77: Milestone 3 | B77: N | C77: PRIME | D77: TCTDBS | E77: PRIMEDB | F77: ACPLINKS | G77: 0.138 | I77: SERNO | L77: CRM_DEV.prime4.TCTDBS_ACPLINKS | M77: DONE | N77: DONE | O77: NA
A78: Milestone 3 | B78: N | C78: PRIME | D78: TCTDBS | E78: PRIMEDB | F78: ACPROFILES | G78: 0 | I78: SERNO | L78: CRM_DEV.prime4.TCTDBS_ACPROFILES | M78: DONE | N78: DONE | O78: NA
A79: Milestone 3 | B79: N | C79: PRIME | D79: TCTDBS | E79: PRIMEDB | F79: APPLOG | G79: 177.805 | I79: EODSERNO,TABNAME,COLNAME,ROWSERNO | L79: CRM_DEV.prime4.TCTDBS_APPLOG | M79: DONE | N79: DONE | O79: NA
A80: Milestone 3 | B80: N | C80: PRIME | D80: TCTDBS | E80: PRIMEDB | F80: BATCHES | G80: 6.158 | L80: CRM_DEV.prime4.TCTDBS_BATCHES | M80: DONE | N80: DONE | O80: NA
A81: Milestone 3 | B81: N | C81: PRIME | D81: TCTDBS | E81: PRIMEDB | F81: CACCOUNTSTMT | G81: 0.955 | I81: SERNO | L81: CRM_DEV.prime4.TCTDBS_CACCOUNTSTMT | M81: DONE | N81: DONE | O81: NA
A82: Milestone 3 | B82: N | C82: PRIME | D82: TCTDBS | E82: PRIMEDB | F82: CADDRESSES | G82: 1.879 | I82: SERNO | L82: CRM_DEV.prime4.TCTDBS_CADDRESSES | M82: DONE | N82: DONE | O82: NA
A83: Milestone 3 | B83: N | C83: ONLINE | D83: TCTDBS | E83: OnlineDB | F83: CARDS | I83: CRNNO | L83: CRM_DEV.online.TCTDBS_CARDS | M83: DONE | N83: Not Done | O83: NA
A84: Milestone 3 | B84: N | C84: PRIME | D84: TCTDBS | E84: PRIMEDB | F84: CCUSTOMERS | G84: 0.612 | I84: SERNO | L84: CRM_DEV.prime4.TCTDBS_CCUSTOMERS | M84: DONE | N84: DONE | O84: NA
A85: Milestone 3 | B85: N | C85: PRIME | D85: TCTDBS | E85: PRIMEDB | F85: CEXTENSION | G85: 17.05 | I85: FIELDNO,ROWSERNO,TABINDICATOR | L85: CRM_DEV.prime4.TCTDBS_CEXTENSION | M85: DONE | N85: DONE | O85: NA
A86: Milestone 3 | B86: N | C86: PRIME | D86: TCTDBS | E86: PRIMEDB | F86: CISOTRXNS | G86: 69.469 | I86: SERNO | L86: CRM_DEV.prime4.TCTDBS_CISOTRXNS | M86: DONE | N86: DONE | O86: NA
A87: Milestone 3 | B87: N | C87: PRIME | D87: TCTDBS | E87: PRIMEDB | F87: CTRANSACTIONS | G87: 120.597 | I87: SERNO | L87: CRM_DEV.prime4.TCTDBS_CTRANSACTIONS | M87: DONE | N87: DONE | O87: NA
A88: Milestone 3 | B88: N | C88: PRIME | D88: TCTDBS | E88: PRIMEDB | F88: TRXNSTATUS | G88: 0 | I88: PSERNO | L88: CRM_DEV.prime4.TCTDBS_TRXNSTATUS | M88: DONE | N88: DONE | O88: NA
